Workbook

Sheet Leeme
A1: Codificación de obligaciones de registro en el alta bancaria digital
A2: María Fernanda Sánchez Villa · Ensayo para el Premio Federico Prades 2026 · Base de datos del componente A de la metodología
A4: Qué contiene
A5: Cada fila de "Codificacion" codifica una obligación concreta relacionada con el alta de un cliente persona física. No todas las obligaciones crean por sí mismas un registro del estado: esa diferencia se explicita en "Auditoria_ECG0".
A6: Total: 176 obligaciones de 17 instrumentos codificados, agrupados en 9 familias normativas. Se añaden actos de apoyo para verificar modificaciones y fechas de aplicación.
A8: Hojas
A9: Libro_codigos: campos, definiciones y valores cerrados admitidos, y la taxonomía de estados E0 a E9.
A10: Codificacion: base principal. Las columnas S a AC marcan con 1 los estados a los que se refiere cada obligación (calculadas por fórmula).
A11: Resumen: recuentos por familia, tipo, finalidad y cobertura de solicitudes no culminadas, y la matriz de solapamiento por dato.
A12: Mapa_visibilidad: recuento descriptivo original por estados y familias. "Mapa_ECG0" ofrece la lectura cualitativa E/C/G/0 más conservadora.
A13: Fiabilidad: muestra aleatoria del 20 % para la recodificación ciega y el cálculo del porcentaje de acuerdo.
A14: Fuentes: instrumentos codificados, enlaces y situación temporal. "Auditoria_ECG0" añade trigger, aplicabilidad al corte y límites de reutilización.
... A35: Mapa_ensayo: recuento por estados y motivos de la taxonomía del ensayo (S0-S6, R01-R11). Mapa_ECG0_ensayo: lectura E/C/G/0 en esos mismos códigos (Figura 5 del ensayo).

Sheet Libro_codigos
A1: Campo | B1: Definición | C1: Valores admitidos | F1: nivel | G1: tipo | H1: dato | I1: finalidad | J1: destinatario | K1: ambito | L1: cubre_no_culminado | M1: confianza
A2: id | B2: Identificador único: prefijo de norma y número correlativo | C2: PAD-, ES-PAD-, ES-TR-, AMLR-, ES-AML-, EBA-RO-, EBA-DR-, GDPR-, AIA-, DORA-, EIDAS-, ES-EAA- | F2: UE_reglamento | G2: Registrar | H2: Identidad | I2: Diligencia_debida_AML | J2: Interesado | K2: Todas_entidades_obligadas | L2: Si | M2: Alta
A3: familia | B3: Agrupación normativa usada en el mapa de visibilidad | C3: Cuenta básica, AML, Directrices EBA, RGPD, AI Act, DORA, eIDAS 2, Accesibilidad, Atención al cliente ES | F3: UE_directiva | G3: Conservar | H3: Documento_identidad | I3: Prevencion_fraude | J3: Autoridad_AML | K3: Cuenta_pago_basica | L3: Parcial | M3: Media
A4: norma | B4: Instrumento normativo (nombre corto) | C4: Texto libre | F4: ES_ley | G4: Comunicar_autoridad | H4: Resultado_verificacion | I4: Transparencia_consumidor | J4: Banco_de_Espana | K4: Sistemas_IA_alto_riesgo | L4: No
A5: articulo | B5: Artículo y apartado exactos (o párrafo, en directrices EBA) | C5: Texto libre | F5: ES_reglamento | G5: Informar_interesado | H5: Motivo_decision | I5: Acceso_inclusion | J5: Autoridad_proteccion_datos | K5: Responsable_tratamiento
A6: nivel | B6: Rango del instrumento | C6: UE_reglamento, UE_directiva, ES_ley, ES_reglamento, Soft_law_EBA | F6: Soft_law_EBA | G6: Motivar | H6: Logs_sistema | I6: Proteccion_datos | J6: Autoridad_vigilancia_IA | K6: Entidades_financieras_DORA
A7: vigencia | B7: Situación temporal de aplicación o transición | C7: Vigente | Aplicable_desde_AAAA-MM-DD | En_vigor_AAAA-MM-DD_adaptacion_hasta_AAAA-MM-DD | G7: Evaluar_riesgo | H7: Informacion_tratamiento | I7: Trazabilidad_IA | J7: Uso_interno
A8: tipo | B8: Qué exige la obligación | C8: Registrar, Conservar, Comunicar_autoridad, Informar_interesado, Motivar, Evaluar_riesgo, Supervision_humana, Notificar_incidente, Abstenerse | G8: Supervision_humana | H8: Evaluacion_riesgo | I8: Resiliencia_operativa | J8: Varios
A9: estado | B9: Estados de la taxonomía a los que se refiere (varios, orden ascendente, separados por "; ") | C9: E0 a E9, TR (ver tabla inferior) | G9: Notificar_incidente | H9: Intervencion_humana | I9: Reclamaciones
A10: dato | B10: Categoría de dato o evidencia exigida | C10: Identidad, Documento_identidad, Resultado_verificacion, Motivo_decision, Logs_sistema, Informacion_tratamiento, Evaluacion_riesgo, Intervencion_humana, Incidente_TIC, Proveedor_tercero, Expediente_completo | G10: Abstenerse | H10: Incidente_TIC
A11: finalidad | B11: Para qué se exige | C11: Diligencia_debida_AML, Prevencion_fraude, Transparencia_consumidor, Acceso_inclusion, Proteccion_datos, Trazabilidad_IA, Resiliencia_operativa, Reclamaciones | H11: Proveedor_tercero
A12: plazo | B12: Plazo de conservación o de actuación, literal breve | C12: "5 años", "10 años", "Mínimo 6 meses", "No especificado" u otro literal | H12: Expediente_completo
A13: destinatario | B13: Quién recibe o puede recibir la evidencia | C13: Interesado, Autoridad_AML, Banco_de_Espana, Autoridad_proteccion_datos, Autoridad_vigilancia_IA, Uso_interno, Varios
A14: ambito | B14: A quién se aplica | C14: Todas_entidades_obligadas, Cuenta_pago_basica, Sistemas_IA_alto_riesgo, Responsable_tratamiento, Entidades_financieras_DORA
A15: cubre_no_culminado | B15: ¿Alcanza, aunque sea en parte, a solicitudes que no terminan en alta? | C15: Si, Parcial, No
A16: cita | B16: Cita literal breve (máx. 35 palabras) del texto oficial en español | C16: Texto literal; "(...)" indica recorte
A17: url | B17: Enlace al texto oficial | C17: EUR-Lex, BOE, EBA
A18: confianza | B18: Alta: verificado en el texto oficial. Media: pendiente de verificar | C18: Alta, Media
A19: notas | B19: Aclaraciones de codificación | C19: Texto libre
A21: Taxonomía de estados
A22: Código | B22: Estado | C22: ¿Culmina?
A23: E0 | B23: Iniciado | C23: En curso
A24: E1 | B24: Abandono temprano | C24: No
A25: E2 | B25: Fallo técnico | C25: No
A26: E3 | B26: Documento no admitido | C26: No
A27: E4 | B27: Diligencia debida incompleta | C27: No
A28: E5 | B28: En revisión manual | C28: En curso
A29: E6 | B29: Revisión sin resolución | C29: No
A30: E7 | B30: Desistimiento tras requerimiento | C30: No
A31: E8 | B31: Denegación formal | C31: No
A32: E9 | B32: Alta completada | C32: Sí
A33: TR | B33: Transversal | C33: No aplica
A35: Visibilidad E/C/G/0
A36: Código | B36: Definición | C36: Regla de uso
A37: E | B37: Evidencia directa | C37: La obligación exige documentar, registrar, conservar, motivar o comunicar de forma verificable el evento/estado codificado.
A38: C | B38: Cobertura condicional o indirecta | C38: El estado solo queda visible si se activa un supuesto adicional (p. ej., sospecha AML, incidente TIC, reclamación o IA de alto riesgo).
A39: G | B39: Gobernanza del dato/proceso | C39: La norma gobierna datos, finalidad, minimización, seguridad o proceso asociado, pero no exige registrar ese estado de onboarding como tal.
A40: 0 | B40: No identificado | C40: En las fuentes revisadas no se identifica una obligación específica que haga visible ese estado.
A41: Nota | B41: No equivale a duplicidad | C41: Solapamiento semántico o probatorio no demuestra duplicidad operativa ni duplicidad regulatoria.

Sheet Codificacion
A1: id | B1: familia | C1: norma | D1: articulo | E1: nivel | F1: vigencia | G1: tipo | H1: estado | I1: dato | J1: finalidad | K1: plazo | L1: destinatario | M1: ambito | N1: cubre_no_culminado | O1: cita | P1: url | Q1: confianza | R1: notas | S1: E0 | T1: E1 | U1: E2 | V1: E3 | W1: E4 | X1: E5 | Y1: E6 | Z1: E7 | AA1: E8 | AB1: E9 | AC1: TR | AD1: codigos_ensayo | AE1: S0 | AF1: R01 | AG1: R02/R03 | AH1: R04 | AI1: R05 | AJ1: S3/R06 | AK1: R07 | AL1: R09 | AM1: R10 | AN1: S5 | AO1: S6 | AP1: TR
A2: PAD-01 | B2: Cuenta básica | C2: Directiva 2014/92/UE (PAD) | D2: art. 15 | E2: UE_directiva | F2: Vigente | G2: Abstenerse | H2: TR | I2: Identidad | J2: Acceso_inclusion | K2: No especificado | L2: Interesado | M2: Cuenta_pago_basica | N2: Si | O2: los proveedores de servicios de pago no discriminen a los consumidores que residan legalmente en la Unión por razón de nacionalidad o lugar de residencia (...) cuando soliciten o accedan a una cuenta de pago | P2: https://eur-lex.europa.eu/legal-content/ES/TXT/HTML/?uri=CELEX:32014L0092 | Q2: Alta | R2: Se aplica a cualquier cuenta de pago, no solo CPB. Corregida la cita: el sujeto es «proveedores de servicios de pago» (no solo entidades de crédito); incluye cualquier otra razón del art. 21 de la Carta. Verificado en el texto ES de EUR-Lex. Obligación dirigida a los Estados miembros ('velarán por que'), exigible a las entidades a través de la transposición (RDL 19/2017). | S2: =IF(ISNUMBER(SEARCH("E0",$H2)),1,0) -> 0 | T2: =IF(ISNUMBER(SEARCH("E1",$H2)),1,0) -> 0 | U2: =IF(ISNUMBER(SEARCH("E2",$H2)),1,0) -> 0 | V2: =IF(ISNUMBER(SEARCH("E3",$H2)),1,0) -> 0 | W2: =IF(ISNUMBER(SEARCH("E4",$H2)),1,0) -> 0 | X2: =IF(ISNUMBER(SEARCH("E5",$H2)),1,0) -> 0 | Y2: =IF(ISNUMBER(SEARCH("E6",$H2)),1,0) -> 0 | Z2: =IF(ISNUMBER(SEARCH("E7",$H2)),1,0) -> 0 | AA2: =IF(ISNUMBER(SEARCH("E8",$H2)),1,0) -> 0 | AB2: =IF(ISNUMBER(SEARCH("E9",$H2)),1,0) -> 0 | AC2: =IF(ISNUMBER(SEARCH("TR",$H2)),1,0) -> 1 | AD2: TR | AE2: =IF(ISNUMBER(SEARCH("S0",$AD2)),1,0) -> 0 | AF2: =IF(ISNUMBER(SEARCH("R01",$AD2)),1,0) -> 0 | AG2: =IF(ISNUMBER(SEARCH("R02R03",$AD2)),1,0) -> 0 | AH2: =IF(ISNUMBER(SEARCH("R04",$AD2)),1,0) -> 0 | AI2: =IF(ISNUMBER(SEARCH("R05",$AD2)),1,0) -> 0 | AJ2: =IF(ISNUMBER(SEARCH("S3R06",$AD2)),1,0) -> 0 | AK2: =IF(ISNUMBER(SEARCH("R07",$AD2)),1,0) -> 0 | AL2: =IF(ISNUMBER(SEARCH("R09",$AD2)),1,0) -> 0 | AM2: =IF(ISNUMBER(SEARCH("R10",$AD2)),1,0) -> 0 | AN2: =IF(ISNUMBER(SEARCH("S5",$AD2)),1,0) -> 0 | AO2: =IF(ISNUMBER(SEARCH("S6",$AD2)),1,0) -> 0 | AP2: =IF(ISNUMBER(SEARCH("TR",$AD2)),1,0) -> 1
A3: PAD-02 | B3: Cuenta básica | C3: Directiva 2014/92/UE (PAD) | D3: art. 16.3 | E3: UE_directiva | F3: Vigente | G3: Informar_interesado | H3: E8; E9 | I3: Motivo_decision | J3: Acceso_inclusion | K3: 10 días hábiles desde la recepción de una solicitud completa | L3: Interesado | M3: Cuenta_pago_basica | N3: Si | O3: rechacen las solicitudes de acceso (...) sin demora injustificada y, a más tardar en un plazo de diez días hábiles a partir de la recepción de una solicitud completa. | P3: https://eur-lex.europa.eu/legal-content/ES/TXT/HTML/?uri=CELEX:32014L0092 | Q3: Alta | R3: Obligación de resolver (abrir o denegar) en plazo; el tipo es aproximado. El RDL 19/2017 solo transpone expresamente el plazo para la denegación (art. 5.2). Ojo: la versión ES dice literalmente «rechacen» (la versión inglesa dice tramitar, abrir o rechazar); probable defecto de traducción, la corrección de errores 32014L0092R(01) no tiene versión ES en EUR-Lex y la R(02) no la he comprobado. Verificado en el texto ES de EUR-Lex. Obligación dirigida a los Estados miembros ('velarán por que'), exigible a las entidades a través de la transposición (RDL 19/2017). | S3: =IF(ISNUMBER(SEARCH("E0",$H3)),1,0) -> 0 | T3: =IF(ISNUMBER(SEARCH("E1",$H3)),1,0) -> 0 | U3: =IF(ISNUMBER(SEARCH("E2",$H3)),1,0) -> 0 | V3: =IF(ISNUMBER(SEARCH("E3",$H3)),1,0) -> 0 | W3: =IF(ISNUMBER(SEARCH("E4",$H3)),1,0) -> 0 | X3: =IF(ISNUMBER(SEARCH("E5",$H3)),1,0) -> 0 | Y3: =IF(ISNUMBER(SEARCH("E6",$H3)),1,0) -> 0 | Z3: =IF(ISNUMBER(SEARCH("E7",$H3)),1,0) -> 0 | AA3: =IF(ISNUMBER(SEARCH("E8",$H3)),1,0) -> 1 | AB3: =IF(ISNUMBER(SEARCH("E9",$H3)),1,0) -> 1 | AC3: =IF(ISNUMBER(SEARCH("TR",$H3)),1,0) -> 0 | AD3: S5; S6 | AE3: =IF(ISNUMBER(SEARCH("S0",$AD3)),1,0) -> 0 | AF3: =IF(ISNUMBER(SEARCH("R01",$AD3)),1,0) -> 0 | AG3: =IF(ISNUMBER(SEARCH("R02R03",$AD3)),1,0) -> 0 | AH3: =IF(ISNUMBER(SEARCH("R04",$AD3)),1,0) -> 0 | AI3: =IF(ISNUMBER(SEARCH("R05",$AD3)),1,0) -> 0 | AJ3: =IF(ISNUMBER(SEARCH("S3R06",$AD3)),1,0) -> 0 | AK3: =IF(ISNUMBER(SEARCH("R07",$AD3)),1,0) -> 0 | AL3: =IF(ISNUMBER(SEARCH("R09",$AD3)),1,0) -> 0 | AM3: =IF(ISNUMBER(SEARCH("R10",$AD3)),1,0) -> 0 | AN3: =IF(ISNUMBER(SEARCH("S5",$AD3)),1,0) -> 1 | AO3: =IF(ISNUMBER(SEARCH("S6",$AD3)),1,0) -> 1 | AP3: =IF(ISNUMBER(SEARCH("TR",$AD3)),1,0) -> 0
A4: PAD-03 | B4: Cuenta básica | C4: Directiva 2014/92/UE (PAD) | D4: art. 16.4 | E4: UE_directiva | F4: Vigente | G4: Abstenerse | H4: E4; E8 | I4: Resultado_verificacion | J4: Diligencia_debida_AML | K4: No especificado | L4: Interesado | M4: Cuenta_pago_basica | N4: Si | O4: las entidades de crédito rechacen las solicitudes de acceso a cuentas de pago básicas siempre que la apertura de una de tales cuentas vulnere las disposiciones relativas a la prevención del blanqueo de capitales | P4: https://eur-lex.europa.eu/legal-content/ES/TXT/HTML/?uri=CELEX:32014L0092 | Q4: Alta | R4: Remite a la Directiva 2005/60/CE (hoy marco AMLR/AMLD). Verificado en el texto ES de EUR-Lex. Obligación dirigida a los Estados miembros ('velarán por que'), exigible a las entidades a través de la transposición (RDL 19/2017). | S4: =IF(ISNUMBER(SEARCH("E0",$H4)),1,0) -> 0 | T4: =IF(ISNUMBER(SEARCH("E1",$H4)),1,0) -> 0 | U4: =IF(ISNUMBER(SEARCH("E2",$H4)),1,0) -> 0 | V4: =IF(ISNUMBER(SEARCH("E3",$H4)),1,0) -> 0 | W4: =IF(ISNUMBER(SEARCH("E4",$H4)),1,0) -> 1 | X4: =IF(ISNUMBER(SEARCH("E5",$H4)),1,0) -> 0 | Y4: =IF(ISNUMBER(SEARCH("E6",$H4)),1,0) -> 0 | Z4: =IF(ISNUMBER(SEARCH("E7",$H4)),1,0) -> 0 | AA4: =IF(ISNUMBER(SEARCH("E8",$H4)),1,0) -> 1 | AB4: =IF(ISNUMBER(SEARCH("E9",$H4)),1,0) -> 0 | AC4: =IF(ISNUMBER(SEARCH("TR",$H4)),1,0) -> 0 | AD4: R05; R07; S5 | AE4: =IF(ISNUMBER(SEARCH("S0",$AD4)),1,0) -> 0 | AF4: =IF(ISNUMBER(SEARCH("R01",$AD4)),1,0) -> 0 | AG4: =IF(ISNUMBER(SEARCH("R02R03",$AD4)),1,0) -> 0 | AH4: =IF(ISNUMBER(SEARCH("R04",$AD4)),1,0) -> 0 | AI4: =IF(ISNUMBER(SEARCH("R05",$AD4)),1,0) -> 1 | AJ4: =IF(ISNUMBER(SEARCH("S3R06",$AD4)),1,0) -> 0 | AK4: =IF(ISNUMBER(SEARCH("R07",$AD4)),1,0) -> 1 | AL4: =IF(ISNUMBER(SEARCH("R09",$AD4)),1,0) -> 0 | AM4: =IF(ISNUMBER(SEARCH("R10",$AD4)),1,0) -> 0 | AN4: =IF(ISNUMBER(SEARCH("S5",$AD4)),1,0) -> 1 | AO4: =IF(ISNUMBER(SEARCH("S6",$AD4)),1,0) -> 0 | AP4: =IF(ISNUMBER(SEARCH("TR",$AD4)),1,0) -> 0
A5: PAD-04 | B5: Cuenta básica | C5: Directiva 2014/92/UE (PAD) | D5: art. 16.7 | E5: UE_directiva | F5: Vigente | G5: Informar_interesado | H5: E8 | I5: Motivo_decision | J5: Acceso_inclusion | K5: Inmediatamente tras la decisión | L5: Interesado | M5: Cuenta_pago_basica | N5: Si | O5: la entidad de crédito, una vez tomada su decisión, comunique inmediatamente al consumidor la denegación y los motivos específicos de tal denegación, por escrito y de forma gratuita | P5: https://eur-lex.europa.eu/legal-content/ES/TXT/HTML/?uri=CELEX:32014L0092 | Q5: Alta | R5: Excepción: cuando la comunicación sea contraria a la seguridad nacional, el orden público o la normativa AML. Aplica a denegaciones de los apdos. 4, 5 y 6. Cita corregida al texto literal. Verificado en el texto ES de EUR-Lex. Obligación dirigida a los Estados miembros ('velarán por que'), exigible a las entidades a través de la transposición (RDL 19/2017). | S5: =IF(ISNUMBER(SEARCH("E0",$H5)),1,0) -> 0 | T5: =IF(ISNUMBER(SEARCH("E1",$H5)),1,0) -> 0 | U5: =IF(ISNUMBER(SEARCH("E2",$H5)),1,0) -> 0 | V5: =IF(ISNUMBER(SEARCH("E3",$H5)),1,0) -> 0 | W5: =IF(ISNUMBER(SEARCH("E4",$H5)),1,0) -> 0 | X5: =IF(ISNUMBER(SEARCH("E5",$H5)),1,0) -> 0 | Y5: =IF(ISNUMBER(SEARCH("E6",$H5)),1,0) -> 0 | Z5: =IF(ISNUMBER(SEARCH("E7",$H5)),1,0) -> 0 | AA5: =IF(ISNUMBER(SEARCH("E8",$H5)),1,0) -> 1 | AB5: =IF(ISNUMBER(SEARCH("E9",$H5)),1,0) -> 0 | AC5: =IF(ISNUMBER(SEARCH("TR",$H5)),1,0) -> 0 | AD5: S5 | AE5: =IF(ISNUMBER(SEARCH("S0",$AD5)),1,0) -> 0 | AF5: =IF(ISNUMBER(SEARCH("R01",$AD5)),1,0) -> 0 | AG5: =IF(ISNUMBER(SEARCH("R02R03",$AD5)),1,0) -> 0 | AH5: =IF(ISNUMBER(SEARCH("R04",$AD5)),1,0) -> 0 | AI5: =IF(ISNUMBER(SEARCH("R05",$AD5)),1,0) -> 0 | AJ5: =IF(ISNUMBER(SEARCH("S3R06",$AD5)),1,0) -> 0 | AK5: =IF(ISNUMBER(SEARCH("R07",$AD5)),1,0) -> 0 | AL5: =IF(ISNUMBER(SEARCH("R09",$AD5)),1,0) -> 0 | AM5: =IF(ISNUMBER(SEARCH("R10",$AD5)),1,0) -> 0 | AN5: =IF(ISNUMBER(SEARCH("S5",$AD5)),1,0) -> 1 | AO5: =IF(ISNUMBER(SEARCH("S6",$AD5)),1,0) -> 0 | AP5: =IF(ISNUMBER(SEARCH("TR",$AD5)),1,0) -> 0
A6: PAD-05 | B6: Cuenta básica | C6: Directiva 2014/92/UE (PAD) | D6: art. 16.7 | E6: UE_directiva | F6: Vigente | G6: Motivar | H6: E8 | I6: Motivo_decision | J6: Transparencia_consumidor | K6: Inmediatamente tras la decisión | L6: Interesado | M6: Cuenta_pago_basica | N6: Si | O6: comunique inmediatamente al consumidor la denegación y los motivos específicos de tal denegación, por escrito y de forma gratuita, a menos que ello vaya en detrimento de los intereses de seguridad nacional | P6: https://eur-lex.europa.eu/legal-content/ES/TXT/HTML/?uri=CELEX:32014L0092 | Q6: Alta | R6: Misma excepción AML/seguridad nacional/orden público que PAD-04. Cita corregida al texto literal. Verificado en el texto ES de EUR-Lex. Obligación dirigida a los Estados miembros ('velarán por que'), exigible a las entidades a través de la transposición (RDL 19/2017). | S6: =IF(ISNUMBER(SEARCH("E0",$H6)),1,0) -> 0 | T6: =IF(ISNUMBER(SEARCH("E1",$H6)),1,0) -> 0 | U6: =IF(ISNUMBER(SEARCH("E2",$H6)),1,0) -> 0 | V6: =IF(ISNUMBER(SEARCH("E3",$H6)),1,0) -> 0 | W6: =IF(ISNUMBER(SEARCH("E4",$H6)),1,0) -> 0 | X6: =IF(ISNUMBER(SEARCH("E5",$H6)),1,0) -> 0 | Y6: =IF(ISNUMBER(SEARCH("E6",$H6)),1,0) -> 0 | Z6: =IF(ISNUMBER(SEARCH("E7",$H6)),1,0) -> 0 | AA6: =IF(ISNUMBER(SEARCH("E8",$H6)),1,0) -> 1 | AB6: =IF(ISNUMBER(SEARCH("E9",$H6)),1,0) -> 0 | AC6: =IF(ISNUMBER(SEARCH("TR",$H6)),1,0) -> 0 | AD6: S5 | AE6: =IF(ISNUMBER(SEARCH("S0",$AD6)),1,0) -> 0 | AF6: =IF(ISNUMBER(SEARCH("R01",$AD6)),1,0) -> 0 | AG6: =IF(ISNUMBER(SEARCH("R02R03",$AD6)),1,0) -> 0 | AH6: =IF(ISNUMBER(SEARCH("R04",$AD6)),1,0) -> 0 | AI6: =IF(ISNUMBER(SEARCH("R05",$AD6)),1,0) -> 0 | AJ6: =IF(ISNUMBER(SEARCH("S3R06",$AD6)),1,0) -> 0 | AK6: =IF(ISNUMBER(SEARCH("R07",$AD6)),1,0) -> 0 | AL6: =IF(ISNUMBER(SEARCH("R09",$AD6)),1,0) -> 0 | AM6: =IF(ISNUMBER(SEARCH("R10",$AD6)),1,0) -> 0 | AN6: =IF(ISNUMBER(SEARCH("S5",$AD6)),1,0) -> 1 | AO6: =IF(ISNUMBER(SEARCH("S6",$AD6)),1,0) -> 0 | AP6: =IF(ISNUMBER(SEARCH("TR",$AD6)),1,0) -> 0
A7: PAD-06 | B7: Cuenta básica | C7: Directiva 2014/92/UE (PAD) | D7: art. 16.7 | E7: UE_directiva | F7: Vigente | G7: Informar_interesado | H7: E8 | I7: Motivo_decision | J7: Reclamaciones | K7: No especificado | L7: Interesado | M7: Cuenta_pago_basica | N7: Si | O7: la entidad de crédito deberá informar al consumidor del procedimiento que ha de seguir para presentar una reclamación contra la denegación y de su derecho a dirigirse a la autoridad competente correspondiente | P7: https://eur-lex.europa.eu/legal-content/ES/TXT/HTML/?uri=CELEX:32014L0092 | Q7: Alta | R7: Incluye facilitar los datos de contacto pertinentes. Cita corregida al texto literal. Verificado en el texto ES de EUR-Lex. Obligación dirigida a los Estados miembros ('velarán por que'), exigible a las entidades a través de la transposición (RDL 19/2017). | S7: =IF(ISNUMBER(SEARCH("E0",$H7)),1,0) -> 0 | T7: =IF(ISNUMBER(SEARCH("E1",$H7)),1,0) -> 0 | U7: =IF(ISNUMBER(SEARCH("E2",$H7)),1,0) -> 0 | V7: =IF(ISNUMBER(SEARCH("E3",$H7)),1,0) -> 0 | W7: =IF(ISNUMBER(SEARCH("E4",$H7)),1,0) -> 0 | X7: =IF(ISNUMBER(SEARCH("E5",$H7)),1,0) -> 0 | Y7: =IF(ISNUMBER(SEARCH("E6",$H7)),1,0) -> 0 | Z7: =IF(ISNUMBER(SEARCH("E7",$H7)),1,0) -> 0 | AA7: =IF(ISNUMBER(SEARCH("E8",$H7)),1,0) -> 1 | AB7: =IF(ISNUMBER(SEARCH("E9",$H7)),1,0) -> 0 | AC7: =IF(ISNUMBER(SEARCH("TR",$H7)),1,0) -> 0 | AD7: S5 | AE7: =IF(ISNUMBER(SEARCH("S0",$AD7)),1,0) -> 0 | AF7: =IF(ISNUMBER(SEARCH("R01",$AD7)),1,0) -> 0 | AG7: =IF(ISNUMBER(SEARCH("R02R03",$AD7)),1,0) -> 0 | AH7: =IF(ISNUMBER(SEARCH("R04",$AD7)),1,0) -> 0 | AI7: =IF(ISNUMBER(SEARCH("R05",$AD7)),1,0) -> 0 | AJ7: =IF(ISNUMBER(SEARCH("S3R06",$AD7)),1,0) -> 0 | AK7: =IF(ISNUMBER(SEARCH("R07",$AD7)),1,0) -> 0 | AL7: =IF(ISNUMBER(SEARCH("R09",$AD7)),1,0) -> 0 | AM7: =IF(ISNUMBER(SEARCH("R10",$AD7)),1,0) -> 0 | AN7: =IF(ISNUMBER(SEARCH("S5",$AD7)),1,0) -> 1 | AO7: =IF(ISNUMBER(SEARCH("S6",$AD7)),1,0) -> 0 | AP7: =IF(ISNUMBER(SEARCH("TR",$AD7)),1,0) -> 0
A8: PAD-07 | B8: Cuenta básica | C8: Directiva 2014/92/UE (PAD) | D8: art. 16.8 | E8: UE_directiva | F8: Vigente | G8: Comunicar_autoridad | H8: E4; E8 | I8: Expediente_completo | J8: Diligencia_debida_AML | K8: No especificado | L8: Autoridad_AML | M8: Cuenta_pago_basica | N8: Si | O8: en los casos a que se refiere el apartado 4, la entidad de crédito adopte medidas apropiadas con arreglo al capítulo III de la Directiva 2005/60/CE. | P8: https://eur-lex.europa.eu/legal-content/ES/TXT/HTML/?uri=CELEX:32014L0092 | Q8: Alta | R8: El capítulo III de la Directiva 2005/60/CE regula las obligaciones de comunicación (operaciones sospechosas); codificado como Comunicar_autoridad por esa remisión. Cita corregida al texto literal. Verificado en el texto ES de EUR-Lex. Obligación dirigida a los Estados miembros ('velarán por que'), exigible a las entidades a través de la transposición (RDL 19/2017). | S8: =IF(ISNUMBER(SEARCH("E0",$H8)),1,0) -> 0 | T8: =IF(ISNUMBER(SEARCH("E1",$H8)),1,0) -> 0 | U8: =IF(ISNUMBER(SEARCH("E2",$H8)),1,0) -> 0 | V8: =IF(ISNUMBER(SEARCH("E3",$H8)),1,0) -> 0 | W8: =IF(ISNUMBER(SEARCH("E4",$H8)),1,0) -> 1 | X8: =IF(ISNUMBER(SEARCH("E5",$H8)),1,0) -> 0 | Y8: =IF(ISNUMBER(SEARCH("E6",$H8)),1,0) -> 0 | Z8: =IF(ISNUMBER(SEARCH("E7",$H8)),1,0) -> 0 | AA8: =IF(ISNUMBER(SEARCH("E8",$H8)),1,0) -> 1 | AB8: =IF(ISNUMBER(SEARCH("E9",$H8)),1,0) -> 0 | AC8: =IF(ISNUMBER(SEARCH("TR",$H8)),1,0) -> 0 | AD8: R05; S5 | AE8: =IF(ISNUMBER(SEARCH("S0",$AD8)),1,0) -> 0 | AF8: =IF(ISNUMBER(SEARCH("R01",$AD8)),1,0) -> 0 | AG8: =IF(ISNUMBER(SEARCH("R02R03",$AD8)),1,0) -> 0 | AH8: =IF(ISNUMBER(SEARCH("R04",$AD8)),1,0) -> 0 | AI8: =IF(ISNUMBER(SEARCH("R05",$AD8)),1,0) -> 1 | AJ8: =IF(ISNUMBER(SEARCH("S3R06",$AD8)),1,0) -> 0 | AK8: =IF(ISNUMBER(SEARCH("R07",$AD8)),1,0) -> 0 | AL8: =IF(ISNUMBER(SEARCH("R09",$AD8)),1,0) -> 0 | AM8: =IF(ISNUMBER(SEARCH("R10",$AD8)),1,0) -> 0 | AN8: =IF(ISNUMBER(SEARCH("S5",$AD8)),1,0) -> 1 | AO8: =IF(ISNUMBER(SEARCH("S6",$AD8)),1,0) -> 0 | AP8: =IF(ISNUMBER(SEARCH("TR",$AD8)),1,0) -> 0
A9: PAD-08 | B9: Cuenta básica | C9: Directiva 2014/92/UE (PAD) | D9: art. 16.9 | E9: UE_directiva | F9: Vigente | G9: Abstenerse | H9: E0; E9 | I9: Expediente_completo | J9: Acceso_inclusion | K9: No especificado | L9: Interesado | M9: Cuenta_pago_basica | N9: Si | O9: el acceso a una cuenta de pago básica no se supedite a la adquisición de otros servicios o participaciones en el capital de la entidad de crédito, salvo si ello fuera obligatorio | P9: https://eur-lex.europa.eu/legal-content/ES/TXT/HTML/?uri=CELEX:32014L0092 | Q9: Alta | R9: Salvo que esto último se exija a toda la clientela de la entidad. Cita corregida al texto literal. Verificado en el texto ES de EUR-Lex. Obligación dirigida a los Estados miembros ('velarán por que'), exigible a las entidades a través de la transposición (RDL 19/2017). | S9: =IF(ISNUMBER(SEARCH("E0",$H9)),1,0) -> 1 | T9: =IF(ISNUMBER(SEARCH("E1",$H9)),1,0) -> 0 | U9: =IF(ISNUMBER(SEARCH("E2",$H9)),1,0) -> 0 | V9: =IF(ISNUMBER(SEARCH("E3",$H9)),1,0) -> 0 | W9: =IF(ISNUMBER(SEARCH("E4",$H9)),1,0) -> 0 | X9: =IF(ISNUMBER(SEARCH("E5",$H9)),1,0) -> 0 | Y9: =IF(ISNUMBER(SEARCH("E6",$H9)),1,0) -> 0 | Z9: =IF(ISNUMBER(SEARCH("E7",$H9)),1,0) -> 0 | AA9: =IF(ISNUMBER(SEARCH("E8",$H9)),1,0) -> 0 | AB9: =IF(ISNUMBER(SEARCH("E9",$H9)),1,0) -> 1 | AC9: =IF(ISNUMBER(SEARCH("TR",$H9)),1,0) -> 0 | AD9: S0; S6 | AE9: =IF(ISNUMBER(SEARCH("S0",$AD9)),1,0) -> 1 | AF9: =IF(ISNUMBER(SEARCH("R01",$AD9)),1,0) -> 0 | AG9: =IF(ISNUMBER(SEARCH("R02R03",$AD9)),1,0) -> 0 | AH9: =IF(ISNUMBER(SEARCH("R04",$AD9)),1,0) -> 0 | AI9: =IF(ISNUMBER(SEARCH("R05",$AD9)),1,0) -> 0 | AJ9: =IF(ISNUMBER(SEARCH("S3R06",$AD9)),1,0) -> 0 | AK9: =IF(ISNUMBER(SEARCH("R07",$AD9)),1,0) -> 0 | AL9: =IF(ISNUMBER(SEARCH("R09",$AD9)),1,0) -> 0 | AM9: =IF(ISNUMBER(SEARCH("R10",$AD9)),1,0) -> 0 | AN9: =IF(ISNUMBER(SEARCH("S5",$AD9)),1,0) -> 0 | AO9: =IF(ISNUMBER(SEARCH("S6",$AD9)),1,0) -> 1 | AP9: =IF(ISNUMBER(SEARCH("TR",$AD9)),1,0) -> 0
A10: PAD-09 | B10: Cuenta básica | C10: Directiva 2014/92/UE (PAD) | D10: art. 20.2 | E10: UE_directiva | F10: Vigente | G10: Informar_interesado | H10: TR | I10: Informacion_tratamiento | J10: Transparencia_consumidor | K10: No especificado | L10: Interesado | M10: Cuenta_pago_basica | N10: Si | O10: las entidades de crédito pongan gratuitamente a disposición de los consumidores información y asistencia accesibles y gratuitas sobre las características específicas de sus cuentas de pago básicas | P10: https://eur-lex.europa.eu/legal-content/ES/TXT/HTML/?uri=CELEX:32014L0092 | Q10: Alta | R10: Información sobre el producto (características, comisiones, condiciones; que no es obligatorio adquirir otros servicios); no existe categoría de dato específica. Cita corregida al texto literal. Verificado en el texto ES de EUR-Lex. Obligación dirigida a los Estados miembros ('velarán por que'), exigible a las entidades a través de la transposición (RDL 19/2017). | S10: =IF(ISNUMBER(SEARCH("E0",$H10)),1,0) -> 0 | T10: =IF(ISNUMBER(SEARCH("E1",$H10)),1,0) -> 0 | U10: =IF(ISNUMBER(SEARCH("E2",$H10)),1,0) -> 0 | V10: =IF(ISNUMBER(SEARCH("E3",$H10)),1,0) -> 0 | W10: =IF(ISNUMBER(SEARCH("E4",$H10)),1,0) -> 0 | X10: =IF(ISNUMBER(SEARCH("E5",$H10)),1,0) -> 0 | Y10: =IF(ISNUMBER(SEARCH("E6",$H10)),1,0) -> 0 | Z10: =IF(ISNUMBER(SEARCH("E7",$H10)),1,0) -> 0 | AA10: =IF(ISNUMBER(SEARCH("E8",$H10)),1,0) -> 0 | AB10: =IF(ISNUMBER(SEARCH("E9",$H10)),1,0) -> 0 | AC10: =IF(ISNUMBER(SEARCH("TR",$H10)),1,0) -> 1 | AD10: TR | AE10: =IF(ISNUMBER(SEARCH("S0",$AD10)),1,0) -> 0 | AF10: =IF(ISNUMBER(SEARCH("R01",$AD10)),1,0) -> 0 | AG10: =IF(ISNUMBER(SEARCH("R02R03",$AD10)),1,0) -> 0 | AH10: =IF(ISNUMBER(SEARCH("R04",$AD10)),1,0) -> 0 | AI10: =IF(ISNUMBER(SEARCH("R05",$AD10)),1,0) -> 0 | AJ10: =IF(ISNUMBER(SEARCH("S3R06",$AD10)),1,0) -> 0 | AK10: =IF(ISNUMBER(SEARCH("R07",$AD10)),1,0) -> 0 | AL10: =IF(ISNUMBER(SEARCH("R09",$AD10)),1,0) -> 0 | AM10: =IF(ISNUMBER(SEARCH("R10",$AD10)),1,0) -> 0 | AN10: =IF(ISNUMBER(SEARCH("S5",$AD10)),1,0) -> 0 | AO10: =IF(ISNUMBER(SEARCH("S6",$AD10)),1,0) -> 0 | AP10: =IF(ISNUMBER(SEARCH("TR",$AD10)),1,0) -> 1
A11: ES-PAD-01 | B11: Cuenta básica | C11: Real Decreto-ley 19/2017 (cuentas de pago básicas) | D11: art. 4.1.a) | E11: ES_ley | F11: Vigente | G11: Abstenerse | H11: E4; E7; E8 | I11: Resultado_verificacion | J11: Diligencia_debida_AML | K11: No especificado | L11: Interesado | M11: Cuenta_pago_basica | N11: Si | O11: Las entidades de crédito denegarán el acceso [...] cuando [...] El potencial cliente no aporte la información requerida por la entidad en función del nivel de riesgo de blanqueo de capitales | P11: https://www.boe.es/buscar/act.php?id=BOE-A-2017-13644 | Q11: Alta | R11: Remite al capítulo II de la Ley 10/2010. | S11: =IF(ISNUMBER(SEARCH("E0",$H11)),1,0) -> 0 | T11: =IF(ISNUMBER(SEARCH("E1",$H11)),1,0) -> 0 | U11: =IF(ISNUMBER(SEARCH("E2",$H11)),1,0) -> 0 | V11: =IF(ISNUMBER(SEARCH("E3",$H11)),1,0) -> 0 | W11: =IF(ISNUMBER(SEARCH("E4",$H11)),1,0) -> 1 | X11: =IF(ISNUMBER(SEARCH("E5",$H11)),1,0) -> 0 | Y11: =IF(ISNUMBER(SEARCH("E6",$H11)),1,0) -> 0 | Z11: =IF(ISNUMBER(SEARCH("E7",$H11)),1,0) -> 1 | AA11: =IF(ISNUMBER(SEARCH("E8",$H11)),1,0) -> 1 | AB11: =IF(ISNUMBER(SEARCH("E9",$H11)),1,0) -> 0 | AC11: =IF(ISNUMBER(SEARCH("TR",$H11)),1,0) -> 0 | AD11: R05; R07; R10; S5 | AE11: =IF(ISNUMBER(SEARCH("S0",$AD11)),1,0) -> 0 | AF11: =IF(ISNUMBER(SEARCH("R01",$AD11)),1,0) -> 0 | AG11: =IF(ISNUMBER(SEARCH("R02R03",$AD11)),1,0) -> 0 | AH11: =IF(ISNUMBER(SEARCH("R04",$AD11)),1,0) -> 0 | AI11: =IF(ISNUMBER(SEARCH("R05",$AD11)),1,0) -> 1 | AJ11: =IF(ISNUMBER(SEARCH("S3R06",$AD11)),1,0) -> 0 | AK11: =IF(ISNUMBER(SEARCH("R07",$AD11)),1,0) -> 1 | AL11: =IF(ISNUMBER(SEARCH("R09",$AD11)),1,0) -> 0 | AM11: =IF(ISNUMBER(SEARCH("R10",$AD11)),1,0) -> 1 | AN11: =IF(ISNUMBER(SEARCH("S5",$AD11)),1,0) -> 1 | AO11: =IF(ISNUMBER(SEARCH("S6",$AD11)),1,0) -> 0 | AP11: =IF(ISNUMBER(SEARCH("TR",$AD11)),1,0) -> 0
A12: ES-PAD-02 | B12: Cuenta básica | C12: Real Decreto-ley 19/2017 (cuentas de pago básicas) | D12: art. 4.1.b) | E12: ES_ley | F12: Vigente | G12: Abstenerse | H12: E8 | I12: Motivo_decision | J12: Acceso_inclusion | K12: No especificado | L12: Interesado | M12: Cuenta_pago_basica | N12: Si | O12: su apertura sea contraria a los intereses de la seguridad nacional o de orden público [...] en los supuestos en que así se haya acordado por el Consejo de Ministros | P12: https://www.boe.es/buscar/act.php?id=BOE-A-2017-13644 | Q12: Alta | S12: =IF(ISNUMBER(SEARCH("E0",$H12)),1,0) -> 0 | T12: =IF(ISNUMBER(SEARCH("E1",$H12)),1,0) -> 0 | U12: =IF(ISNUMBER(SEARCH("E2",$H12)),1,0) -> 0 | V12: =IF(ISNUMBER(SEARCH("E3",$H12)),1,0) -> 0 | W12: =IF(ISNUMBER(SEARCH("E4",$H12)),1,0) -> 0 | X12: =IF(ISNUMBER(SEARCH("E5",$H12)),1,0) -> 0 | Y12: =IF(ISNUMBER(SEARCH("E6",$H12)),1,0) -> 0 | Z12: =IF(ISNUMBER(SEARCH("E7",$H12)),1,0) -> 0 | AA12: =IF(ISNUMBER(SEARCH("E8",$H12)),1,0) -> 1 | AB12: =IF(ISNUMBER(SEARCH("E9",$H12)),1,0) -> 0 | AC12: =IF(ISNUMBER(SEARCH("TR",$H12)),1,0) -> 0 | AD12: S5 | AE12: =IF(ISNUMBER(SEARCH("S0",$AD12)),1,0) -> 0 | AF12: =IF(ISNUMBER(SEARCH("R01",$AD12)),1,0) -> 0 | AG12: =IF(ISNUMBER(SEARCH("R02R03",$AD12)),1,0) -> 0 | AH12: =IF(ISNUMBER(SEARCH("R04",$AD12)),1,0) -> 0 | AI12: =IF(ISNUMBER(SEARCH("R05",$AD12)),1,0) -> 0 | AJ12: =IF(ISNUMBER(SEARCH("S3R06",$AD12)),1,0) -> 0 | AK12: =IF(ISNUMBER(SEARCH("R07",$AD12)),1,0) -> 0 | AL12: =IF(ISNUMBER(SEARCH("R09",$AD12)),1,0) -> 0 | AM12: =IF(ISNUMBER(SEARCH("R10",$AD12)),1,0) -> 0 | AN12: =IF(ISNUMBER(SEARCH("S5",$AD12)),1,0) -> 1 | AO12: =IF(ISNUMBER(SEARCH("S6",$AD12)),1,0) -> 0 | AP12: =IF(ISNUMBER(SEARCH("TR",$AD12)),1,0) -> 0
A13: ES-PAD-03 | B13: Cuenta básica | C13: Real Decreto-ley 19/2017 (cuentas de pago básicas) | D13: art. 4.1.c) | E13: ES_ley | F13: Vigente | G13: Abstenerse | H13: E8 | I13: Resultado_verificacion | J13: Acceso_inclusion | K13: No especificado | L13: Interesado | M13: Cuenta_pago_basica | N13: Si | O13: el potencial cliente ya sea titular en España de una cuenta en un proveedor de servicios de pago que le permita realizar los servicios contemplados en el artículo 8.1 | P13: https://www.boe.es/buscar/act.php?id=BOE-A-2017-13644 | Q13: Alta | R13: Denegación obligatoria en España (la PAD la configura como opción). La entidad podrá verificarlo y basarse en una declaración responsable firmada por el cliente. | S13: =IF(ISNUMBER(SEARCH("E0",$H13)),1,0) -> 0 | T13: =IF(ISNUMBER(SEARCH("E1",$H13)),1,0) -> 0 | U13: =IF(ISNUMBER(SEARCH("E2",$H13)),1,0) -> 0 | V13: =IF(ISNUMBER(SEARCH("E3",$H13)),1,0) -> 0 | W13: =IF(ISNUMBER(SEARCH("E4",$H13)),1,0) -> 0 | X13: =IF(ISNUMBER(SEARCH("E5",$H13)),1,0) -> 0 | Y13: =IF(ISNUMBER(SEARCH("E6",$H13)),1,0) -> 0 | Z13: =IF(ISNUMBER(SEARCH("E7",$H13)),1,0) -> 0 | AA13: =IF(ISNUMBER(SEARCH("E8",$H13)),1,0) -> 1 | AB13: =IF(ISNUMBER(SEARCH("E9",$H13)),1,0) -> 0 | AC13: =IF(ISNUMBER(SEARCH("TR",$H13)),1,0) -> 0 | AD13: S5 | AE13: =IF(ISNUMBER(SEARCH("S0",$AD13)),1,0) -> 0 | AF13: =IF(ISNUMBER(SEARCH("R01",$AD13)),1,0) -> 0 | AG13: =IF(ISNUMBER(SEARCH("R02R03",$AD13)),1,0) -> 0 | AH13: =IF(ISNUMBER(SEARCH("R04",$AD13)),1,0) -> 0 | AI13: =IF(ISNUMBER(SEARCH("R05",$AD13)),1,0) -> 0 | AJ13: =IF(ISNUMBER(SEARCH("S3R06",$AD13)),1,0) -> 0 | AK13: =IF(ISNUMBER(SEARCH("R07",$AD13)),1,0) -> 0 | AL13: =IF(ISNUMBER(SEARCH("R09",$AD13)),1,0) -> 0 | AM13: =IF(ISNUMBER(SEARCH("R10",$AD13)),1,0) -> 0 | AN13: =IF(ISNUMBER(SEARCH("S5",$AD13)),1,0) -> 1 | AO13: =IF(ISNUMBER(SEARCH("S6",$AD13)),1,0) -> 0 | AP13: =IF(ISNUMBER(SEARCH("TR",$AD13)),1,0) -> 0
A14: ES-PAD-04 | B14: Cuenta básica | C14: Real Decreto-ley 19/2017 (cuentas de pago básicas) | D14: art. 4.1 (párrafo final) | E14: ES_ley | F14: Vigente | G14: Conservar | H14: E8 | I14: Motivo_decision | J14: Acceso_inclusion | K14: No especificado | L14: Uso_interno | M14: Cuenta_pago_basica | N14: Si | O14: La entidad conservará los documentos y el análisis realizado en el que se base esta decisión. | P14: https://www.boe.es/buscar/act.php?id=BOE-A-2017-13644 | Q14: Alta | R14: Obligación específica de conservar el expediente de la denegación; sin plazo propio en el RDL. | S14: =IF(ISNUMBER(SEARCH("E0",$H14)),1,0) -> 0 | T14: =IF(ISNUMBER(SEARCH("E1",$H14)),1,0) -> 0 | U14: =IF(ISNUMBER(SEARCH("E2",$H14)),1,0) -> 0 | V14: =IF(ISNUMBER(SEARCH("E3",$H14)),1,0) -> 0 | W14: =IF(ISNUMBER(SEARCH("E4",$H14)),1,0) -> 0 | X14: =IF(ISNUMBER(SEARCH("E5",$H14)),1,0) -> 0 | Y14: =IF(ISNUMBER(SEARCH("E6",$H14)),1,0) -> 0 | Z14: =IF(ISNUMBER(SEARCH("E7",$H14)),1,0) -> 0 | AA14: =IF(ISNUMBER(SEARCH("E8",$H14)),1,0) -> 1 | AB14: =IF(ISNUMBER(SEARCH("E9",$H14)),1,0) -> 0 | AC14: =IF(ISNUMBER(SEARCH("TR",$H14)),1,0) -> 0 | AD14: S5 | AE14: =IF(ISNUMBER(SEARCH("S0",$AD14)),1,0) -> 0 | AF14: =IF(ISNUMBER(SEARCH("R01",$AD14)),1,0) -> 0 | AG14: =IF(ISNUMBER(SEARCH("R02R03",$AD14)),1,0) -> 0 | AH14: =IF(ISNUMBER(SEARCH("R04",$AD14)),1,0) -> 0 | AI14: =IF(ISNUMBER(SEARCH("R05",$AD14)),1,0) -> 0 | AJ14: =IF(ISNUMBER(SEARCH("S3R06",$AD14)),1,0) -> 0 | AK14: =IF(ISNUMBER(SEARCH("R07",$AD14)),1,0) -> 0 | AL14: =IF(ISNUMBER(SEARCH("R09",$AD14)),1,0) -> 0 | AM14: =IF(ISNUMBER(SEARCH("R10",$AD14)),1,0) -> 0 | AN14: =IF(ISNUMBER(SEARCH("S5",$AD14)),1,0) -> 1 | AO14: =IF(ISNUMBER(SEARCH("S6",$AD14)),1,0) -> 0 | AP14: =IF(ISNUMBER(SEARCH("TR",$AD14)),1,0) -> 0
A15: ES-PAD-05 | B15: Cuenta básica | C15: Real Decreto-ley 19/2017 (cuentas de pago básicas) | D15: art. 4.2 | E15: ES_ley | F15: Vigente | G15: Abstenerse | H15: E0; E9 | I15: Expediente_completo | J15: Acceso_inclusion | K15: No especificado | L15: Interesado | M15: Cuenta_pago_basica | N15: Si | O15: El acceso a la cuenta de pago básica no podrá supeditarse a la adquisición de otros servicios, ni a la adquisición de participaciones en el capital | P15: https://www.boe.es/buscar/act.php?id=BOE-A-2017-13644 | Q15: Alta | R15: Salvo que lo imponga la normativa o sea requisito ineludible para toda la clientela. | S15: =IF(ISNUMBER(SEARCH("E0",$H15)),1,0) -> 1 | T15: =IF(ISNUMBER(SEARCH("E1",$H15)),1,0) -> 0 | U15: =IF(ISNUMBER(SEARCH("E2",$H15)),1,0) -> 0 | V15: =IF(ISNUMBER(SEARCH("E3",$H15)),1,0) -> 0 | W15: =IF(ISNUMBER(SEARCH("E4",$H15)),1,0) -> 0 | X15: =IF(ISNUMBER(SEARCH("E5",$H15)),1,0) -> 0 | Y15: =IF(ISNUMBER(SEARCH("E6",$H15)),1,0) -> 0 | Z15: =IF(ISNUMBER(SEARCH("E7",$H15)),1,0) -> 0 | AA15: =IF(ISNUMBER(SEARCH("E8",$H15)),1,0) -> 0 | AB15: =IF(ISNUMBER(SEARCH("E9",$H15)),1,0) -> 1 | AC15: =IF(ISNUMBER(SEARCH("TR",$H15)),1,0) -> 0 | AD15: S0; S6 | AE15: =IF(ISNUMBER(SEARCH("S0",$AD15)),1,0) -> 1 | AF15: =IF(ISNUMBER(SEARCH("R01",$AD15)),1,0) -> 0 | AG15: =IF(ISNUMBER(SEARCH("R02R03",$AD15)),1,0) -> 0 | AH15: =IF(ISNUMBER(SEARCH("R04",$AD15)),1,0) -> 0 | AI15: =IF(ISNUMBER(SEARCH("R05",$AD15)),1,0) -> 0 | AJ15: =IF(ISNUMBER(SEARCH("S3R06",$AD15)),1,0) -> 0 | AK15: =IF(ISNUMBER(SEARCH("R07",$AD15)),1,0) -> 0 | AL15: =IF(ISNUMBER(SEARCH("R09",$AD15)),1,0) -> 0 | AM15: =IF(ISNUMBER(SEARCH("R10",$AD15)),1,0) -> 0 | AN15: =IF(ISNUMBER(SEARCH("S5",$AD15)),1,0) -> 0 | AO15: =IF(ISNUMBER(SEARCH("S6",$AD15)),1,0) -> 1 | AP15: =IF(ISNUMBER(SEARCH("TR",$AD15)),1,0) -> 0
A16: ES-PAD-06 | B16: Cuenta básica | C16: Real Decreto-ley 19/2017 (cuentas de pago básicas) | D16: art. 5.1 | E16: ES_ley | F16: Vigente | G16: Informar_interesado | H16: E8 | I16: Motivo_decision | J16: Acceso_inclusion | K16: No especificado | L16: Interesado | M16: Cuenta_pago_basica | N16: Si | O16: La entidad de crédito deberá informar al potencial cliente de la denegación de la apertura de una cuenta de pago básica, a menos que no resulte compatible con lo establecido en la Ley 10/2010 | P16: https://www.boe.es/buscar/act.php?id=BOE-A-2017-13644 | Q16: Alta | R16: Excepción también por seguridad nacional u orden público. | S16: =IF(ISNUMBER(SEARCH("E0",$H16)),1,0) -> 0 | T16: =IF(ISNUMBER(SEARCH("E1",$H16)),1,0) -> 0 | U16: =IF(ISNUMBER(SEARCH("E2",$H16)),1,0) -> 0 | V16: =IF(ISNUMBER(SEARCH("E3",$H16)),1,0) -> 0 | W16: =IF(ISNUMBER(SEARCH("E4",$H16)),1,0) -> 0 | X16: =IF(ISNUMBER(SEARCH("E5",$H16)),1,0) -> 0 | Y16: =IF(ISNUMBER(SEARCH("E6",$H16)),1,0) -> 0 | Z16: =IF(ISNUMBER(SEARCH("E7",$H16)),1,0) -> 0 | AA16: =IF(ISNUMBER(SEARCH("E8",$H16)),1,0) -> 1 | AB16: =IF(ISNUMBER(SEARCH("E9",$H16)),1,0) -> 0 | AC16: =IF(ISNUMBER(SEARCH("TR",$H16)),1,0) -> 0 | AD16: S5 | AE16: =IF(ISNUMBER(SEARCH("S0",$AD16)),1,0) -> 0 | AF16: =IF(ISNUMBER(SEARCH("R01",$AD16)),1,0) -> 0 | AG16: =IF(ISNUMBER(SEARCH("R02R03",$AD16)),1,0) -> 0 | AH16: =IF(ISNUMBER(SEARCH("R04",$AD16)),1,0) -> 0 | AI16: =IF(ISNUMBER(SEARCH("R05",$AD16)),1,0) -> 0 | AJ16: =IF(ISNUMBER(SEARCH("S3R06",$AD16)),1,0) -> 0 | AK16: =IF(ISNUMBER(SEARCH("R07",$AD16)),1,0) -> 0 | AL16: =IF(ISNUMBER(SEARCH("R09",$AD16)),1,0) -> 0 | AM16: =IF(ISNUMBER(SEARCH("R10",$AD16)),1,0) -> 0 | AN16: =IF(ISNUMBER(SEARCH("S5",$AD16)),1,0) -> 1 | AO16: =IF(ISNUMBER(SEARCH("S6",$AD16)),1,0) -> 0 | AP16: =IF(ISNUMBER(SEARCH("TR",$AD16)),1,0) -> 0
A17: ES-PAD-07 | B17: Cuenta básica | C17: Real Decreto-ley 19/2017 (cuentas de pago básicas) | D17: art. 5.2 | E17: ES_ley | F17: Vigente | G17: Motivar | H17: E8 | I17: Motivo_decision | J17: Transparencia_consumidor | K17: 10 días hábiles desde la recepción de la solicitud completa | L17: Interesado | M17: Cuenta_pago_basica | N17: Si | O17: La denegación se notificará al potencial cliente por escrito y de manera gratuita, expresando las razones concretas en las que se funda [...] a más tardar en un plazo máximo de diez días hábiles | P17: https://www.boe.es/buscar/act.php?id=BOE-A-2017-13644 | Q17: Alta | S17: =IF(ISNUMBER(SEARCH("E0",$H17)),1,0) -> 0 | T17: =IF(ISNUMBER(SEARCH("E1",$H17)),1,0) -> 0 | U17: =IF(ISNUMBER(SEARCH("E2",$H17)),1,0) -> 0 | V17: =IF(ISNUMBER(SEARCH("E3",$H17)),1,0) -> 0 | W17: =IF(ISNUMBER(SEARCH("E4",$H17)),1,0) -> 0 | X17: =IF(ISNUMBER(SEARCH("E5",$H17)),1,0) -> 0 | Y17: =IF(ISNUMBER(SEARCH("E6",$H17)),1,0) -> 0 | Z17: =IF(ISNUMBER(SEARCH("E7",$H17)),1,0) -> 0 | AA17: =IF(ISNUMBER(SEARCH("E8",$H17)),1,0) -> 1 | AB17: =IF(ISNUMBER(SEARCH("E9",$H17)),1,0) -> 0 | AC17: =IF(ISNUMBER(SEARCH("TR",$H17)),1,0) -> 0 | AD17: S5 | AE17: =IF(ISNUMBER(SEARCH("S0",$AD17)),1,0) -> 0 | AF17: =IF(ISNUMBER(SEARCH("R01",$AD17)),1,0) -> 0 | AG17: =IF(ISNUMBER(SEARCH("R02R03",$AD17)),1,0) -> 0 | AH17: =IF(ISNUMBER(SEARCH("R04",$AD17)),1,0) -> 0 | AI17: =IF(ISNUMBER(SEARCH("R05",$AD17)),1,0) -> 0 | AJ17: =IF(ISNUMBER(SEARCH("S3R06",$AD17)),1,0) -> 0 | AK17: =IF(ISNUMBER(SEARCH("R07",$AD17)),1,0) -> 0 | AL17: =IF(ISNUMBER(SEARCH("R09",$AD17)),1,0) -> 0 | AM17: =IF(ISNUMBER(SEARCH("R10",$AD17)),1,0) -> 0 | AN17: =IF(ISNUMBER(SEARCH("S5",$AD17)),1,0) -> 1 | AO17: =IF(ISNUMBER(SEARCH("S6",$AD17)),1,0) -> 0 | AP17: =IF(ISNUMBER(SEARCH("TR",$AD17)),1,0) -> 0
A18: ES-PAD-08 | B18: Cuenta básica | C18: Real Decreto-ley 19/2017 (cuentas de pago básicas) | D18: art. 5.3 | E18: ES_ley | F18: Vigente | G18: Informar_interesado | H18: E8 | I18: Motivo_decision | J18: Reclamaciones | K18: Al notificar la denegación | L18: Interesado | M18: Cuenta_pago_basica | N18: Si | O18: al notificar el rechazo de la solicitud de apertura, las entidades informarán al potencial cliente del procedimiento que ha de seguir para presentar una reclamación contra la denegación | P18: https://www.boe.es/buscar/act.php?id=BOE-A-2017-13644 | Q18: Alta | R18: Y de su derecho al procedimiento del art. 30 Ley 44/2002 (Banco de España). Véase también art. 6 Orden ECE/228/2019 (la negativa a abrir es reclamable conforme a la DA 1.ª Ley 7/2017). | S18: =IF(ISNUMBER(SEARCH("E0",$H18)),1,0) -> 0 | T18: =IF(ISNUMBER(SEARCH("E1",$H18)),1,0) -> 0 | U18: =IF(ISNUMBER(SEARCH("E2",$H18)),1,0) -> 0 | V18: =IF(ISNUMBER(SEARCH("E3",$H18)),1,0) -> 0 | W18: =IF(ISNUMBER(SEARCH("E4",$H18)),1,0) -> 0 | X18: =IF(ISNUMBER(SEARCH("E5",$H18)),1,0) -> 0 | Y18: =IF(ISNUMBER(SEARCH("E6",$H18)),1,0) -> 0 | Z18: =IF(ISNUMBER(SEARCH("E7",$H18)),1,0) -> 0 | AA18: =IF(ISNUMBER(SEARCH("E8",$H18)),1,0) -> 1 | AB18: =IF(ISNUMBER(SEARCH("E9",$H18)),1,0) -> 0 | AC18: =IF(ISNUMBER(SEARCH("TR",$H18)),1,0) -> 0 | AD18: S5 | AE18: =IF(ISNUMBER(SEARCH("S0",$AD18)),1,0) -> 0 | AF18: =IF(ISNUMBER(SEARCH("R01",$AD18)),1,0) -> 0 | AG18: =IF(ISNUMBER(SEARCH("R02R03",$AD18)),1,0) -> 0 | AH18: =IF(ISNUMBER(SEARCH("R04",$AD18)),1,0) -> 0 | AI18: =IF(ISNUMBER(SEARCH("R05",$AD18)),1,0) -> 0 | AJ18: =IF(ISNUMBER(SEARCH("S3R06",$AD18)),1,0) -> 0 | AK18: =IF(ISNUMBER(SEARCH("R07",$AD18)),1,0) -> 0 | AL18: =IF(ISNUMBER(SEARCH("R09",$AD18)),1,0) -> 0 | AM18: =IF(ISNUMBER(SEARCH("R10",$AD18)),1,0) -> 0 | AN18: =IF(ISNUMBER(SEARCH("S5",$AD18)),1,0) -> 1 | AO18: =IF(ISNUMBER(SEARCH("S6",$AD18)),1,0) -> 0 | AP18: =IF(ISNUMBER(SEARCH("TR",$AD18)),1,0) -> 0
A19: ES-PAD-09 | B19: Cuenta básica | C19: Real Decreto-ley 19/2017 (cuentas de pago básicas) | D19: art. 10.2 | E19: ES_ley | F19: Vigente | G19: Informar_interesado | H19: TR | I19: Informacion_tratamiento | J19: Transparencia_consumidor | K19: No especificado | L19: Interesado | M19: Cuenta_pago_basica | N19: Parcial | O19: se indicará claramente en la publicidad e información facilitada por las entidades de crédito que para tener acceso a una cuenta de pago básica no es obligatorio adquirir otros servicios | P19: https://www.boe.es/buscar/act.php?id=BOE-A-2017-13644 | Q19: Alta | R19: Incluye uso destacado de la denominación «cuenta de pago básica». Información sobre el producto (no hay categoría de dato específica). | S19: =IF(ISNUMBER(SEARCH("E0",$H19)),1,0) -> 0 | T19: =IF(ISNUMBER(SEARCH("E1",$H19)),1,0) -> 0 | U19: =IF(ISNUMBER(SEARCH("E2",$H19)),1,0) -> 0 | V19: =IF(ISNUMBER(SEARCH("E3",$H19)),1,0) -> 0 | W19: =IF(ISNUMBER(SEARCH("E4",$H19)),1,0) -> 0 | X19: =IF(ISNUMBER(SEARCH("E5",$H19)),1,0) -> 0 | Y19: =IF(ISNUMBER(SEARCH("E6",$H19)),1,0) -> 0 | Z19: =IF(ISNUMBER(SEARCH("E7",$H19)),1,0) -> 0 | AA19: =IF(ISNUMBER(SEARCH("E8",$H19)),1,0) -> 0 | AB19: =IF(ISNUMBER(SEARCH("E9",$H19)),1,0) -> 0 | AC19: =IF(ISNUMBER(SEARCH("TR",$H19)),1,0) -> 1 | AD19: TR | AE19: =IF(ISNUMBER(SEARCH("S0",$AD19)),1,0) -> 0 | AF19: =IF(ISNUMBER(SEARCH("R01",$AD19)),1,0) -> 0 | AG19: =IF(ISNUMBER(SEARCH("R02R03",$AD19)),1,0) -> 0 | AH19: =IF(ISNUMBER(SEARCH("R04",$AD19)),1,0) -> 0 | AI19: =IF(ISNUMBER(SEARCH("R05",$AD19)),1,0) -> 0 | AJ19: =IF(ISNUMBER(SEARCH("S3R06",$AD19)),1,0) -> 0 | AK19: =IF(ISNUMBER(SEARCH("R07",$AD19)),1,0) -> 0 | AL19: =IF(ISNUMBER(SEARCH("R09",$AD19)),1,0) -> 0 | AM19: =IF(ISNUMBER(SEARCH("R10",$AD19)),1,0) -> 0 | AN19: =IF(ISNUMBER(SEARCH("S5",$AD19)),1,0) -> 0 | AO19: =IF(ISNUMBER(SEARCH("S6",$AD19)),1,0) -> 0 | AP19: =IF(ISNUMBER(SEARCH("TR",$AD19)),1,0) -> 1
A20: ES-PAD-10 | B20: Cuenta básica | C20: Real Decreto-ley 19/2017 (cuentas de pago básicas) | D20: art. 10.3 | E20: ES_ley | F20: Vigente | G20: Informar_interesado | H20: TR | I20: Informacion_tratamiento | J20: Transparencia_consumidor | K20: No especificado | L20: Interesado | M20: Cuenta_pago_basica | N20: Si | O20: las entidades de crédito deberán tener a disposición de los clientes o potenciales clientes gratuitamente en todos sus canales de distribución al consumidor, información y asistencia | P20: https://www.boe.es/buscar/act.php?id=BOE-A-2017-13644 | Q20: Alta | R20: Sobre servicios incluidos, comisiones y condiciones de uso. Información sobre el producto. | S20: =IF(ISNUMBER(SEARCH("E0",$H20)),1,0) -> 0 | T20: =IF(ISNUMBER(SEARCH("E1",$H20)),1,0) -> 0 | U20: =IF(ISNUMBER(SEARCH("E2",$H20)),1,0) -> 0 | V20: =IF(ISNUMBER(SEARCH("E3",$H20)),1,0) -> 0 | W20: =IF(ISNUMBER(SEARCH("E4",$H20)),1,0) -> 0 | X20: =IF(ISNUMBER(SEARCH("E5",$H20)),1,0) -> 0 | Y20: =IF(ISNUMBER(SEARCH("E6",$H20)),1,0) -> 0 | Z20: =IF(ISNUMBER(SEARCH("E7",$H20)),1,0) -> 0 | AA20: =IF(ISNUMBER(SEARCH("E8",$H20)),1,0) -> 0 | AB20: =IF(ISNUMBER(SEARCH("E9",$H20)),1,0) -> 0 | AC20: =IF(ISNUMBER(SEARCH("TR",$H20)),1,0) -> 1 | AD20: TR | AE20: =IF(ISNUMBER(SEARCH("S0",$AD20)),1,0) -> 0 | AF20: =IF(ISNUMBER(SEARCH("R01",$AD20)),1,0) -> 0 | AG20: =IF(ISNUMBER(SEARCH("R02R03",$AD20)),1,0) -> 0 | AH20: =IF(ISNUMBER(SEARCH("R04",$AD20)),1,0) -> 0 | AI20: =IF(ISNUMBER(SEARCH("R05",$AD20)),1,0) -> 0 | AJ20: =IF(ISNUMBER(SEARCH("S3R06",$AD20)),1,0) -> 0 | AK20: =IF(ISNUMBER(SEARCH("R07",$AD20)),1,0) -> 0 | AL20: =IF(ISNUMBER(SEARCH("R09",$AD20)),1,0) -> 0 | AM20: =IF(ISNUMBER(SEARCH("R10",$AD20)),1,0) -> 0 | AN20: =IF(ISNUMBER(SEARCH("S5",$AD20)),1,0) -> 0 | AO20: =IF(ISNUMBER(SEARCH("S6",$AD20)),1,0) -> 0 | AP20: =IF(ISNUMBER(SEARCH("TR",$AD20)),1,0) -> 1
A21: ES-PAD-11 | B21: Cuenta básica | C21: Orden ECE/228/2019 (cuentas de pago básicas) | D21: art. 8.1.e) | E21: ES_reglamento | F21: Vigente | G21: Informar_interesado | H21: TR | I21: Informacion_tratamiento | J21: Acceso_inclusion | K21: No especificado | L21: Interesado | M21: Cuenta_pago_basica | N21: Si | O21: el procedimiento a seguir para la apertura de una cuenta de pago básica, incluyendo, en particular, la información y documentación a presentar | P21: https://www.boe.es/buscar/act.php?id=BOE-A-2019-3113 | Q21: Alta | R21: Norma añadida (no listada en el encargo) por desarrollar el art. 10 RDL 19/2017. El art. 8.1 obliga además a aprobar, ejecutar y evaluar el impacto de procedimientos de difusión; el 8.2, medidas para consumidores vulnerables. | S21: =IF(ISNUMBER(SEARCH("E0",$H21)),1,0) -> 0 | T21: =IF(ISNUMBER(SEARCH("E1",$H21)),1,0) -> 0 | U21: =IF(ISNUMBER(SEARCH("E2",$H21)),1,0) -> 0 | V21: =IF(ISNUMBER(SEARCH("E3",$H21)),1,0) -> 0 | W21: =IF(ISNUMBER(SEARCH("E4",$H21)),1,0) -> 0 | X21: =IF(ISNUMBER(SEARCH("E5",$H21)),1,0) -> 0 | Y21: =IF(ISNUMBER(SEARCH("E6",$H21)),1,0) -> 0 | Z21: =IF(ISNUMBER(SEARCH("E7",$H21)),1,0) -> 0 | AA21: =IF(ISNUMBER(SEARCH("E8",$H21)),1,0) -> 0 | AB21: =IF(ISNUMBER(SEARCH("E9",$H21)),1,0) -> 0 | AC21: =IF(ISNUMBER(SEARCH("TR",$H21)),1,0) -> 1 | AD21: TR | AE21: =IF(ISNUMBER(SEARCH("S0",$AD21)),1,0) -> 0 | AF21: =IF(ISNUMBER(SEARCH("R01",$AD21)),1,0) -> 0 | AG21: =IF(ISNUMBER(SEARCH("R02R03",$AD21)),1,0) -> 0 | AH21: =IF(ISNUMBER(SEARCH("R04",$AD21)),1,0) -> 0 | AI21: =IF(ISNUMBER(SEARCH("R05",$AD21)),1,0) -> 0 | AJ21: =IF(ISNUMBER(SEARCH("S3R06",$AD21)),1,0) -> 0 | AK21: =IF(ISNUMBER(SEARCH("R07",$AD21)),1,0) -> 0 | AL21: =IF(ISNUMBER(SEARCH("R09",$AD21)),1,0) -> 0 | AM21: =IF(ISNUMBER(SEARCH("R10",$AD21)),1,0) -> 0 | AN21: =IF(ISNUMBER(SEARCH("S5",$AD21)),1,0) -> 0 | AO21: =IF(ISNUMBER(SEARCH("S6",$AD21)),1,0) -> 0 | AP21: =IF(ISNUMBER(SEARCH("TR",$AD21)),1,0) -> 1
A22: ES-PAD-12 | B22: Cuenta básica | C22: Real Decreto 164/2019 (gratuidad CPB vulnerables) | D22: art. 4.4 | E22: ES_reglamento | F22: Vigente | G22: Informar_interesado | H22: E8; E9 | I22: Motivo_decision | J22: Acceso_inclusion | K22: Máximo 30 días desde la aportación completa | L22: Interesado | M22: Cuenta_pago_basica | N22: Si | O22: El reconocimiento o la denegación de la condición de gratuidad se comunicará al cliente, por escrito y de manera gratuita, en el plazo máximo de treinta días desde la fecha de la aportación completa | P22: https://www.boe.es/buscar/act.php?id=BOE-A-2019-4906 | Q22: Alta | R22: Silencio positivo: transcurrido el plazo sin comunicación se entiende reconocida la gratuidad. No exige expresamente motivar. Puede solicitarse en el alta o después (art. 2.2). | S22: =IF(ISNUMBER(SEARCH("E0",$H22)),1,0) -> 0 | T22: =IF(ISNUMBER(SEARCH("E1",$H22)),1,0) -> 0 | U22: =IF(ISNUMBER(SEARCH("E2",$H22)),1,0) -> 0 | V22: =IF(ISNUMBER(SEARCH("E3",$H22)),1,0) -> 0 | W22: =IF(ISNUMBER(SEARCH("E4",$H22)),1,0) -> 0 | X22: =IF(ISNUMBER(SEARCH("E5",$H22)),1,0) -> 0 | Y22: =IF(ISNUMBER(SEARCH("E6",$H22)),1,0) -> 0 | Z22: =IF(ISNUMBER(SEARCH("E7",$H22)),1,0) -> 0 | AA22: =IF(ISNUMBER(SEARCH("E8",$H22)),1,0) -> 1 | AB22: =IF(ISNUMBER(SEARCH("E9",$H22)),1,0) -> 1 | AC22: =IF(ISNUMBER(SEARCH("TR",$H22)),1,0) -> 0 | AD22: S5; S6 | AE22: =IF(ISNUMBER(SEARCH("S0",$AD22)),1,0) -> 0 | AF22: =IF(ISNUMBER(SEARCH("R01",$AD22)),1,0) -> 0 | AG22: =IF(ISNUMBER(SEARCH("R02R03",$AD22)),1,0) -> 0 | AH22: =IF(ISNUMBER(SEARCH("R04",$AD22)),1,0) -> 0 | AI22: =IF(ISNUMBER(SEARCH("R05",$AD22)),1,0) -> 0 | AJ22: =IF(ISNUMBER(SEARCH("S3R06",$AD22)),1,0) -> 0 | AK22: =IF(ISNUMBER(SEARCH("R07",$AD22)),1,0) -> 0 | AL22: =IF(ISNUMBER(SEARCH("R09",$AD22)),1,0) -> 0 | AM22: =IF(ISNUMBER(SEARCH("R10",$AD22)),1,0) -> 0 | AN22: =IF(ISNUMBER(SEARCH("S5",$AD22)),1,0) -> 1 | AO22: =IF(ISNUMBER(SEARCH("S6",$AD22)),1,0) -> 1 | AP22: =IF(ISNUMBER(SEARCH("TR",$AD22)),1,0) -> 0
A23: ES-PAD-13 | B23: Cuenta básica | C23: Real Decreto 164/2019 (gratuidad CPB vulnerables) | D23: art. 4.4 (párrafo 2) | E23: ES_reglamento | F23: Vigente | G23: Informar_interesado | H23: E8 | I23: Motivo_decision | J23: Reclamaciones | K23: Con la comunicación de la denegación | L23: Interesado | M23: Cuenta_pago_basica | N23: Si | O23: El escrito incluirá la información del derecho del cliente a presentar una reclamación contra la denegación, conforme a lo previsto en la disposición adicional segunda. | P23: https://www.boe.es/buscar/act.php?id=BOE-A-2019-4906 | Q23: Alta | S23: =IF(ISNUMBER(SEARCH("E0",$H23)),1,0) -> 0 | T23: =IF(ISNUMBER(SEARCH("E1",$H23)),1,0) -> 0 | U23: =IF(ISNUMBER(SEARCH("E2",$H23)),1,0) -> 0 | V23: =IF(ISNUMBER(SEARCH("E3",$H23)),1,0) -> 0 | W23: =IF(ISNUMBER(SEARCH("E4",$H23)),1,0) -> 0 | X23: =IF(ISNUMBER(SEARCH("E5",$H23)),1,0) -> 0 | Y23: =IF(ISNUMBER(SEARCH("E6",$H23)),1,0) -> 0 | Z23: =IF(ISNUMBER(SEARCH("E7",$H23)),1,0) -> 0 | AA23: =IF(ISNUMBER(SEARCH("E8",$H23)),1,0) -> 1 | AB23: =IF(ISNUMBER(SEARCH("E9",$H23)),1,0) -> 0 | AC23: =IF(ISNUMBER(SEARCH("TR",$H23)),1,0) -> 0 | AD23: S5 | AE23: =IF(ISNUMBER(SEARCH("S0",$AD23)),1,0) -> 0 | AF23: =IF(ISNUMBER(SEARCH("R01",$AD23)),1,0) -> 0 | AG23: =IF(ISNUMBER(SEARCH("R02R03",$AD23)),1,0) -> 0 | AH23: =IF(ISNUMBER(SEARCH("R04",$AD23)),1,0) -> 0 | AI23: =IF(ISNUMBER(SEARCH("R05",$AD23)),1,0) -> 0 | AJ23: =IF(ISNUMBER(SEARCH("S3R06",$AD23)),1,0) -> 0 | AK23: =IF(ISNUMBER(SEARCH("R07",$AD23)),1,0) -> 0 | AL23: =IF(ISNUMBER(SEARCH("R09",$AD23)),1,0) -> 0 | AM23: =IF(ISNUMBER(SEARCH("R10",$AD23)),1,0) -> 0 | AN23: =IF(ISNUMBER(SEARCH("S5",$AD23)),1,0) -> 1 | AO23: =IF(ISNUMBER(SEARCH("S6",$AD23)),1,0) -> 0 | AP23: =IF(ISNUMBER(SEARCH("TR",$AD23)),1,0) -> 0
A24: ES-PAD-14 | B24: Cuenta básica | C24: Real Decreto 164/2019 (gratuidad CPB vulnerables) | D24: art. 5 | E24: ES_reglamento | F24: Vigente | G24: Informar_interesado | H24: E9; TR | I24: Informacion_tratamiento | J24: Acceso_inclusion | K24: En el momento de la contratación | L24: Interesado | M24: Cuenta_pago_basica | N24: Parcial | O24: informará a los clientes sobre dichas condiciones en el momento de la contratación de la cuenta de pago básica | P24: https://www.boe.es/buscar/act.php?id=BOE-A-2019-4906 | Q24: Alta | R24: Además, incluir las condiciones de gratuidad en la información general del art. 10 RDL 19/2017 y art. 8 Orden ECE/228/2019 (TR). | S24: =IF(ISNUMBER(SEARCH("E0",$H24)),1,0) -> 0 | T24: =IF(ISNUMBER(SEARCH("E1",$H24)),1,0) -> 0 | U24: =IF(ISNUMBER(SEARCH("E2",$H24)),1,0) -> 0 | V24: =IF(ISNUMBER(SEARCH("E3",$H24)),1,0) -> 0 | W24: =IF(ISNUMBER(SEARCH("E4",$H24)),1,0) -> 0 | X24: =IF(ISNUMBER(SEARCH("E5",$H24)),1,0) -> 0 | Y24: =IF(ISNUMBER(SEARCH("E6",$H24)),1,0) -> 0 | Z24: =IF(ISNUMBER(SEARCH("E7",$H24)),1,0) -> 0 | AA24: =IF(ISNUMBER(SEARCH("E8",$H24)),1,0) -> 0 | AB24: =IF(ISNUMBER(SEARCH("E9",$H24)),1,0) -> 1 | AC24: =IF(ISNUMBER(SEARCH("TR",$H24)),1,0) -> 1 | AD24: S6; TR | AE24: =IF(ISNUMBER(SEARCH("S0",$AD24)),1,0) -> 0 | AF24: =IF(ISNUMBER(SEARCH("R01",$AD24)),1,0) -> 0 | AG24: =IF(ISNUMBER(SEARCH("R02R03",$AD24)),1,0) -> 0 | AH24: =IF(ISNUMBER(SEARCH("R04",$AD24)),1,0) -> 0 | AI24: =IF(ISNUMBER(SEARCH("R05",$AD24)),1,0) -> 0 | AJ24: =IF(ISNUMBER(SEARCH("S3R06",$AD24)),1,0) -> 0 | AK24: =IF(ISNUMBER(SEARCH("R07",$AD24)),1,0) -> 0 | AL24: =IF(ISNUMBER(SEARCH("R09",$AD24)),1,0) -> 0 | AM24: =IF(ISNUMBER(SEARCH("R10",$AD24)),1,0) -> 0 | AN24: =IF(ISNUMBER(SEARCH("S5",$AD24)),1,0) -> 0 | AO24: =IF(ISNUMBER(SEARCH("S6",$AD24)),1,0) -> 1 | AP24: =IF(ISNUMBER(SEARCH("TR",$AD24)),1,0) -> 1
A25: ES-PAD-15 | B25: Cuenta básica | C25: Real Decreto 164/2019 (gratuidad CPB vulnerables) | D25: art. 7.1 | E25: ES_reglamento | F25: Vigente | G25: Conservar | H25: E8; E9 | I25: Expediente_completo | J25: Acceso_inclusion | K25: Mínimo 6 años | L25: Uso_interno | M25: Cuenta_pago_basica | N25: Si | O25: conservarán [...] durante un plazo mínimo de 6 años, la documentación señalada en los artículos 4, 5 y 6, con independencia de si la condición de gratuidad de la cuenta se ha reconocido o no | P25: https://www.boe.es/buscar/act.php?id=BOE-A-2019-4906 | Q25: Alta | R25: Art. 7.2: el cómputo se inicia desde la denegación o desde el fin de la gratuidad. Finalidad declarada: verificar el cumplimiento. | S25: =IF(ISNUMBER(SEARCH("E0",$H25)),1,0) -> 0 | T25: =IF(ISNUMBER(SEARCH("E1",$H25)),1,0) -> 0 | U25: =IF(ISNUMBER(SEARCH("E2",$H25)),1,0) -> 0 | V25: =IF(ISNUMBER(SEARCH("E3",$H25)),1,0) -> 0 | W25: =IF(ISNUMBER(SEARCH("E4",$H25)),1,0) -> 0 | X25: =IF(ISNUMBER(SEARCH("E5",$H25)),1,0) -> 0 | Y25: =IF(ISNUMBER(SEARCH("E6",$H25)),1,0) -> 0 | Z25: =IF(ISNUMBER(SEARCH("E7",$H25)),1,0) -> 0 | AA25: =IF(ISNUMBER(SEARCH("E8",$H25)),1,0) -> 1 | AB25: =IF(ISNUMBER(SEARCH("E9",$H25)),1,0) -> 1 | AC25: =IF(ISNUMBER(SEARCH("TR",$H25)),1,0) -> 0 | AD25: S5; S6 | AE25: =IF(ISNUMBER(SEARCH("S0",$AD25)),1,0) -> 0 | AF25: =IF(ISNUMBER(SEARCH("R01",$AD25)),1,0) -> 0 | AG25: =IF(ISNUMBER(SEARCH("R02R03",$AD25)),1,0) -> 0 | AH25: =IF(ISNUMBER(SEARCH("R04",$AD25)),1,0) -> 0 | AI25: =IF(ISNUMBER(SEARCH("R05",$AD25)),1,0) -> 0 | AJ25: =IF(ISNUMBER(SEARCH("S3R06",$AD25)),1,0) -> 0 | AK25: =IF(ISNUMBER(SEARCH("R07",$AD25)),1,0) -> 0 | AL25: =IF(ISNUMBER(SEARCH("R09",$AD25)),1,0) -> 0 | AM25: =IF(ISNUMBER(SEARCH("R10",$AD25)),1,0) -> 0 | AN25: =IF(ISNUMBER(SEARCH("S5",$AD25)),1,0) -> 1 | AO25: =IF(ISNUMBER(SEARCH("S6",$AD25)),1,0) -> 1 | AP25: =IF(ISNUMBER(SEARCH("TR",$AD25)),1,0) -> 0
A26: ES-TR-01 | B26: Atención al cliente ES | C26: Orden ECO/734/2004 (servicios de atención al cliente) | D26: art. 3 | E26: ES_reglamento | F26: Vigente | G26: Informar_interesado | H26: E8 | I26: Motivo_decision | J26: Reclamaciones | K26: No especificado | L26: Interesado | M26: Todas_entidades_obligadas | N26: Parcial | O26: las entidades [...] estarán obligadas a atender y resolver las quejas y reclamaciones que sus clientes les presenten, relacionadas con sus intereses y derechos legalmente reconocidos | P26: https://www.boe.es/buscar/act.php?id=BOE-A-2004-5290 | Q26: Alta | R26: Aplica a reclamaciones contra la denegación del alta (vía SAC). Orden parcialmente derogada por la Ley 10/2025, de 26 de diciembre (arts. 6 y 9 a 16, incluidos deberes de información, plazos y procedimiento); revisar Ley 10/2025. 'Clientes': alcance sobre potenciales clientes dudoso. | S26: =IF(ISNUMBER(SEARCH("E0",$H26)),1,0) -> 0 | T26: =IF(ISNUMBER(SEARCH("E1",$H26)),1,0) -> 0 | U26: =IF(ISNUMBER(SEARCH("E2",$H26)),1,0) -> 0 | V26: =IF(ISNUMBER(SEARCH("E3",$H26)),1,0) -> 0 | W26: =IF(ISNUMBER(SEARCH("E4",$H26)),1,0) -> 0 | X26: =IF(ISNUMBER(SEARCH("E5",$H26)),1,0) -> 0 | Y26: =IF(ISNUMBER(SEARCH("E6",$H26)),1,0) -> 0 | Z26: =IF(ISNUMBER(SEARCH("E7",$H26)),1,0) -> 0 | AA26: =IF(ISNUMBER(SEARCH("E8",$H26)),1,0) -> 1 | AB26: =IF(ISNUMBER(SEARCH("E9",$H26)),1,0) -> 0 | AC26: =IF(ISNUMBER(SEARCH("TR",$H26)),1,0) -> 0 | AD26: S5 | AE26: =IF(ISNUMBER(SEARCH("S0",$AD26)),1,0) -> 0 | AF26: =IF(ISNUMBER(SEARCH("R01",$AD26)),1,0) -> 0 | AG26: =IF(ISNUMBER(SEARCH("R02R03",$AD26)),1,0) -> 0 | AH26: =IF(ISNUMBER(SEARCH("R04",$AD26)),1,0) -> 0 | AI26: =IF(ISNUMBER(SEARCH("R05",$AD26)),1,0) -> 0 | AJ26: =IF(ISNUMBER(SEARCH("S3R06",$AD26)),1,0) -> 0 | AK26: =IF(ISNUMBER(SEARCH("R07",$AD26)),1,0) -> 0 | AL26: =IF(ISNUMBER(SEARCH("R09",$AD26)),1,0) -> 0 | AM26: =IF(ISNUMBER(SEARCH("R10",$AD26)),1,0) -> 0 | AN26: =IF(ISNUMBER(SEARCH("S5",$AD26)),1,0) -> 1 | AO26: =IF(ISNUMBER(SEARCH("S6",$AD26)),1,0) -> 0 | AP26: =IF(ISNUMBER(SEARCH("TR",$AD26)),1,0) -> 0
A27: ES-TR-02 | B27: Atención al cliente ES | C27: Orden ECO/734/2004 (servicios de atención al cliente) | D27: art. 17.1 | E27: ES_reglamento | F27: Vigente | G27: Registrar | H27: E8 | I27: Motivo_decision | J27: Reclamaciones | K27: Anual (primer trimestre) | L27: Uso_interno | M27: Todas_entidades_obligadas | N27: Parcial | O27: un informe explicativo del desarrollo de su función durante el ejercicio precedente, que habrá de tener el contenido mínimo siguiente: a) resumen estadístico de las quejas y reclamaciones atendidas | P27: https://www.boe.es/buscar/act.php?id=BOE-A-2004-5290 | Q27: Alta | R27: Informe anual del SAC al consejo; solo alcanza al alta en cuanto haya reclamaciones por denegación. Pertinencia marginal. | S27: =IF(ISNUMBER(SEARCH("E0",$H27)),1,0) -> 0 | T27: =IF(ISNUMBER(SEARCH("E1",$H27)),1,0) -> 0 | U27: =IF(ISNUMBER(SEARCH("E2",$H27)),1,0) -> 0 | V27: =IF(ISNUMBER(SEARCH("E3",$H27)),1,0) -> 0 | W27: =IF(ISNUMBER(SEARCH("E4",$H27)),1,0) -> 0 | X27: =IF(ISNUMBER(SEARCH("E5",$H27)),1,0) -> 0 | Y27: =IF(ISNUMBER(SEARCH("E6",$H27)),1,0) -> 0 | Z27: =IF(ISNUMBER(SEARCH("E7",$H27)),1,0) -> 0 | AA27: =IF(ISNUMBER(SEARCH("E8",$H27)),1,0) -> 1 | AB27: =IF(ISNUMBER(SEARCH("E9",$H27)),1,0) -> 0 | AC27: =IF(ISNUMBER(SEARCH("TR",$H27)),1,0) -> 0 | AD27: S5 | AE27: =IF(ISNUMBER(SEARCH("S0",$AD27)),1,0) -> 0 | AF27: =IF(ISNUMBER(SEARCH("R01",$AD27)),1,0) -> 0 | AG27: =IF(ISNUMBER(SEARCH("R02R03",$AD27)),1,0) -> 0 | AH27: =IF(ISNUMBER(SEARCH("R04",$AD27)),1,0) -> 0 | AI27: =IF(ISNUMBER(SEARCH("R05",$AD27)),1,0) -> 0 | AJ27: =IF(ISNUMBER(SEARCH("S3R06",$AD27)),1,0) -> 0 | AK27: =IF(ISNUMBER(SEARCH("R07",$AD27)),1,0) -> 0 | AL27: =IF(ISNUMBER(SEARCH("R09",$AD27)),1,0) -> 0 | AM27: =IF(ISNUMBER(SEARCH("R10",$AD27)),1,0) -> 0 | AN27: =IF(ISNUMBER(SEARCH("S5",$AD27)),1,0) -> 1 | AO27: =IF(ISNUMBER(SEARCH("S6",$AD27)),1,0) -> 0 | AP27: =IF(ISNUMBER(SEARCH("TR",$AD27)),1,0) -> 0
A28: ES-TR-03 | B28: Atención al cliente ES | C28: Orden EHA/2899/2011 (transparencia bancaria) | D28: art. 6 | E28: ES_reglamento | F28: Vigente | G28: Informar_interesado | H28: E0 | I28: Informacion_tratamiento | J28: Transparencia_consumidor | K28: Con la debida antelación y antes de quedar vinculado | L28: Interesado | M28: Todas_entidades_obligadas | N28: Si | O28: Las entidades de crédito deberán facilitar de forma gratuita al cliente de servicios bancarios toda la información precontractual que sea legalmente exigible para adoptar una decisión informada | P28: https://www.boe.es/buscar/act.php?id=BOE-A-2011-16804 | Q28: Alta | R28: Duda de ámbito: para servicios/cuentas de pago el art. 34 remite a su normativa específica (Orden ECE/1263/2019); aplicable sin duda a depósitos a la vista. Información sobre el producto. | S28: =IF(ISNUMBER(SEARCH("E0",$H28)),1,0) -> 1 | T28: =IF(ISNUMBER(SEARCH("E1",$H28)),1,0) -> 0 | U28: =IF(ISNUMBER(SEARCH("E2",$H28)),1,0) -> 0 | V28: =IF(ISNUMBER(SEARCH("E3",$H28)),1,0) -> 0 | W28: =IF(ISNUMBER(SEARCH("E4",$H28)),1,0) -> 0 | X28: =IF(ISNUMBER(SEARCH("E5",$H28)),1,0) -> 0 | Y28: =IF(ISNUMBER(SEARCH("E6",$H28)),1,0) -> 0 | Z28: =IF(ISNUMBER(SEARCH("E7",$H28)),1,0) -> 0 | AA28: =IF(ISNUMBER(SEARCH("E8",$H28)),1,0) -> 0 | AB28: =IF(ISNUMBER(SEARCH("E9",$H28)),1,0) -> 0 | AC28: =IF(ISNUMBER(SEARCH("TR",$H28)),1,0) -> 0 | AD28: S0 | AE28: =IF(ISNUMBER(SEARCH("S0",$AD28)),1,0) -> 1 | AF28: =IF(ISNUMBER(SEARCH("R01",$AD28)),1,0) -> 0 | AG28: =IF(ISNUMBER(SEARCH("R02R03",$AD28)),1,0) -> 0 | AH28: =IF(ISNUMBER(SEARCH("R04",$AD28)),1,0) -> 0 | AI28: =IF(ISNUMBER(SEARCH("R05",$AD28)),1,0) -> 0 | AJ28: =IF(ISNUMBER(SEARCH("S3R06",$AD28)),1,0) -> 0 | AK28: =IF(ISNUMBER(SEARCH("R07",$AD28)),1,0) -> 0 | AL28: =IF(ISNUMBER(SEARCH("R09",$AD28)),1,0) -> 0 | AM28: =IF(ISNUMBER(SEARCH("R10",$AD28)),1,0) -> 0 | AN28: =IF(ISNUMBER(SEARCH("S5",$AD28)),1,0) -> 0 | AO28: =IF(ISNUMBER(SEARCH("S6",$AD28)),1,0) -> 0 | AP28: =IF(ISNUMBER(SEARCH("TR",$AD28)),1,0) -> 0
A29: ES-TR-04 | B29: Atención al cliente ES | C29: Orden EHA/2899/2011 (transparencia bancaria) | D29: art. 7.1 | E29: ES_reglamento | F29: Vigente | G29: Informar_interesado | H29: E9 | I29: Expediente_completo | J29: Transparencia_consumidor | K29: No especificado | L29: Interesado | M29: Todas_entidades_obligadas | N29: No | O29: Las entidades de crédito deberán entregar al cliente el correspondiente ejemplar del documento contractual en que se formalice el servicio recibido. | P29: https://www.boe.es/buscar/act.php?id=BOE-A-2011-16804 | Q29: Alta | R29: Misma duda de ámbito que ES-TR-03. | S29: =IF(ISNUMBER(SEARCH("E0",$H29)),1,0) -> 0 | T29: =IF(ISNUMBER(SEARCH("E1",$H29)),1,0) -> 0 | U29: =IF(ISNUMBER(SEARCH("E2",$H29)),1,0) -> 0 | V29: =IF(ISNUMBER(SEARCH("E3",$H29)),1,0) -> 0 | W29: =IF(ISNUMBER(SEARCH("E4",$H29)),1,0) -> 0 | X29: =IF(ISNUMBER(SEARCH("E5",$H29)),1,0) -> 0 | Y29: =IF(ISNUMBER(SEARCH("E6",$H29)),1,0) -> 0 | Z29: =IF(ISNUMBER(SEARCH("E7",$H29)),1,0) -> 0 | AA29: =IF(ISNUMBER(SEARCH("E8",$H29)),1,0) -> 0 | AB29: =IF(ISNUMBER(SEARCH("E9",$H29)),1,0) -> 1 | AC29: =IF(ISNUMBER(SEARCH("TR",$H29)),1,0) -> 0 | AD29: S6 | AE29: =IF(ISNUMBER(SEARCH("S0",$AD29)),1,0) -> 0 | AF29: =IF(ISNUMBER(SEARCH("R01",$AD29)),1,0) -> 0 | AG29: =IF(ISNUMBER(SEARCH("R02R03",$AD29)),1,0) -> 0 | AH29: =IF(ISNUMBER(SEARCH("R04",$AD29)),1,0) -> 0 | AI29: =IF(ISNUMBER(SEARCH("R05",$AD29)),1,0) -> 0 | AJ29: =IF(ISNUMBER(SEARCH("S3R06",$AD29)),1,0) -> 0 | AK29: =IF(ISNUMBER(SEARCH("R07",$AD29)),1,0) -> 0 | AL29: =IF(ISNUMBER(SEARCH("R09",$AD29)),1,0) -> 0 | AM29: =IF(ISNUMBER(SEARCH("R10",$AD29)),1,0) -> 0 | AN29: =IF(ISNUMBER(SEARCH("S5",$AD29)),1,0) -> 0 | AO29: =IF(ISNUMBER(SEARCH("S6",$AD29)),1,0) -> 1 | AP29: =IF(ISNUMBER(SEARCH("TR",$AD29)),1,0) -> 0
A30: ES-TR-05 | B30: Atención al cliente ES | C30: Orden EHA/2899/2011 (transparencia bancaria) | D30: art. 7.2 | E30: ES_reglamento | F30: Vigente | G30: Conservar | H30: E9 | I30: Expediente_completo | J30: Transparencia_consumidor | K30: No especificado | L30: Interesado | M30: Todas_entidades_obligadas | N30: No | O30: Las entidades de crédito deberán conservar el documento contractual y poner a disposición del cliente copia del mismo siempre que éste lo solicite. | P30: https://www.boe.es/buscar/act.php?id=BOE-A-2011-16804 | Q30: Alta | R30: Misma duda de ámbito que ES-TR-03. | S30: =IF(ISNUMBER(SEARCH("E0",$H30)),1,0) -> 0 | T30: =IF(ISNUMBER(SEARCH("E1",$H30)),1,0) -> 0 | U30: =IF(ISNUMBER(SEARCH("E2",$H30)),1,0) -> 0 | V30: =IF(ISNUMBER(SEARCH("E3",$H30)),1,0) -> 0 | W30: =IF(ISNUMBER(SEARCH("E4",$H30)),1,0) -> 0 | X30: =IF(ISNUMBER(SEARCH("E5",$H30)),1,0) -> 0 | Y30: =IF(ISNUMBER(SEARCH("E6",$H30)),1,0) -> 0 | Z30: =IF(ISNUMBER(SEARCH("E7",$H30)),1,0) -> 0 | AA30: =IF(ISNUMBER(SEARCH("E8",$H30)),1,0) -> 0 | AB30: =IF(ISNUMBER(SEARCH("E9",$H30)),1,0) -> 1 | AC30: =IF(ISNUMBER(SEARCH("TR",$H30)),1,0) -> 0 | AD30: S6 | AE30: =IF(ISNUMBER(SEARCH("S0",$AD30)),1,0) -> 0 | AF30: =IF(ISNUMBER(SEARCH("R01",$AD30)),1,0) -> 0 | AG30: =IF(ISNUMBER(SEARCH("R02R03",$AD30)),1,0) -> 0 | AH30: =IF(ISNUMBER(SEARCH("R04",$AD30)),1,0) -> 0 | AI30: =IF(ISNUMBER(SEARCH("R05",$AD30)),1,0) -> 0 | AJ30: =IF(ISNUMBER(SEARCH("S3R06",$AD30)),1,0) -> 0 | AK30: =IF(ISNUMBER(SEARCH("R07",$AD30)),1,0) -> 0 | AL30: =IF(ISNUMBER(SEARCH("R09",$AD30)),1,0) -> 0 | AM30: =IF(ISNUMBER(SEARCH("R10",$AD30)),1,0) -> 0 | AN30: =IF(ISNUMBER(SEARCH("S5",$AD30)),1,0) -> 0 | AO30: =IF(ISNUMBER(SEARCH("S6",$AD30)),1,0) -> 1 | AP30: =IF(ISNUMBER(SEARCH("TR",$AD30)),1,0) -> 0
A31: ES-TR-06 | B31: Atención al cliente ES | C31: Orden EHA/2899/2011 (transparencia bancaria) | D31: art. 9 | E31: ES_reglamento | F31: Vigente | G31: Informar_interesado | H31: TR | I31: Informacion_tratamiento | J31: Transparencia_consumidor | K31: No especificado | L31: Interesado | M31: Todas_entidades_obligadas | N31: Parcial | O31: Las entidades de crédito deberán facilitar a todo cliente explicaciones adecuadas y suficientes para comprender los términos esenciales de todo servicio bancario ofertado y adoptar una decisión informada | P31: https://www.boe.es/buscar/act.php?id=BOE-A-2011-16804 | Q31: Alta | R31: Misma duda de ámbito que ES-TR-03. | S31: =IF(ISNUMBER(SEARCH("E0",$H31)),1,0) -> 0 | T31: =IF(ISNUMBER(SEARCH("E1",$H31)),1,0) -> 0 | U31: =IF(ISNUMBER(SEARCH("E2",$H31)),1,0) -> 0 | V31: =IF(ISNUMBER(SEARCH("E3",$H31)),1,0) -> 0 | W31: =IF(ISNUMBER(SEARCH("E4",$H31)),1,0) -> 0 | X31: =IF(ISNUMBER(SEARCH("E5",$H31)),1,0) -> 0 | Y31: =IF(ISNUMBER(SEARCH("E6",$H31)),1,0) -> 0 | Z31: =IF(ISNUMBER(SEARCH("E7",$H31)),1,0) -> 0 | AA31: =IF(ISNUMBER(SEARCH("E8",$H31)),1,0) -> 0 | AB31: =IF(ISNUMBER(SEARCH("E9",$H31)),1,0) -> 0 | AC31: =IF(ISNUMBER(SEARCH("TR",$H31)),1,0) -> 1 | AD31: TR | AE31: =IF(ISNUMBER(SEARCH("S0",$AD31)),1,0) -> 0 | AF31: =IF(ISNUMBER(SEARCH("R01",$AD31)),1,0) -> 0 | AG31: =IF(ISNUMBER(SEARCH("R02R03",$AD31)),1,0) -> 0 | AH31: =IF(ISNUMBER(SEARCH("R04",$AD31)),1,0) -> 0 | AI31: =IF(ISNUMBER(SEARCH("R05",$AD31)),1,0) -> 0 | AJ31: =IF(ISNUMBER(SEARCH("S3R06",$AD31)),1,0) -> 0 | AK31: =IF(ISNUMBER(SEARCH("R07",$AD31)),1,0) -> 0 | AL31: =IF(ISNUMBER(SEARCH("R09",$AD31)),1,0) -> 0 | AM31: =IF(ISNUMBER(SEARCH("R10",$AD31)),1,0) -> 0 | AN31: =IF(ISNUMBER(SEARCH("S5",$AD31)),1,0) -> 0 | AO31: =IF(ISNUMBER(SEARCH("S6",$AD31)),1,0) -> 0 | AP31: =IF(ISNUMBER(SEARCH("TR",$AD31)),1,0) -> 1
A32: ES-TR-07 | B32: Atención al cliente ES | C32: Ley 44/2002, en la redacción de la Ley 10/2025 (servicios de atención a la clientela) | D32: DF 2.ª; art. 29.1 párr. 1 Ley 44/2002 | E32: ES_ley | F32: En_vigor_2025-12-28_adaptacion_hasta_2026-12-28 | G32: Informar_interesado | H32: E8 | I32: Motivo_decision | J32: Reclamaciones | K32: No especificado | L32: Interesado | M32: Todas_entidades_obligadas | N32: Parcial | O32: estarán obligadas a atender y resolver las quejas y reclamaciones que los usuarios de servicios financieros puedan presentar, relacionados con sus intereses y derechos legalmente reconocidos | P32: https://www.boe.es/buscar/act.php?id=BOE-A-2025-26698 | Q32: Alta | R32: Sustituye la redacción anterior ('clientes') por 'usuarios de servicios financieros', lo que favorece incluir al solicitante denegado. Deben contar con un departamento o servicio de atención a la clientela. Ley 10/2025 (BOE núm. 312, de 27-12-2025) en vigor el 28-12-2025; plazo de adaptación de doce meses (DT única.1), de ahí 2026-12-28. Que ese plazo alcance a las modificaciones de la Ley 44/2002 (DF 2.ª) es interpretable. Art. 2.5: los servicios financieros se rigen por su normativa sectorial; la Ley 10/2025 es supletoria. Deroga los arts. 6 y 9 a 16 de la Orden ECO/734/2004. | S32: =IF(ISNUMBER(SEARCH("E0",$H32)),1,0) -> 0 | T32: =IF(ISNUMBER(SEARCH("E1",$H32)),1,0) -> 0 | U32: =IF(ISNUMBER(SEARCH("E2",$H32)),1,0) -> 0 | V32: =IF(ISNUMBER(SEARCH("E3",$H32)),1,0) -> 0 | W32: =IF(ISNUMBER(SEARCH("E4",$H32)),1,0) -> 0 | X32: =IF(ISNUMBER(SEARCH("E5",$H32)),1,0) -> 0 | Y32: =IF(ISNUMBER(SEARCH("E6",$H32)),1,0) -> 0 | Z32: =IF(ISNUMBER(SEARCH("E7",$H32)),1,0) -> 0 | AA32: =IF(ISNUMBER(SEARCH("E8",$H32)),1,0) -> 1 | AB32: =IF(ISNUMBER(SEARCH("E9",$H32)),1,0) -> 0 | AC32: =IF(ISNUMBER(SEARCH("TR",$H32)),1,0) -> 0 | AD32: S5 | AE32: =IF(ISNUMBER(SEARCH("S0",$AD32)),1,0) -> 0 | AF32: =IF(ISNUMBER(SEARCH("R01",$AD32)),1,0) -> 0 | AG32: =IF(ISNUMBER(SEARCH("R02R03",$AD32)),1,0) -> 0 | AH32: =IF(ISNUMBER(SEARCH("R04",$AD32)),1,0) -> 0 | AI32: =IF(ISNUMBER(SEARCH("R05",$AD32)),1,0) -> 0 | AJ32: =IF(ISNUMBER(SEARCH("S3R06",$AD32)),1,0) -> 0 | AK32: =IF(ISNUMBER(SEARCH("R07",$AD32)),1,0) -> 0 | AL32: =IF(ISNUMBER(SEARCH("R09",$AD32)),1,0) -> 0 | AM32: =IF(ISNUMBER(SEARCH("R10",$AD32)),1,0) -> 0 | AN32: =IF(ISNUMBER(SEARCH("S5",$AD32)),1,0) -> 1 | AO32: =IF(ISNUMBER(SEARCH("S6",$AD32)),1,0) -> 0 | AP32: =IF(ISNUMBER(SEARCH("TR",$AD32)),1,0) -> 0
A33: ES-TR-08 | B33: Atención al cliente ES | C33: Ley 44/2002, en la redacción de la Ley 10/2025 (servicios de atención a la clientela) | D33: DF 2.ª; art. 29.1 Ley 44/2002 (párrafos sobre prestación personalizada) | E33: ES_ley | F33: En_vigor_2025-12-28_adaptacion_hasta_2026-12-28 | G33: Supervision_humana | H33: E8; TR | I33: Intervencion_humana | J33: Acceso_inclusion | K33: No especificado | L33: Interesado | M33: Todas_entidades_obligadas | N33: Parcial | O33: deberá disponerse por las entidades de los recursos adecuados que, a través de la atención telefónica, puedan prestar una atención personalizada específica a personas vulnerables o en riesgo de exclusión financiera | P33: https://www.boe.es/buscar/act.php?id=BOE-A-2025-26698 | Q33: Alta | R33: También prohíbe los contestadores automáticos u otros medios análogos como medio exclusivo de atención. La prestación personalizada considera, entre otros, la condición de persona extranjera y su situación administrativa y las competencias digitales. Ley 10/2025 (BOE núm. 312, de 27-12-2025) en vigor el 28-12-2025; plazo de adaptación de doce meses (DT única.1), de ahí 2026-12-28. Que ese plazo alcance a las modificaciones de la Ley 44/2002 (DF 2.ª) es interpretable. Art. 2.5: los servicios financieros se rigen por su normativa sectorial; la Ley 10/2025 es supletoria. Deroga los arts. 6 y 9 a 16 de la Orden ECO/734/2004. | S33: =IF(ISNUMBER(SEARCH("E0",$H33)),1,0) -> 0 | T33: =IF(ISNUMBER(SEARCH("E1",$H33)),1,0) -> 0 | U33: =IF(ISNUMBER(SEARCH("E2",$H33)),1,0) -> 0 | V33: =IF(ISNUMBER(SEARCH("E3",$H33)),1,0) -> 0 | W33: =IF(ISNUMBER(SEARCH("E4",$H33)),1,0) -> 0 | X33: =IF(ISNUMBER(SEARCH("E5",$H33)),1,0) -> 0 | Y33: =IF(ISNUMBER(SEARCH("E6",$H33)),1,0) -> 0 | Z33: =IF(ISNUMBER(SEARCH("E7",$H33)),1,0) -> 0 | AA33: =IF(ISNUMBER(SEARCH("E8",$H33)),1,0) -> 1 | AB33: =IF(ISNUMBER(SEARCH("E9",$H33)),1,0) -> 0 | AC33: =IF(ISNUMBER(SEARCH("TR",$H33)),1,0) -> 1 | AD33: S5; TR | AE33: =IF(ISNUMBER(SEARCH("S0",$AD33)),1,0) -> 0 | AF33: =IF(ISNUMBER(SEARCH("R01",$AD33)),1,0) -> 0 | AG33: =IF(ISNUMBER(SEARCH("R02R03",$AD33)),1,0) -> 0 | AH33: =IF(ISNUMBER(SEARCH("R04",$AD33)),1,0) -> 0 | AI33: =IF(ISNUMBER(SEARCH("R05",$AD33)),1,0) -> 0 | AJ33: =IF(ISNUMBER(SEARCH("S3R06",$AD33)),1,0) -> 0 | AK33: =IF(ISNUMBER(SEARCH("R07",$AD33)),1,0) -> 0 | AL33: =IF(ISNUMBER(SEARCH("R09",$AD33)),1,0) -> 0 | AM33: =IF(ISNUMBER(SEARCH("R10",$AD33)),1,0) -> 0 | AN33: =IF(ISNUMBER(SEARCH("S5",$AD33)),1,0) -> 1 | AO33: =IF(ISNUMBER(SEARCH("S6",$AD33)),1,0) -> 0 | AP33: =IF(ISNUMBER(SEARCH("TR",$AD33)),1,0) -> 1
A34: ES-TR-09 | B34: Atención al cliente ES | C34: Ley 44/2002, en la redacción de la Ley 10/2025 (servicios de atención a la clientela) | D34: DF 2.ª; art. 29.5.b) Ley 44/2002 | E34: ES_ley | F34: En_vigor_2025-12-28_adaptacion_hasta_2026-12-28 | G34: Informar_interesado | H34: TR | I34: Motivo_decision | J34: Reclamaciones | K34: Un mes desde la presentación (servicios de pago: art. 69 RDL 19/2018) | L34: Interesado | M34: Todas_entidades_obligadas | N34: Parcial | O34: La obligación por parte de la entidad de atender y resolver las quejas y reclamaciones presentadas por su clientela, en el plazo de un mes desde su presentación. | P34: https://www.boe.es/buscar/act.php?id=BOE-A-2025-26698 | Q34: Alta | R34: Información que debe figurar en todas las oficinas y en la web (apdo. 5, letras a-h: existencia del servicio, plazos, canales, registro y constancia, seguimiento, medios de resolución, reglamento, horario). Dato real: información sobre vías de reclamación (sin valor exacto en la lista cerrada). Ley 10/2025 (BOE núm. 312, de 27-12-2025) en vigor el 28-12-2025; plazo de adaptación de doce meses (DT única.1), de ahí 2026-12-28. Que ese plazo alcance a las modificaciones de la Ley 44/2002 (DF 2.ª) es interpretable. Art. 2.5: los servicios financieros se rigen por su normativa sectorial; la Ley 10/2025 es supletoria. Deroga los arts. 6 y 9 a 16 de la Orden ECO/734/2004. | S34: =IF(ISNUMBER(SEARCH("E0",$H34)),1,0) -> 0 | T34: =IF(ISNUMBER(SEARCH("E1",$H34)),1,0) -> 0 | U34: =IF(ISNUMBER(SEARCH("E2",$H34)),1,0) -> 0 | V34: =IF(ISNUMBER(SEARCH("E3",$H34)),1,0) -> 0 | W34: =IF(ISNUMBER(SEARCH("E4",$H34)),1,0) -> 0 | X34: =IF(ISNUMBER(SEARCH("E5",$H34)),1,0) -> 0 | Y34: =IF(ISNUMBER(SEARCH("E6",$H34)),1,0) -> 0 | Z34: =IF(ISNUMBER(SEARCH("E7",$H34)),1,0) -> 0 | AA34: =IF(ISNUMBER(SEARCH("E8",$H34)),1,0) -> 0 | AB34: =IF(ISNUMBER(SEARCH("E9",$H34)),1,0) -> 0 | AC34: =IF(ISNUMBER(SEARCH("TR",$H34)),1,0) -> 1 | AD34: TR | AE34: =IF(ISNUMBER(SEARCH("S0",$AD34)),1,0) -> 0 | AF34: =IF(ISNUMBER(SEARCH("R01",$AD34)),1,0) -> 0 | AG34: =IF(ISNUMBER(SEARCH("R02R03",$AD34)),1,0) -> 0 | AH34: =IF(ISNUMBER(SEARCH("R04",$AD34)),1,0) -> 0 | AI34: =IF(ISNUMBER(SEARCH("R05",$AD34)),1,0) -> 0 | AJ34: =IF(ISNUMBER(SEARCH("S3R06",$AD34)),1,0) -> 0 | AK34: =IF(ISNUMBER(SEARCH("R07",$AD34)),1,0) -> 0 | AL34: =IF(ISNUMBER(SEARCH("R09",$AD34)),1,0) -> 0 | AM34: =IF(ISNUMBER(SEARCH("R10",$AD34)),1,0) -> 0 | AN34: =IF(ISNUMBER(SEARCH("S5",$AD34)),1,0) -> 0 | AO34: =IF(ISNUMBER(SEARCH("S6",$AD34)),1,0) -> 0 | AP34: =IF(ISNUMBER(SEARCH("TR",$AD34)),1,0) -> 1
A35: ES-TR-10 | B35: Atención al cliente ES | C35: Ley 44/2002, en la redacción de la Ley 10/2025 (servicios de atención a la clientela) | D35: DF 2.ª; art. 29 quater.1 Ley 44/2002 | E35: ES_ley | F35: En_vigor_2025-12-28_adaptacion_hasta_2026-12-28 | G35: Registrar | H35: E8 | I35: Expediente_completo | J35: Reclamaciones | K35: No especificado | L35: Uso_interno | M35: Todas_entidades_obligadas | N35: Parcial | O35: se deberá acusar recibo por escrito, en papel o en cualquier otro soporte duradero, y dejar constancia del contenido, la hora y la fecha de presentación a efectos del cómputo de dicho plazo. | P35: https://www.boe.es/buscar/act.php?id=BOE-A-2025-26698 | Q35: Alta | R35: Además: asignar una clave identificativa comunicada al reclamante para el seguimiento y abrir expediente. Registro de la reclamación, no del alta en sí. Ley 10/2025 (BOE núm. 312, de 27-12-2025) en vigor el 28-12-2025; plazo de adaptación de doce meses (DT única.1), de ahí 2026-12-28. Que ese plazo alcance a las modificaciones de la Ley 44/2002 (DF 2.ª) es interpretable. Art. 2.5: los servicios financieros se rigen por su normativa sectorial; la Ley 10/2025 es supletoria. Deroga los arts. 6 y 9 a 16 de la Orden ECO/734/2004. | S35: =IF(ISNUMBER(SEARCH("E0",$H35)),1,0) -> 0 | T35: =IF(ISNUMBER(SEARCH("E1",$H35)),1,0) -> 0 | U35: =IF(ISNUMBER(SEARCH("E2",$H35)),1,0) -> 0 | V35: =IF(ISNUMBER(SEARCH("E3",$H35)),1,0) -> 0 | W35: =IF(ISNUMBER(SEARCH("E4",$H35)),1,0) -> 0 | X35: =IF(ISNUMBER(SEARCH("E5",$H35)),1,0) -> 0 | Y35: =IF(ISNUMBER(SEARCH("E6",$H35)),1,0) -> 0 | Z35: =IF(ISNUMBER(SEARCH("E7",$H35)),1,0) -> 0 | AA35: =IF(ISNUMBER(SEARCH("E8",$H35)),1,0) -> 1 | AB35: =IF(ISNUMBER(SEARCH("E9",$H35)),1,0) -> 0 | AC35: =IF(ISNUMBER(SEARCH("TR",$H35)),1,0) -> 0 | AD35: S5 | AE35: =IF(ISNUMBER(SEARCH("S0",$AD35)),1,0) -> 0 | AF35: =IF(ISNUMBER(SEARCH("R01",$AD35)),1,0) -> 0 | AG35: =IF(ISNUMBER(SEARCH("R02R03",$AD35)),1,0) -> 0 | AH35: =IF(ISNUMBER(SEARCH("R04",$AD35)),1,0) -> 0 | AI35: =IF(ISNUMBER(SEARCH("R05",$AD35)),1,0) -> 0 | AJ35: =IF(ISNUMBER(SEARCH("S3R06",$AD35)),1,0) -> 0 | AK35: =IF(ISNUMBER(SEARCH("R07",$AD35)),1,0) -> 0 | AL35: =IF(ISNUMBER(SEARCH("R09",$AD35)),1,0) -> 0 | AM35: =IF(ISNUMBER(SEARCH("R10",$AD35)),1,0) -> 0 | AN35: =IF(ISNUMBER(SEARCH("S5",$AD35)),1,0) -> 1 | AO35: =IF(ISNUMBER(SEARCH("S6",$AD35)),1,0) -> 0 | AP35: =IF(ISNUMBER(SEARCH("TR",$AD35)),1,0) -> 0
... A41: AMLR-01 | B41: AML | C41: Reglamento (UE) 2024/1624 (AMLR) | D41: art. 19.1.a) | E41: UE_reglamento | F41: Aplicable_desde_2027-07-10 | G41: Registrar | H41: E0; E4; E9 | I41: Identidad | J41: Diligencia_debida_AML | K41: No especificado | L41: Uso_interno | M41: Todas_entidades_obligadas | N41: Parcial | O41: Las entidades obligadas aplicarán medidas de diligencia debida con respecto al cliente en cualquiera de las circunstancias siguientes: a) al establecer una relación de negocios; | P41: https://eur-lex.europa.eu/legal-content/ES/TXT/HTML/?uri=CELEX:32024R1624 | Q41: Alta | R41: Disparador de la diligencia debida en el alta. Las letras e) y f) (dudas sobre datos o sobre si quien interactúa es el cliente) también aplican durante el alta. | S41: =IF(ISNUMBER(SEARCH("E0",$H41)),1,0) -> 1 | T41: =IF(ISNUMBER(SEARCH("E1",$H41)),1,0) -> 0 | U41: =IF(ISNUMBER(SEARCH("E2",$H41)),1,0) -> 0 | V41: =IF(ISNUMBER(SEARCH("E3",$H41)),1,0) -> 0 | W41: =IF(ISNUMBER(SEARCH("E4",$H41)),1,0) -> 1 | X41: =IF(ISNUMBER(SEARCH("E5",$H41)),1,0) -> 0 | Y41: =IF(ISNUMBER(SEARCH("E6",$H41)),1,0) -> 0 | Z41: =IF(ISNUMBER(SEARCH("E7",$H41)),1,0) -> 0 | AA41: =IF(ISNUMBER(SEARCH("E8",$H41)),1,0) -> 0 | AB41: =IF(ISNUMBER(SEARCH("E9",$H41)),1,0) -> 1 | AC41: =IF(ISNUMBER(SEARCH("TR",$H41)),1,0) -> 0 | AD41: S0; R05; S6 | AE41: =IF(ISNUMBER(SEARCH("S0",$AD41)),1,0) -> 1 | AF41: =IF(ISNUMBER(SEARCH("R01",$AD41)),1,0) -> 0 | AG41: =IF(ISNUMBER(SEARCH("R02R03",$AD41)),1,0) -> 0 | AH41: =IF(ISNUMBER(SEARCH("R04",$AD41)),1,0) -> 0 | AI41: =IF(ISNUMBER(SEARCH("R05",$AD41)),1,0) -> 1 | AJ41: =IF(ISNUMBER(SEARCH("S3R06",$AD41)),1,0) -> 0 | AK41: =IF(ISNUMBER(SEARCH("R07",$AD41)),1,0) -> 0 | AL41: =IF(ISNUMBER(SEARCH("R09",$AD41)),1,0) -> 0 | AM41: =IF(ISNUMBER(SEARCH("R10",$AD41)),1,0) -> 0 | AN41: =IF(ISNUMBER(SEARCH("S5",$AD41)),1,0) -> 0 | AO41: =IF(ISNUMBER(SEARCH("S6",$AD41)),1,0) -> 1 | AP41: =IF(ISNUMBER(SEARCH("TR",$AD41)),1,0) -> 0
A42: AMLR-02 | B42: AML | C42: Reglamento (UE) 2024/1624 (AMLR) | D42: art. 20.1.a) | E42: UE_reglamento | F42: Aplicable_desde_2027-07-10 | G42: Registrar | H42: E0; E3; E4; E9 | I42: Identidad | J42: Diligencia_debida_AML | K42: No especificado | L42: Uso_interno | M42: Todas_entidades_obligadas | N42: Parcial | O42: A efectos de realizar el procedimiento de diligencia debida con respecto al cliente, las entidades obligadas aplicarán las siguientes medidas: a) identificar al cliente y comprobar su identidad; | P42: https://eur-lex.europa.eu/legal-content/ES/TXT/HTML/?uri=CELEX:32024R1624 | Q42: Alta | S42: =IF(ISNUMBER(SEARCH("E0",$H42)),1,0) -> 1 | T42: =IF(ISNUMBER(SEARCH("E1",$H42)),1,0) -> 0 | U42: =IF(ISNUMBER(SEARCH("E2",$H42)),1,0) -> 0 | V42: =IF(ISNUMBER(SEARCH("E3",$H42)),1,0) -> 1 | W42: =IF(ISNUMBER(SEARCH("E4",$H42)),1,0) -> 1 | X42: =IF(ISNUMBER(SEARCH("E5",$H42)),1,0) -> 0 | Y42: =IF(ISNUMBER(SEARCH("E6",$H42)),1,0) -> 0 | Z42: =IF(ISNUMBER(SEARCH("E7",$H42)),1,0) -> 0 | AA42: =IF(ISNUMBER(SEARCH("E8",$H42)),1,0) -> 0 | AB42: =IF(ISNUMBER(SEARCH("E9",$H42)),1,0) -> 1 | AC42: =IF(ISNUMBER(SEARCH("TR",$H42)),1,0) -> 0 | AD42: S0; R04; R05; S6 | AE42: =IF(ISNUMBER(SEARCH("S0",$AD42)),1,0) -> 1 | AF42: =IF(ISNUMBER(SEARCH("R01",$AD42)),1,0) -> 0 | AG42: =IF(ISNUMBER(SEARCH("R02R03",$AD42)),1,0) -> 0 | AH42: =IF(ISNUMBER(SEARCH("R04",$AD42)),1,0) -> 1 | AI42: =IF(ISNUMBER(SEARCH("R05",$AD42)),1,0) -> 1 | AJ42: =IF(ISNUMBER(SEARCH("S3R06",$AD42)),1,0) -> 0 | AK42: =IF(ISNUMBER(SEARCH("R07",$AD42)),1,0) -> 0 | AL42: =IF(ISNUMBER(SEARCH("R09",$AD42)),1,0) -> 0 | AM42: =IF(ISNUMBER(SEARCH("R10",$AD42)),1,0) -> 0 | AN42: =IF(ISNUMBER(SEARCH("S5",$AD42)),1,0) -> 0 | AO42: =IF(ISNUMBER(SEARCH("S6",$AD42)),1,0) -> 1 | AP42: =IF(ISNUMBER(SEARCH("TR",$AD42)),1,0) -> 0
A43: AMLR-03 | B43: AML | C43: Reglamento (UE) 2024/1624 (AMLR) | D43: art. 25 | E43: UE_reglamento | F43: Aplicable_desde_2027-07-10 | G43: Evaluar_riesgo | H43: E0; E4; E9 | I43: Evaluacion_riesgo | J43: Diligencia_debida_AML | K43: No especificado | L43: Uso_interno | M43: Todas_entidades_obligadas | N43: Parcial | O43: Antes de establecer una relación de negocios o realizar una operación ocasional, las entidades obligadas se asegurarán de comprender su propósito y su índole prevista. | P43: https://eur-lex.europa.eu/legal-content/ES/TXT/HTML/?uri=CELEX:32024R1624 | Q43: Alta | R43: Información a obtener según proceda: propósito, cantidad estimada de actividad, origen y destino de fondos, ocupación (letras a-e). Desarrolla el art. 20.1.c). | S43: =IF(ISNUMBER(SEARCH("E0",$H43)),1,0) -> 1 | T43: =IF(ISNUMBER(SEARCH("E1",$H43)),1,0) -> 0 | U43: =IF(ISNUMBER(SEARCH("E2",$H43)),1,0) -> 0 | V43: =IF(ISNUMBER(SEARCH("E3",$H43)),1,0) -> 0 | W43: =IF(ISNUMBER(SEARCH("E4",$H43)),1,0) -> 1 | X43: =IF(ISNUMBER(SEARCH("E5",$H43)),1,0) -> 0 | Y43: =IF(ISNUMBER(SEARCH("E6",$H43)),1,0) -> 0 | Z43: =IF(ISNUMBER(SEARCH("E7",$H43)),1,0) -> 0 | AA43: =IF(ISNUMBER(SEARCH("E8",$H43)),1,0) -> 0 | AB43: =IF(ISNUMBER(SEARCH("E9",$H43)),1,0) -> 1 | AC43: =IF(ISNUMBER(SEARCH("TR",$H43)),1,0) -> 0 | AD43: S0; R05; S6 | AE43: =IF(ISNUMBER(SEARCH("S0",$AD43)),1,0) -> 1 | AF43: =IF(ISNUMBER(SEARCH("R01",$AD43)),1,0) -> 0 | AG43: =IF(ISNUMBER(SEARCH("R02R03",$AD43)),1,0) -> 0 | AH43: =IF(ISNUMBER(SEARCH("R04",$AD43)),1,0) -> 0 | AI43: =IF(ISNUMBER(SEARCH("R05",$AD43)),1,0) -> 1 | AJ43: =IF(ISNUMBER(SEARCH("S3R06",$AD43)),1,0) -> 0 | AK43: =IF(ISNUMBER(SEARCH("R07",$AD43)),1,0) -> 0 | AL43: =IF(ISNUMBER(SEARCH("R09",$AD43)),1,0) -> 0 | AM43: =IF(ISNUMBER(SEARCH("R10",$AD43)),1,0) -> 0 | AN43: =IF(ISNUMBER(SEARCH("S5",$AD43)),1,0) -> 0 | AO43: =IF(ISNUMBER(SEARCH("S6",$AD43)),1,0) -> 1 | AP43: =IF(ISNUMBER(SEARCH("TR",$AD43)),1,0) -> 0
A44: AMLR-04 | B44: AML | C44: Reglamento (UE) 2024/1624 (AMLR) | D44: art. 20.1.d) | E44: UE_reglamento | F44: Aplicable_desde_2027-07-10 | G44: Evaluar_riesgo | H44: E4; E5; E9 | I44: Resultado_verificacion | J44: Diligencia_debida_AML | K44: No especificado | L44: Uso_interno | M44: Todas_entidades_obligadas | N44: Parcial | O44: comprobar si el cliente o los titulares reales sean objeto de sanciones financieras específicas | P44: https://eur-lex.europa.eu/legal-content/ES/TXT/HTML/?uri=CELEX:32024R1624 | Q44: Alta | R44: Cribado de sanciones como medida de diligencia debida en el alta. | S44: =IF(ISNUMBER(SEARCH("E0",$H44)),1,0) -> 0 | T44: =IF(ISNUMBER(SEARCH("E1",$H44)),1,0) -> 0 | U44: =IF(ISNUMBER(SEARCH("E2",$H44)),1,0) -> 0 | V44: =IF(ISNUMBER(SEARCH("E3",$H44)),1,0) -> 0 | W44: =IF(ISNUMBER(SEARCH("E4",$H44)),1,0) -> 1 | X44: =IF(ISNUMBER(SEARCH("E5",$H44)),1,0) -> 1 | Y44: =IF(ISNUMBER(SEARCH("E6",$H44)),1,0) -> 0 | Z44: =IF(ISNUMBER(SEARCH("E7",$H44)),1,0) -> 0 | AA44: =IF(ISNUMBER(SEARCH("E8",$H44)),1,0) -> 0 | AB44: =IF(ISNUMBER(SEARCH("E9",$H44)),1,0) -> 1 | AC44: =IF(ISNUMBER(SEARCH("TR",$H44)),1,0) -> 0 | AD44: R05; S3R06; S6 | AE44: =IF(ISNUMBER(SEARCH("S0",$AD44)),1,0) -> 0 | AF44: =IF(ISNUMBER(SEARCH("R01",$AD44)),1,0) -> 0 | AG44: =IF(ISNUMBER(SEARCH("R02R03",$AD44)),1,0) -> 0 | AH44: =IF(ISNUMBER(SEARCH("R04",$AD44)),1,0) -> 0 | AI44: =IF(ISNUMBER(SEARCH("R05",$AD44)),1,0) -> 1 | AJ44: =IF(ISNUMBER(SEARCH("S3R06",$AD44)),1,0) -> 1 | AK44: =IF(ISNUMBER(SEARCH("R07",$AD44)),1,0) -> 0 | AL44: =IF(ISNUMBER(SEARCH("R09",$AD44)),1,0) -> 0 | AM44: =IF(ISNUMBER(SEARCH("R10",$AD44)),1,0) -> 0 | AN44: =IF(ISNUMBER(SEARCH("S5",$AD44)),1,0) -> 0 | AO44: =IF(ISNUMBER(SEARCH("S6",$AD44)),1,0) -> 1 | AP44: =IF(ISNUMBER(SEARCH("TR",$AD44)),1,0) -> 0
A45: AMLR-05 | B45: AML | C45: Reglamento (UE) 2024/1624 (AMLR) | D45: art. 20.1.g) | E45: UE_reglamento | F45: Aplicable_desde_2027-07-10 | G45: Evaluar_riesgo | H45: E4; E5; E9 | I45: Resultado_verificacion | J45: Diligencia_debida_AML | K45: No especificado | L45: Uso_interno | M45: Todas_entidades_obligadas | N45: Parcial | O45: determinar si el cliente, el titular real del cliente y, en su caso, la persona o personas en cuyo nombre o beneficio se lleve a cabo una operación o actividad son personas del medio político | P45: https://eur-lex.europa.eu/legal-content/ES/TXT/HTML/?uri=CELEX:32024R1624 | Q45: Alta | R45: Determinación PEP (incluye familiares y allegados). | S45: =IF(ISNUMBER(SEARCH("E0",$H45)),1,0) -> 0 | T45: =IF(ISNUMBER(SEARCH("E1",$H45)),1,0) -> 0 | U45: =IF(ISNUMBER(SEARCH("E2",$H45)),1,0) -> 0 | V45: =IF(ISNUMBER(SEARCH("E3",$H45)),1,0) -> 0 | W45: =IF(ISNUMBER(SEARCH("E4",$H45)),1,0) -> 1 | X45: =IF(ISNUMBER(SEARCH("E5",$H45)),1,0) -> 1 | Y45: =IF(ISNUMBER(SEARCH("E6",$H45)),1,0) -> 0 | Z45: =IF(ISNUMBER(SEARCH("E7",$H45)),1,0) -> 0 | AA45: =IF(ISNUMBER(SEARCH("E8",$H45)),1,0) -> 0 | AB45: =IF(ISNUMBER(SEARCH("E9",$H45)),1,0) -> 1 | AC45: =IF(ISNUMBER(SEARCH("TR",$H45)),1,0) -> 0 | AD45: R05; S3R06; S6 | AE45: =IF(ISNUMBER(SEARCH("S0",$AD45)),1,0) -> 0 | AF45: =IF(ISNUMBER(SEARCH("R01",$AD45)),1,0) -> 0 | AG45: =IF(ISNUMBER(SEARCH("R02R03",$AD45)),1,0) -> 0 | AH45: =IF(ISNUMBER(SEARCH("R04",$AD45)),1,0) -> 0 | AI45: =IF(ISNUMBER(SEARCH("R05",$AD45)),1,0) -> 1 | AJ45: =IF(ISNUMBER(SEARCH("S3R06",$AD45)),1,0) -> 1 | AK45: =IF(ISNUMBER(SEARCH("R07",$AD45)),1,0) -> 0 | AL45: =IF(ISNUMBER(SEARCH("R09",$AD45)),1,0) -> 0 | AM45: =IF(ISNUMBER(SEARCH("R10",$AD45)),1,0) -> 0 | AN45: =IF(ISNUMBER(SEARCH("S5",$AD45)),1,0) -> 0 | AO45: =IF(ISNUMBER(SEARCH("S6",$AD45)),1,0) -> 1 | AP45: =IF(ISNUMBER(SEARCH("TR",$AD45)),1,0) -> 0
A46: AMLR-06 | B46: AML | C46: Reglamento (UE) 2024/1624 (AMLR) | D46: art. 20.2 | E46: UE_reglamento | F46: Aplicable_desde_2027-07-10 | G46: Evaluar_riesgo | H46: E0; E5; E9 | I46: Evaluacion_riesgo | J46: Diligencia_debida_AML | K46: No especificado | L46: Uso_interno | M46: Todas_entidades_obligadas | N46: Parcial | O46: Las entidades obligadas determinarán el alcance de las medidas a que se refiere el apartado 1 sobre la base de un análisis individual de los riesgos de blanqueo de capitales y financiación del terrorismo | P46: https://eur-lex.europa.eu/legal-content/ES/TXT/HTML/?uri=CELEX:32024R1624 | Q46: Alta | R46: Párr. 2: riesgo mayor obliga a medidas reforzadas (sección 4); riesgo menor permite simplificadas (sección 3). Factores en anexos I a III. | S46: =IF(ISNUMBER(SEARCH("E0",$H46)),1,0) -> 1 | T46: =IF(ISNUMBER(SEARCH("E1",$H46)),1,0) -> 0 | U46: =IF(ISNUMBER(SEARCH("E2",$H46)),1,0) -> 0 | V46: =IF(ISNUMBER(SEARCH("E3",$H46)),1,0) -> 0 | W46: =IF(ISNUMBER(SEARCH("E4",$H46)),1,0) -> 0 | X46: =IF(ISNUMBER(SEARCH("E5",$H46)),1,0) -> 1 | Y46: =IF(ISNUMBER(SEARCH("E6",$H46)),1,0) -> 0 | Z46: =IF(ISNUMBER(SEARCH("E7",$H46)),1,0) -> 0 | AA46: =IF(ISNUMBER(SEARCH("E8",$H46)),1,0) -> 0 | AB46: =IF(ISNUMBER(SEARCH("E9",$H46)),1,0) -> 1 | AC46: =IF(ISNUMBER(SEARCH("TR",$H46)),1,0) -> 0 | AD46: S0; S3R06; S6 | AE46: =IF(ISNUMBER(SEARCH("S0",$AD46)),1,0) -> 1 | AF46: =IF(ISNUMBER(SEARCH("R01",$AD46)),1,0) -> 0 | AG46: =IF(ISNUMBER(SEARCH("R02R03",$AD46)),1,0) -> 0 | AH46: =IF(ISNUMBER(SEARCH("R04",$AD46)),1,0) -> 0 | AI46: =IF(ISNUMBER(SEARCH("R05",$AD46)),1,0) -> 0 | AJ46: =IF(ISNUMBER(SEARCH("S3R06",$AD46)),1,0) -> 1 | AK46: =IF(ISNUMBER(SEARCH("R07",$AD46)),1,0) -> 0 | AL46: =IF(ISNUMBER(SEARCH("R09",$AD46)),1,0) -> 0 | AM46: =IF(ISNUMBER(SEARCH("R10",$AD46)),1,0) -> 0 | AN46: =IF(ISNUMBER(SEARCH("S5",$AD46)),1,0) -> 0 | AO46: =IF(ISNUMBER(SEARCH("S6",$AD46)),1,0) -> 1 | AP46: =IF(ISNUMBER(SEARCH("TR",$AD46)),1,0) -> 0
A47: AMLR-07 | B47: AML | C47: Reglamento (UE) 2024/1624 (AMLR) | D47: art. 20.4 | E47: UE_reglamento | F47: Aplicable_desde_2027-07-10 | G47: Registrar | H47: TR | I47: Evaluacion_riesgo | J47: Diligencia_debida_AML | K47: No especificado | L47: Autoridad_AML | M47: Todas_entidades_obligadas | N47: Parcial | O47: Las entidades obligadas deberán estar siempre en condiciones de demostrar a sus supervisores que las medidas adoptadas son adecuadas en vista de los riesgos detectados | P47: https://eur-lex.europa.eu/legal-content/ES/TXT/HTML/?uri=CELEX:32024R1624 | Q47: Alta | R47: Obligación de demostrabilidad: exige documentar la evaluación de riesgo y las medidas aplicadas. | S47: =IF(ISNUMBER(SEARCH("E0",$H47)),1,0) -> 0 | T47: =IF(ISNUMBER(SEARCH("E1",$H47)),1,0) -> 0 | U47: =IF(ISNUMBER(SEARCH("E2",$H47)),1,0) -> 0 | V47: =IF(ISNUMBER(SEARCH("E3",$H47)),1,0) -> 0 | W47: =IF(ISNUMBER(SEARCH("E4",$H47)),1,0) -> 0 | X47: =IF(ISNUMBER(SEARCH("E5",$H47)),1,0) -> 0 | Y47: =IF(ISNUMBER(SEARCH("E6",$H47)),1,0) -> 0 | Z47: =IF(ISNUMBER(SEARCH("E7",$H47)),1,0) -> 0 | AA47: =IF(ISNUMBER(SEARCH("E8",$H47)),1,0) -> 0 | AB47: =IF(ISNUMBER(SEARCH("E9",$H47)),1,0) -> 0 | AC47: =IF(ISNUMBER(SEARCH("TR",$H47)),1,0) -> 1 | AD47: TR | AE47: =IF(ISNUMBER(SEARCH("S0",$AD47)),1,0) -> 0 | AF47: =IF(ISNUMBER(SEARCH("R01",$AD47)),1,0) -> 0 | AG47: =IF(ISNUMBER(SEARCH("R02R03",$AD47)),1,0) -> 0 | AH47: =IF(ISNUMBER(SEARCH("R04",$AD47)),1,0) -> 0 | AI47: =IF(ISNUMBER(SEARCH("R05",$AD47)),1,0) -> 0 | AJ47: =IF(ISNUMBER(SEARCH("S3R06",$AD47)),1,0) -> 0 | AK47: =IF(ISNUMBER(SEARCH("R07",$AD47)),1,0) -> 0 | AL47: =IF(ISNUMBER(SEARCH("R09",$AD47)),1,0) -> 0 | AM47: =IF(ISNUMBER(SEARCH("R10",$AD47)),1,0) -> 0 | AN47: =IF(ISNUMBER(SEARCH("S5",$AD47)),1,0) -> 0 | AO47: =IF(ISNUMBER(SEARCH("S6",$AD47)),1,0) -> 0 | AP47: =IF(ISNUMBER(SEARCH("TR",$AD47)),1,0) -> 1
A48: AMLR-08 | B48: AML | C48: Reglamento (UE) 2024/1624 (AMLR) | D48: art. 22.1.a) | E48: UE_reglamento | F48: Aplicable_desde_2027-07-10 | G48: Registrar | H48: E0; E3; E4; E9 | I48: Identidad | J48: Diligencia_debida_AML | K48: No especificado | L48: Uso_interno | M48: Todas_entidades_obligadas | N48: Parcial | O48: iii) las nacionalidades, o la apatridia o el estatuto de refugiado o de protección subsidiaria cuando proceda, y el número de identificación nacional, en su caso, | P48: https://eur-lex.europa.eu/legal-content/ES/TXT/HTML/?uri=CELEX:32024R1624 | Q48: Alta | R48: Datos mínimos persona física: nombres y apellidos, lugar y fecha de nacimiento, nacionalidades/apatridia/estatuto de refugiado, residencia habitual o dirección postal si no hay domicilio fijo con residencia legítima en la UE, NIF si disponible. Excepción: casos de menor riesgo (sección 3). Relevante para inclusión (refugiados, sin domicilio fijo). | S48: =IF(ISNUMBER(SEARCH("E0",$H48)),1,0) -> 1 | T48: =IF(ISNUMBER(SEARCH("E1",$H48)),1,0) -> 0 | U48: =IF(ISNUMBER(SEARCH("E2",$H48)),1,0) -> 0 | V48: =IF(ISNUMBER(SEARCH("E3",$H48)),1,0) -> 1 | W48: =IF(ISNUMBER(SEARCH("E4",$H48)),1,0) -> 1 | X48: =IF(ISNUMBER(SEARCH("E5",$H48)),1,0) -> 0 | Y48: =IF(ISNUMBER(SEARCH("E6",$H48)),1,0) -> 0 | Z48: =IF(ISNUMBER(SEARCH("E7",$H48)),1,0) -> 0 | AA48: =IF(ISNUMBER(SEARCH("E8",$H48)),1,0) -> 0 | AB48: =IF(ISNUMBER(SEARCH("E9",$H48)),1,0) -> 1 | AC48: =IF(ISNUMBER(SEARCH("TR",$H48)),1,0) -> 0 | AD48: S0; R04; R05; S6 | AE48: =IF(ISNUMBER(SEARCH("S0",$AD48)),1,0) -> 1 | AF48: =IF(ISNUMBER(SEARCH("R01",$AD48)),1,0) -> 0 | AG48: =IF(ISNUMBER(SEARCH("R02R03",$AD48)),1,0) -> 0 | AH48: =IF(ISNUMBER(SEARCH("R04",$AD48)),1,0) -> 1 | AI48: =IF(ISNUMBER(SEARCH("R05",$AD48)),1,0) -> 1 | AJ48: =IF(ISNUMBER(SEARCH("S3R06",$AD48)),1,0) -> 0 | AK48: =IF(ISNUMBER(SEARCH("R07",$AD48)),1,0) -> 0 | AL48: =IF(ISNUMBER(SEARCH("R09",$AD48)),1,0) -> 0 | AM48: =IF(ISNUMBER(SEARCH("R10",$AD48)),1,0) -> 0 | AN48: =IF(ISNUMBER(SEARCH("S5",$AD48)),1,0) -> 0 | AO48: =IF(ISNUMBER(SEARCH("S6",$AD48)),1,0) -> 1 | AP48: =IF(ISNUMBER(SEARCH("TR",$AD48)),1,0) -> 0
A49: AMLR-09 | B49: AML | C49: Reglamento (UE) 2024/1624 (AMLR) | D49: art. 22.6.a) y b) | E49: UE_reglamento | F49: Aplicable_desde_2027-07-10 | G49: Registrar | H49: E0; E2; E3; E9 | I49: Documento_identidad | J49: Diligencia_debida_AML | K49: No especificado | L49: Uso_interno | M49: Todas_entidades_obligadas | N49: Parcial | O49: el uso de medios de identificación electrónica, siempre que cumplan los requisitos del Reglamento (UE) n.o 910/2014 en lo que respecta a los niveles de seguridad «sustancial» o «elevado» | P49: https://eur-lex.europa.eu/legal-content/ES/TXT/HTML/?uri=CELEX:32024R1624 | Q49: Alta | R49: Letra a): documento de identidad, pasaporte o equivalente y, cuando proceda, fuentes fiables e independientes. El articulado NO menciona expresamente la Cartera Europea de Identidad Digital ni la identificación 'a distancia'; la cartera encajaría como medio eIDAS de nivel elevado (interpretación, no texto). | S49: =IF(ISNUMBER(SEARCH("E0",$H49)),1,0) -> 1 | T49: =IF(ISNUMBER(SEARCH("E1",$H49)),1,0) -> 0 | U49: =IF(ISNUMBER(SEARCH("E2",$H49)),1,0) -> 1 | V49: =IF(ISNUMBER(SEARCH("E3",$H49)),1,0) -> 1 | W49: =IF(ISNUMBER(SEARCH("E4",$H49)),1,0) -> 0 | X49: =IF(ISNUMBER(SEARCH("E5",$H49)),1,0) -> 0 | Y49: =IF(ISNUMBER(SEARCH("E6",$H49)),1,0) -> 0 | Z49: =IF(ISNUMBER(SEARCH("E7",$H49)),1,0) -> 0 | AA49: =IF(ISNUMBER(SEARCH("E8",$H49)),1,0) -> 0 | AB49: =IF(ISNUMBER(SEARCH("E9",$H49)),1,0) -> 1 | AC49: =IF(ISNUMBER(SEARCH("TR",$H49)),1,0) -> 0 | AD49: S0; R02R03; R04; S6 | AE49: =IF(ISNUMBER(SEARCH("S0",$AD49)),1,0) -> 1 | AF49: =IF(ISNUMBER(SEARCH("R01",$AD49)),1,0) -> 0 | AG49: =IF(ISNUMBER(SEARCH("R02R03",$AD49)),1,0) -> 1 | AH49: =IF(ISNUMBER(SEARCH("R04",$AD49)),1,0) -> 1 | AI49: =IF(ISNUMBER(SEARCH("R05",$AD49)),1,0) -> 0 | AJ49: =IF(ISNUMBER(SEARCH("S3R06",$AD49)),1,0) -> 0 | AK49: =IF(ISNUMBER(SEARCH("R07",$AD49)),1,0) -> 0 | AL49: =IF(ISNUMBER(SEARCH("R09",$AD49)),1,0) -> 0 | AM49: =IF(ISNUMBER(SEARCH("R10",$AD49)),1,0) -> 0 | AN49: =IF(ISNUMBER(SEARCH("S5",$AD49)),1,0) -> 0 | AO49: =IF(ISNUMBER(SEARCH("S6",$AD49)),1,0) -> 1 | AP49: =IF(ISNUMBER(SEARCH("TR",$AD49)),1,0) -> 0
A50: AMLR-10 | B50: AML | C50: Reglamento (UE) 2024/1624 (AMLR) | D50: art. 23.1 | E50: UE_reglamento | F50: Aplicable_desde_2027-07-10 | G50: Abstenerse | H50: E4; E5; E9 | I50: Resultado_verificacion | J50: Diligencia_debida_AML | K50: Antes de establecer la relación de negocios | L50: Uso_interno | M50: Todas_entidades_obligadas | N50: Parcial | O50: La comprobación de la identidad del cliente, del titular real y de toda persona con arreglo al artículo 20, apartado 1, letras h) e i), se efectuará antes de que se establezca una relación | P50: https://eur-lex.europa.eu/legal-content/ES/TXT/HTML/?uri=CELEX:32024R1624 | Q50: Alta | R50: Requisito de secuencia. Excepciones: menor riesgo (sección 3) y art. 23.2 (ultimar durante el establecimiento si riesgo escaso, lo antes posible tras el primer contacto). | S50: =IF(ISNUMBER(SEARCH("E0",$H50)),1,0) -> 0 | T50: =IF(ISNUMBER(SEARCH("E1",$H50)),1,0) -> 0 | U50: =IF(ISNUMBER(SEARCH("E2",$H50)),1,0) -> 0 | V50: =IF(ISNUMBER(SEARCH("E3",$H50)),1,0) -> 0 | W50: =IF(ISNUMBER(SEARCH("E4",$H50)),1,0) -> 1 | X50: =IF(ISNUMBER(SEARCH("E5",$H50)),1,0) -> 1 | Y50: =IF(ISNUMBER(SEARCH("E6",$H50)),1,0) -> 0 | Z50: =IF(ISNUMBER(SEARCH("E7",$H50)),1,0) -> 0 | AA50: =IF(ISNUMBER(SEARCH("E8",$H50)),1,0) -> 0 | AB50: =IF(ISNUMBER(SEARCH("E9",$H50)),1,0) -> 1 | AC50: =IF(ISNUMBER(SEARCH("TR",$H50)),1,0) -> 0 | AD50: R05; R07; S3R06; S6 | AE50: =IF(ISNUMBER(SEARCH("S0",$AD50)),1,0) -> 0 | AF50: =IF(ISNUMBER(SEARCH("R01",$AD50)),1,0) -> 0 | AG50: =IF(ISNUMBER(SEARCH("R02R03",$AD50)),1,0) -> 0 | AH50: =IF(ISNUMBER(SEARCH("R04",$AD50)),1,0) -> 0 | AI50: =IF(ISNUMBER(SEARCH("R05",$AD50)),1,0) -> 1 | AJ50: =IF(ISNUMBER(SEARCH("S3R06",$AD50)),1,0) -> 1 | AK50: =IF(ISNUMBER(SEARCH("R07",$AD50)),1,0) -> 1 | AL50: =IF(ISNUMBER(SEARCH("R09",$AD50)),1,0) -> 0 | AM50: =IF(ISNUMBER(SEARCH("R10",$AD50)),1,0) -> 0 | AN50: =IF(ISNUMBER(SEARCH("S5",$AD50)),1,0) -> 0 | AO50: =IF(ISNUMBER(SEARCH("S6",$AD50)),1,0) -> 1 | AP50: =IF(ISNUMBER(SEARCH("TR",$AD50)),1,0) -> 0
A51: AMLR-11 | B51: AML | C51: Reglamento (UE) 2024/1624 (AMLR) | D51: art. 23.3 | E51: UE_reglamento | F51: Aplicable_desde_2027-07-10 | G51: Abstenerse | H51: E5; E9 | I51: Resultado_verificacion | J51: Diligencia_debida_AML | K51: Hasta cumplir art. 20.1.a) y b) | L51: Uso_interno | M51: Todas_entidades_obligadas | N51: Parcial | O51: existan suficientes garantías de que ni el cliente o ni otras personas en su nombre efectuarán operaciones hasta que se hayan cumplido plenamente las medidas de diligencia debida con respecto al cliente | P51: https://eur-lex.europa.eu/legal-content/ES/TXT/HTML/?uri=CELEX:32024R1624 | Q51: Alta | R51: Permite apertura de cuenta bloqueada antes de completar la verificación (relevante para estados intermedios del alta). | S51: =IF(ISNUMBER(SEARCH("E0",$H51)),1,0) -> 0 | T51: =IF(ISNUMBER(SEARCH("E1",$H51)),1,0) -> 0 | U51: =IF(ISNUMBER(SEARCH("E2",$H51)),1,0) -> 0 | V51: =IF(ISNUMBER(SEARCH("E3",$H51)),1,0) -> 0 | W51: =IF(ISNUMBER(SEARCH("E4",$H51)),1,0) -> 0 | X51: =IF(ISNUMBER(SEARCH("E5",$H51)),1,0) -> 1 | Y51: =IF(ISNUMBER(SEARCH("E6",$H51)),1,0) -> 0 | Z51: =IF(ISNUMBER(SEARCH("E7",$H51)),1,0) -> 0 | AA51: =IF(ISNUMBER(SEARCH("E8",$H51)),1,0) -> 0 | AB51: =IF(ISNUMBER(SEARCH("E9",$H51)),1,0) -> 1 | AC51: =IF(ISNUMBER(SEARCH("TR",$H51)),1,0) -> 0 | AD51: S3R06; S6 | AE51: =IF(ISNUMBER(SEARCH("S0",$AD51)),1,0) -> 0 | AF51: =IF(ISNUMBER(SEARCH("R01",$AD51)),1,0) -> 0 | AG51: =IF(ISNUMBER(SEARCH("R02R03",$AD51)),1,0) -> 0 | AH51: =IF(ISNUMBER(SEARCH("R04",$AD51)),1,0) -> 0 | AI51: =IF(ISNUMBER(SEARCH("R05",$AD51)),1,0) -> 0 | AJ51: =IF(ISNUMBER(SEARCH("S3R06",$AD51)),1,0) -> 1 | AK51: =IF(ISNUMBER(SEARCH("R07",$AD51)),1,0) -> 0 | AL51: =IF(ISNUMBER(SEARCH("R09",$AD51)),1,0) -> 0 | AM51: =IF(ISNUMBER(SEARCH("R10",$AD51)),1,0) -> 0 | AN51: =IF(ISNUMBER(SEARCH("S5",$AD51)),1,0) -> 0 | AO51: =IF(ISNUMBER(SEARCH("S6",$AD51)),1,0) -> 1 | AP51: =IF(ISNUMBER(SEARCH("TR",$AD51)),1,0) -> 0
A52: AMLR-12 | B52: AML | C52: Reglamento (UE) 2024/1624 (AMLR) | D52: art. 21.1 párr. 1 | E52: UE_reglamento | F52: Aplicable_desde_2027-07-10 | G52: Abstenerse | H52: E4; E7; E8 | I52: Motivo_decision | J52: Diligencia_debida_AML | K52: No especificado | L52: Uso_interno | M52: Todas_entidades_obligadas | N52: Si | O52: Cuando una entidad obligada no pueda cumplir el requisito de aplicar las medidas de diligencia debida con respecto al cliente (...) se abstendrá de efectuar operaciones o de establecer relaciones de negocios | P52: https://eur-lex.europa.eu/legal-content/ES/TXT/HTML/?uri=CELEX:32024R1624 | Q52: Alta | R52: Art. 21.4: la ALBC y la ABE emitirán directrices conjuntas a más tardar el 10-07-2027 sobre la aplicación de la Directiva 2014/92/UE (cuenta de pago básica) y prácticas de reducción del riesgo (obligación de las autoridades, no de las entidades). | S52: =IF(ISNUMBER(SEARCH("E0",$H52)),1,0) -> 0 | T52: =IF(ISNUMBER(SEARCH("E1",$H52)),1,0) -> 0 | U52: =IF(ISNUMBER(SEARCH("E2",$H52)),1,0) -> 0 | V52: =IF(ISNUMBER(SEARCH("E3",$H52)),1,0) -> 0 | W52: =IF(ISNUMBER(SEARCH("E4",$H52)),1,0) -> 1 | X52: =IF(ISNUMBER(SEARCH("E5",$H52)),1,0) -> 0 | Y52: =IF(ISNUMBER(SEARCH("E6",$H52)),1,0) -> 0 | Z52: =IF(ISNUMBER(SEARCH("E7",$H52)),1,0) -> 1 | AA52: =IF(ISNUMBER(SEARCH("E8",$H52)),1,0) -> 1 | AB52: =IF(ISNUMBER(SEARCH("E9",$H52)),1,0) -> 0 | AC52: =IF(ISNUMBER(SEARCH("TR",$H52)),1,0) -> 0 | AD52: R05; R07; R10; S5 | AE52: =IF(ISNUMBER(SEARCH("S0",$AD52)),1,0) -> 0 | AF52: =IF(ISNUMBER(SEARCH("R01",$AD52)),1,0) -> 0 | AG52: =IF(ISNUMBER(SEARCH("R02R03",$AD52)),1,0) -> 0 | AH52: =IF(ISNUMBER(SEARCH("R04",$AD52)),1,0) -> 0 | AI52: =IF(ISNUMBER(SEARCH("R05",$AD52)),1,0) -> 1 | AJ52: =IF(ISNUMBER(SEARCH("S3R06",$AD52)),1,0) -> 0 | AK52: =IF(ISNUMBER(SEARCH("R07",$AD52)),1,0) -> 1 | AL52: =IF(ISNUMBER(SEARCH("R09",$AD52)),1,0) -> 0 | AM52: =IF(ISNUMBER(SEARCH("R10",$AD52)),1,0) -> 1 | AN52: =IF(ISNUMBER(SEARCH("S5",$AD52)),1,0) -> 1 | AO52: =IF(ISNUMBER(SEARCH("S6",$AD52)),1,0) -> 0 | AP52: =IF(ISNUMBER(SEARCH("TR",$AD52)),1,0) -> 0
A53: AMLR-13 | B53: AML | C53: Reglamento (UE) 2024/1624 (AMLR) | D53: art. 21.1 párr. 1 | E53: UE_reglamento | F53: Aplicable_desde_2027-07-10 | G53: Comunicar_autoridad | H53: E4; E7; E8 | I53: Motivo_decision | J53: Diligencia_debida_AML | K53: No especificado | L53: Autoridad_AML | M53: Todas_entidades_obligadas | N53: Si | O53: se planteará la posibilidad de poner en conocimiento de la UIF una operación sospechosa en relación con el cliente, con arreglo al artículo 69. | P53: https://eur-lex.europa.eu/legal-content/ES/TXT/HTML/?uri=CELEX:32024R1624 | Q53: Alta | R53: Obligación de valorar (no de comunicar automáticamente) una comunicación de operación sospechosa. | S53: =IF(ISNUMBER(SEARCH("E0",$H53)),1,0) -> 0 | T53: =IF(ISNUMBER(SEARCH("E1",$H53)),1,0) -> 0 | U53: =IF(ISNUMBER(SEARCH("E2",$H53)),1,0) -> 0 | V53: =IF(ISNUMBER(SEARCH("E3",$H53)),1,0) -> 0 | W53: =IF(ISNUMBER(SEARCH("E4",$H53)),1,0) -> 1 | X53: =IF(ISNUMBER(SEARCH("E5",$H53)),1,0) -> 0 | Y53: =IF(ISNUMBER(SEARCH("E6",$H53)),1,0) -> 0 | Z53: =IF(ISNUMBER(SEARCH("E7",$H53)),1,0) -> 1 | AA53: =IF(ISNUMBER(SEARCH("E8",$H53)),1,0) -> 1 | AB53: =IF(ISNUMBER(SEARCH("E9",$H53)),1,0) -> 0 | AC53: =IF(ISNUMBER(SEARCH("TR",$H53)),1,0) -> 0 | AD53: R05; R10; S5 | AE53: =IF(ISNUMBER(SEARCH("S0",$AD53)),1,0) -> 0 | AF53: =IF(ISNUMBER(SEARCH("R01",$AD53)),1,0) -> 0 | AG53: =IF(ISNUMBER(SEARCH("R02R03",$AD53)),1,0) -> 0 | AH53: =IF(ISNUMBER(SEARCH("R04",$AD53)),1,0) -> 0 | AI53: =IF(ISNUMBER(SEARCH("R05",$AD53)),1,0) -> 1 | AJ53: =IF(ISNUMBER(SEARCH("S3R06",$AD53)),1,0) -> 0 | AK53: =IF(ISNUMBER(SEARCH("R07",$AD53)),1,0) -> 0 | AL53: =IF(ISNUMBER(SEARCH("R09",$AD53)),1,0) -> 0 | AM53: =IF(ISNUMBER(SEARCH("R10",$AD53)),1,0) -> 1 | AN53: =IF(ISNUMBER(SEARCH("S5",$AD53)),1,0) -> 1 | AO53: =IF(ISNUMBER(SEARCH("S6",$AD53)),1,0) -> 0 | AP53: =IF(ISNUMBER(SEARCH("TR",$AD53)),1,0) -> 0
A54: AMLR-14 | B54: AML | C54: Reglamento (UE) 2024/1624 (AMLR) | D54: art. 21.3 párr. 1 | E54: UE_reglamento | F54: Aplicable_desde_2027-07-10 | G54: Registrar | H54: TR | I54: Expediente_completo | J54: Diligencia_debida_AML | K54: No especificado | L54: Uso_interno | M54: Todas_entidades_obligadas | N54: Si | O54: Las entidades obligadas mantendrán un registro de las medidas adoptadas para cumplir el requisito de aplicar las medidas de diligencia debida con respecto al cliente, incluidos registros de las decisiones adoptadas | P54: https://eur-lex.europa.eu/legal-content/ES/TXT/HTML/?uri=CELEX:32024R1624 | Q54: Alta | R54: El plazo de conservación se rige por el art. 77.3 (cinco años). | S54: =IF(ISNUMBER(SEARCH("E0",$H54)),1,0) -> 0 | T54: =IF(ISNUMBER(SEARCH("E1",$H54)),1,0) -> 0 | U54: =IF(ISNUMBER(SEARCH("E2",$H54)),1,0) -> 0 | V54: =IF(ISNUMBER(SEARCH("E3",$H54)),1,0) -> 0 | W54: =IF(ISNUMBER(SEARCH("E4",$H54)),1,0) -> 0 | X54: =IF(ISNUMBER(SEARCH("E5",$H54)),1,0) -> 0 | Y54: =IF(ISNUMBER(SEARCH("E6",$H54)),1,0) -> 0 | Z54: =IF(ISNUMBER(SEARCH("E7",$H54)),1,0) -> 0 | AA54: =IF(ISNUMBER(SEARCH("E8",$H54)),1,0) -> 0 | AB54: =IF(ISNUMBER(SEARCH("E9",$H54)),1,0) -> 0 | AC54: =IF(ISNUMBER(SEARCH("TR",$H54)),1,0) -> 1 | AD54: TR | AE54: =IF(ISNUMBER(SEARCH("S0",$AD54)),1,0) -> 0 | AF54: =IF(ISNUMBER(SEARCH("R01",$AD54)),1,0) -> 0 | AG54: =IF(ISNUMBER(SEARCH("R02R03",$AD54)),1,0) -> 0 | AH54: =IF(ISNUMBER(SEARCH("R04",$AD54)),1,0) -> 0 | AI54: =IF(ISNUMBER(SEARCH("R05",$AD54)),1,0) -> 0 | AJ54: =IF(ISNUMBER(SEARCH("S3R06",$AD54)),1,0) -> 0 | AK54: =IF(ISNUMBER(SEARCH("R07",$AD54)),1,0) -> 0 | AL54: =IF(ISNUMBER(SEARCH("R09",$AD54)),1,0) -> 0 | AM54: =IF(ISNUMBER(SEARCH("R10",$AD54)),1,0) -> 0 | AN54: =IF(ISNUMBER(SEARCH("S5",$AD54)),1,0) -> 0 | AO54: =IF(ISNUMBER(SEARCH("S6",$AD54)),1,0) -> 0 | AP54: =IF(ISNUMBER(SEARCH("TR",$AD54)),1,0) -> 1
... A56: AMLR-16 | B56: AML | C56: Reglamento (UE) 2024/1624 (AMLR) | D56: art. 33.1.a) | E56: UE_reglamento | F56: Aplicable_desde_2027-07-10 | G56: Evaluar_riesgo | H56: E9 | I56: Resultado_verificacion | J56: Diligencia_debida_AML | K56: Máximo 60 días tras el establecimiento | L56: Uso_interno | M56: Todas_entidades_obligadas | N56: No | O56: comprobar la identidad del cliente y del titular real después del establecimiento de la relación de negocios, siempre y cuando el menor riesgo específico detectado justifique dicho aplazamiento, pero en ningún caso más de sesenta | P56: https://eur-lex.europa.eu/legal-content/ES/TXT/HTML/?uri=CELEX:32024R1624 | Q56: Alta | R56: Medida simplificada facultativa para riesgo bajo; art. 33.3 exige limitar operaciones mientras no se compruebe. | S56: =IF(ISNUMBER(SEARCH("E0",$H56)),1,0) -> 0 | T56: =IF(ISNUMBER(SEARCH("E1",$H56)),1,0) -> 0 | U56: =IF(ISNUMBER(SEARCH("E2",$H56)),1,0) -> 0 | V56: =IF(ISNUMBER(SEARCH("E3",$H56)),1,0) -> 0 | W56: =IF(ISNUMBER(SEARCH("E4",$H56)),1,0) -> 0 | X56: =IF(ISNUMBER(SEARCH("E5",$H56)),1,0) -> 0 | Y56: =IF(ISNUMBER(SEARCH("E6",$H56)),1,0) -> 0 | Z56: =IF(ISNUMBER(SEARCH("E7",$H56)),1,0) -> 0 | AA56: =IF(ISNUMBER(SEARCH("E8",$H56)),1,0) -> 0 | AB56: =IF(ISNUMBER(SEARCH("E9",$H56)),1,0) -> 1 | AC56: =IF(ISNUMBER(SEARCH("TR",$H56)),1,0) -> 0 | AD56: S6 | AE56: =IF(ISNUMBER(SEARCH("S0",$AD56)),1,0) -> 0 | AF56: =IF(ISNUMBER(SEARCH("R01",$AD56)),1,0) -> 0 | AG56: =IF(ISNUMBER(SEARCH("R02R03",$AD56)),1,0) -> 0 | AH56: =IF(ISNUMBER(SEARCH("R04",$AD56)),1,0) -> 0 | AI56: =IF(ISNUMBER(SEARCH("R05",$AD56)),1,0) -> 0 | AJ56: =IF(ISNUMBER(SEARCH("S3R06",$AD56)),1,0) -> 0 | AK56: =IF(ISNUMBER(SEARCH("R07",$AD56)),1,0) -> 0 | AL56: =IF(ISNUMBER(SEARCH("R09",$AD56)),1,0) -> 0 | AM56: =IF(ISNUMBER(SEARCH("R10",$AD56)),1,0) -> 0 | AN56: =IF(ISNUMBER(SEARCH("S5",$AD56)),1,0) -> 0 | AO56: =IF(ISNUMBER(SEARCH("S6",$AD56)),1,0) -> 1 | AP56: =IF(ISNUMBER(SEARCH("TR",$AD56)),1,0) -> 0
A57: AMLR-17 | B57: AML | C57: Reglamento (UE) 2024/1624 (AMLR) | D57: art. 33.2 | E57: UE_reglamento | F57: Aplicable_desde_2027-07-10 | G57: Registrar | H57: TR | I57: Evaluacion_riesgo | J57: Diligencia_debida_AML | K57: No especificado | L57: Uso_interno | M57: Todas_entidades_obligadas | N57: Parcial | O57: Las entidades obligadas documentarán las decisiones para tener en cuenta los factores adicionales de menor riesgo. | P57: https://eur-lex.europa.eu/legal-content/ES/TXT/HTML/?uri=CELEX:32024R1624 | Q57: Alta | S57: =IF(ISNUMBER(SEARCH("E0",$H57)),1,0) -> 0 | T57: =IF(ISNUMBER(SEARCH("E1",$H57)),1,0) -> 0 | U57: =IF(ISNUMBER(SEARCH("E2",$H57)),1,0) -> 0 | V57: =IF(ISNUMBER(SEARCH("E3",$H57)),1,0) -> 0 | W57: =IF(ISNUMBER(SEARCH("E4",$H57)),1,0) -> 0 | X57: =IF(ISNUMBER(SEARCH("E5",$H57)),1,0) -> 0 | Y57: =IF(ISNUMBER(SEARCH("E6",$H57)),1,0) -> 0 | Z57: =IF(ISNUMBER(SEARCH("E7",$H57)),1,0) -> 0 | AA57: =IF(ISNUMBER(SEARCH("E8",$H57)),1,0) -> 0 | AB57: =IF(ISNUMBER(SEARCH("E9",$H57)),1,0) -> 0 | AC57: =IF(ISNUMBER(SEARCH("TR",$H57)),1,0) -> 1 | AD57: TR | AE57: =IF(ISNUMBER(SEARCH("S0",$AD57)),1,0) -> 0 | AF57: =IF(ISNUMBER(SEARCH("R01",$AD57)),1,0) -> 0 | AG57: =IF(ISNUMBER(SEARCH("R02R03",$AD57)),1,0) -> 0 | AH57: =IF(ISNUMBER(SEARCH("R04",$AD57)),1,0) -> 0 | AI57: =IF(ISNUMBER(SEARCH("R05",$AD57)),1,0) -> 0 | AJ57: =IF(ISNUMBER(SEARCH("S3R06",$AD57)),1,0) -> 0 | AK57: =IF(ISNUMBER(SEARCH("R07",$AD57)),1,0) -> 0 | AL57: =IF(ISNUMBER(SEARCH("R09",$AD57)),1,0) -> 0 | AM57: =IF(ISNUMBER(SEARCH("R10",$AD57)),1,0) -> 0 | AN57: =IF(ISNUMBER(SEARCH("S5",$AD57)),1,0) -> 0 | AO57: =IF(ISNUMBER(SEARCH("S6",$AD57)),1,0) -> 0 | AP57: =IF(ISNUMBER(SEARCH("TR",$AD57)),1,0) -> 1
A58: AMLR-18 | B58: AML | C58: Reglamento (UE) 2024/1624 (AMLR) | D58: art. 33.5.a) | E58: UE_reglamento | F58: Aplicable_desde_2027-07-10 | G58: Evaluar_riesgo | H58: E3; E4; E5 | I58: Resultado_verificacion | J58: Diligencia_debida_AML | K58: No especificado | L58: Uso_interno | M58: Todas_entidades_obligadas | N58: Si | O58: las entidades obligadas albergan dudas sobre la veracidad de la información facilitada por el cliente o el titular real en la fase de identificación, o detectan incongruencias en relación con la información; | P58: https://eur-lex.europa.eu/legal-content/ES/TXT/HTML/?uri=CELEX:32024R1624 | Q58: Alta | R58: Supuesto en que la entidad se abstendrá de aplicar medidas simplificadas. | S58: =IF(ISNUMBER(SEARCH("E0",$H58)),1,0) -> 0 | T58: =IF(ISNUMBER(SEARCH("E1",$H58)),1,0) -> 0 | U58: =IF(ISNUMBER(SEARCH("E2",$H58)),1,0) -> 0 | V58: =IF(ISNUMBER(SEARCH("E3",$H58)),1,0) -> 1 | W58: =IF(ISNUMBER(SEARCH("E4",$H58)),1,0) -> 1 | X58: =IF(ISNUMBER(SEARCH("E5",$H58)),1,0) -> 1 | Y58: =IF(ISNUMBER(SEARCH("E6",$H58)),1,0) -> 0 | Z58: =IF(ISNUMBER(SEARCH("E7",$H58)),1,0) -> 0 | AA58: =IF(ISNUMBER(SEARCH("E8",$H58)),1,0) -> 0 | AB58: =IF(ISNUMBER(SEARCH("E9",$H58)),1,0) -> 0 | AC58: =IF(ISNUMBER(SEARCH("TR",$H58)),1,0) -> 0 | AD58: R04; R05; S3R06 | AE58: =IF(ISNUMBER(SEARCH("S0",$AD58)),1,0) -> 0 | AF58: =IF(ISNUMBER(SEARCH("R01",$AD58)),1,0) -> 0 | AG58: =IF(ISNUMBER(SEARCH("R02R03",$AD58)),1,0) -> 0 | AH58: =IF(ISNUMBER(SEARCH("R04",$AD58)),1,0) -> 1 | AI58: =IF(ISNUMBER(SEARCH("R05",$AD58)),1,0) -> 1 | AJ58: =IF(ISNUMBER(SEARCH("S3R06",$AD58)),1,0) -> 1 | AK58: =IF(ISNUMBER(SEARCH("R07",$AD58)),1,0) -> 0 | AL58: =IF(ISNUMBER(SEARCH("R09",$AD58)),1,0) -> 0 | AM58: =IF(ISNUMBER(SEARCH("R10",$AD58)),1,0) -> 0 | AN58: =IF(ISNUMBER(SEARCH("S5",$AD58)),1,0) -> 0 | AO58: =IF(ISNUMBER(SEARCH("S6",$AD58)),1,0) -> 0 | AP58: =IF(ISNUMBER(SEARCH("TR",$AD58)),1,0) -> 0
A59: AMLR-19 | B59: AML | C59: Reglamento (UE) 2024/1624 (AMLR) | D59: art. 34.1 | E59: UE_reglamento | F59: Aplicable_desde_2027-07-10 | G59: Evaluar_riesgo | H59: E5; E9 | I59: Evaluacion_riesgo | J59: Diligencia_debida_AML | K59: No especificado | L59: Uso_interno | M59: Todas_entidades_obligadas | N59: Parcial | O59: las entidades obligadas aplicarán medidas reforzadas de diligencia debida para gestionar y atenuar debidamente tales riesgos. | P59: https://eur-lex.europa.eu/legal-content/ES/TXT/HTML/?uri=CELEX:32024R1624 | Q59: Alta | R59: Supuestos: arts. 29-31 y 36-46 y otros casos de mayor riesgo (art. 20.2). Art. 34.3: tener en cuenta como mínimo los factores del anexo III. | S59: =IF(ISNUMBER(SEARCH("E0",$H59)),1,0) -> 0 | T59: =IF(ISNUMBER(SEARCH("E1",$H59)),1,0) -> 0 | U59: =IF(ISNUMBER(SEARCH("E2",$H59)),1,0) -> 0 | V59: =IF(ISNUMBER(SEARCH("E3",$H59)),1,0) -> 0 | W59: =IF(ISNUMBER(SEARCH("E4",$H59)),1,0) -> 0 | X59: =IF(ISNUMBER(SEARCH("E5",$H59)),1,0) -> 1 | Y59: =IF(ISNUMBER(SEARCH("E6",$H59)),1,0) -> 0 | Z59: =IF(ISNUMBER(SEARCH("E7",$H59)),1,0) -> 0 | AA59: =IF(ISNUMBER(SEARCH("E8",$H59)),1,0) -> 0 | AB59: =IF(ISNUMBER(SEARCH("E9",$H59)),1,0) -> 1 | AC59: =IF(ISNUMBER(SEARCH("TR",$H59)),1,0) -> 0 | AD59: S3R06; S6 | AE59: =IF(ISNUMBER(SEARCH("S0",$AD59)),1,0) -> 0 | AF59: =IF(ISNUMBER(SEARCH("R01",$AD59)),1,0) -> 0 | AG59: =IF(ISNUMBER(SEARCH("R02R03",$AD59)),1,0) -> 0 | AH59: =IF(ISNUMBER(SEARCH("R04",$AD59)),1,0) -> 0 | AI59: =IF(ISNUMBER(SEARCH("R05",$AD59)),1,0) -> 0 | AJ59: =IF(ISNUMBER(SEARCH("S3R06",$AD59)),1,0) -> 1 | AK59: =IF(ISNUMBER(SEARCH("R07",$AD59)),1,0) -> 0 | AL59: =IF(ISNUMBER(SEARCH("R09",$AD59)),1,0) -> 0 | AM59: =IF(ISNUMBER(SEARCH("R10",$AD59)),1,0) -> 0 | AN59: =IF(ISNUMBER(SEARCH("S5",$AD59)),1,0) -> 0 | AO59: =IF(ISNUMBER(SEARCH("S6",$AD59)),1,0) -> 1 | AP59: =IF(ISNUMBER(SEARCH("TR",$AD59)),1,0) -> 0
A60: AMLR-20 | B60: AML | C60: Reglamento (UE) 2024/1624 (AMLR) | D60: art. 34.4.e) | E60: UE_reglamento | F60: Aplicable_desde_2027-07-10 | G60: Supervision_humana | H60: E5; E9 | I60: Intervencion_humana | J60: Diligencia_debida_AML | K60: No especificado | L60: Uso_interno | M60: Todas_entidades_obligadas | N60: Parcial | O60: e) obtener la aprobación de los órganos de dirección para establecer o mantener la relación de negocios; | P60: https://eur-lex.europa.eu/legal-content/ES/TXT/HTML/?uri=CELEX:32024R1624 | Q60: Alta | R60: Medida reforzada potestativa ('podrá incluir') en casos de mayor riesgo. | S60: =IF(ISNUMBER(SEARCH("E0",$H60)),1,0) -> 0 | T60: =IF(ISNUMBER(SEARCH("E1",$H60)),1,0) -> 0 | U60: =IF(ISNUMBER(SEARCH("E2",$H60)),1,0) -> 0 | V60: =IF(ISNUMBER(SEARCH("E3",$H60)),1,0) -> 0 | W60: =IF(ISNUMBER(SEARCH("E4",$H60)),1,0) -> 0 | X60: =IF(ISNUMBER(SEARCH("E5",$H60)),1,0) -> 1 | Y60: =IF(ISNUMBER(SEARCH("E6",$H60)),1,0) -> 0 | Z60: =IF(ISNUMBER(SEARCH("E7",$H60)),1,0) -> 0 | AA60: =IF(ISNUMBER(SEARCH("E8",$H60)),1,0) -> 0 | AB60: =IF(ISNUMBER(SEARCH("E9",$H60)),1,0) -> 1 | AC60: =IF(ISNUMBER(SEARCH("TR",$H60)),1,0) -> 0 | AD60: S3R06; S6 | AE60: =IF(ISNUMBER(SEARCH("S0",$AD60)),1,0) -> 0 | AF60: =IF(ISNUMBER(SEARCH("R01",$AD60)),1,0) -> 0 | AG60: =IF(ISNUMBER(SEARCH("R02R03",$AD60)),1,0) -> 0 | AH60: =IF(ISNUMBER(SEARCH("R04",$AD60)),1,0) -> 0 | AI60: =IF(ISNUMBER(SEARCH("R05",$AD60)),1,0) -> 0 | AJ60: =IF(ISNUMBER(SEARCH("S3R06",$AD60)),1,0) -> 1 | AK60: =IF(ISNUMBER(SEARCH("R07",$AD60)),1,0) -> 0 | AL60: =IF(ISNUMBER(SEARCH("R09",$AD60)),1,0) -> 0 | AM60: =IF(ISNUMBER(SEARCH("R10",$AD60)),1,0) -> 0 | AN60: =IF(ISNUMBER(SEARCH("S5",$AD60)),1,0) -> 0 | AO60: =IF(ISNUMBER(SEARCH("S6",$AD60)),1,0) -> 1 | AP60: =IF(ISNUMBER(SEARCH("TR",$AD60)),1,0) -> 0
A61: AMLR-21 | B61: AML | C61: Reglamento (UE) 2024/1624 (AMLR) | D61: anexo II, punto 2.d) | E61: UE_reglamento | F61: Aplicable_desde_2027-07-10 | G61: Evaluar_riesgo | H61: E5; E9 | I61: Evaluacion_riesgo | J61: Acceso_inclusion | K61: No especificado | L61: Uso_interno | M61: Todas_entidades_obligadas | N61: Parcial | O61: productos o servicios financieros adecuadamente definidos y limitados, destinados a determinados tipos de clientes, con objeto de aumentar el acceso con fines de inclusión financiera; | P61: https://eur-lex.europa.eu/legal-content/ES/TXT/HTML/?uri=CELEX:32024R1624 | Q61: Alta | R61: Factor de menor riesgo potencial que la entidad debe considerar (art. 20.2). Nota: el anexo III del AMLR no incluye las relaciones no presenciales como factor de mayor riesgo. | S61: =IF(ISNUMBER(SEARCH("E0",$H61)),1,0) -> 0 | T61: =IF(ISNUMBER(SEARCH("E1",$H61)),1,0) -> 0 | U61: =IF(ISNUMBER(SEARCH("E2",$H61)),1,0) -> 0 | V61: =IF(ISNUMBER(SEARCH("E3",$H61)),1,0) -> 0 | W61: =IF(ISNUMBER(SEARCH("E4",$H61)),1,0) -> 0 | X61: =IF(ISNUMBER(SEARCH("E5",$H61)),1,0) -> 1 | Y61: =IF(ISNUMBER(SEARCH("E6",$H61)),1,0) -> 0 | Z61: =IF(ISNUMBER(SEARCH("E7",$H61)),1,0) -> 0 | AA61: =IF(ISNUMBER(SEARCH("E8",$H61)),1,0) -> 0 | AB61: =IF(ISNUMBER(SEARCH("E9",$H61)),1,0) -> 1 | AC61: =IF(ISNUMBER(SEARCH("TR",$H61)),1,0) -> 0 | AD61: S3R06; S6 | AE61: =IF(ISNUMBER(SEARCH("S0",$AD61)),1,0) -> 0 | AF61: =IF(ISNUMBER(SEARCH("R01",$AD61)),1,0) -> 0 | AG61: =IF(ISNUMBER(SEARCH("R02R03",$AD61)),1,0) -> 0 | AH61: =IF(ISNUMBER(SEARCH("R04",$AD61)),1,0) -> 0 | AI61: =IF(ISNUMBER(SEARCH("R05",$AD61)),1,0) -> 0 | AJ61: =IF(ISNUMBER(SEARCH("S3R06",$AD61)),1,0) -> 1 | AK61: =IF(ISNUMBER(SEARCH("R07",$AD61)),1,0) -> 0 | AL61: =IF(ISNUMBER(SEARCH("R09",$AD61)),1,0) -> 0 | AM61: =IF(ISNUMBER(SEARCH("R10",$AD61)),1,0) -> 0 | AN61: =IF(ISNUMBER(SEARCH("S5",$AD61)),1,0) -> 0 | AO61: =IF(ISNUMBER(SEARCH("S6",$AD61)),1,0) -> 1 | AP61: =IF(ISNUMBER(SEARCH("TR",$AD61)),1,0) -> 0
A62: AMLR-22 | B62: AML | C62: Reglamento (UE) 2024/1624 (AMLR) | D62: art. 69.1 párr. 2 | E62: UE_reglamento | F62: Aplicable_desde_2027-07-10 | G62: Comunicar_autoridad | H62: E1; E4; E7; E8 | I62: Motivo_decision | J62: Diligencia_debida_AML | K62: Sin demora | L62: Autoridad_AML | M62: Todas_entidades_obligadas | N62: Si | O62: Se comunicarán de conformidad con el párrafo primero todas las operaciones sospechosas, inclusive las que queden en fase de tentativa y las sospechas derivadas de la incapacidad de llevar a cabo la diligencia debida | P62: https://eur-lex.europa.eu/legal-content/ES/TXT/HTML/?uri=CELEX:32024R1624 | Q62: Alta | R62: 'Sin demora' figura en el párrafo primero del art. 69.1. | S62: =IF(ISNUMBER(SEARCH("E0",$H62)),1,0) -> 0 | T62: =IF(ISNUMBER(SEARCH("E1",$H62)),1,0) -> 1 | U62: =IF(ISNUMBER(SEARCH("E2",$H62)),1,0) -> 0 | V62: =IF(ISNUMBER(SEARCH("E3",$H62)),1,0) -> 0 | W62: =IF(ISNUMBER(SEARCH("E4",$H62)),1,0) -> 1 | X62: =IF(ISNUMBER(SEARCH("E5",$H62)),1,0) -> 0 | Y62: =IF(ISNUMBER(SEARCH("E6",$H62)),1,0) -> 0 | Z62: =IF(ISNUMBER(SEARCH("E7",$H62)),1,0) -> 1 | AA62: =IF(ISNUMBER(SEARCH("E8",$H62)),1,0) -> 1 | AB62: =IF(ISNUMBER(SEARCH("E9",$H62)),1,0) -> 0 | AC62: =IF(ISNUMBER(SEARCH("TR",$H62)),1,0) -> 0 | AD62: R01; R05; R10; S5 | AE62: =IF(ISNUMBER(SEARCH("S0",$AD62)),1,0) -> 0 | AF62: =IF(ISNUMBER(SEARCH("R01",$AD62)),1,0) -> 1 | AG62: =IF(ISNUMBER(SEARCH("R02R03",$AD62)),1,0) -> 0 | AH62: =IF(ISNUMBER(SEARCH("R04",$AD62)),1,0) -> 0 | AI62: =IF(ISNUMBER(SEARCH("R05",$AD62)),1,0) -> 1 | AJ62: =IF(ISNUMBER(SEARCH("S3R06",$AD62)),1,0) -> 0 | AK62: =IF(ISNUMBER(SEARCH("R07",$AD62)),1,0) -> 0 | AL62: =IF(ISNUMBER(SEARCH("R09",$AD62)),1,0) -> 0 | AM62: =IF(ISNUMBER(SEARCH("R10",$AD62)),1,0) -> 1 | AN62: =IF(ISNUMBER(SEARCH("S5",$AD62)),1,0) -> 1 | AO62: =IF(ISNUMBER(SEARCH("S6",$AD62)),1,0) -> 0 | AP62: =IF(ISNUMBER(SEARCH("TR",$AD62)),1,0) -> 0
A63: AMLR-23 | B63: AML | C63: Reglamento (UE) 2024/1624 (AMLR) | D63: art. 76.2.a) | E63: UE_reglamento | F63: Aplicable_desde_2027-07-10 | G63: Informar_interesado | H63: E0 | I63: Informacion_tratamiento | J63: Proteccion_datos | K63: No especificado | L63: Interesado | M63: Todas_entidades_obligadas | N63: Si | O63: informen a sus clientes o clientes potenciales de que dichas categorías de datos podrán tratarse con el fin de cumplir los requisitos del presente Reglamento; | P63: https://eur-lex.europa.eu/legal-content/ES/TXT/HTML/?uri=CELEX:32024R1624 | Q63: Alta | R63: Solo si se tratan categorías especiales de datos (art. 9 RGPD). | S63: =IF(ISNUMBER(SEARCH("E0",$H63)),1,0) -> 1 | T63: =IF(ISNUMBER(SEARCH("E1",$H63)),1,0) -> 0 | U63: =IF(ISNUMBER(SEARCH("E2",$H63)),1,0) -> 0 | V63: =IF(ISNUMBER(SEARCH("E3",$H63)),1,0) -> 0 | W63: =IF(ISNUMBER(SEARCH("E4",$H63)),1,0) -> 0 | X63: =IF(ISNUMBER(SEARCH("E5",$H63)),1,0) -> 0 | Y63: =IF(ISNUMBER(SEARCH("E6",$H63)),1,0) -> 0 | Z63: =IF(ISNUMBER(SEARCH("E7",$H63)),1,0) -> 0 | AA63: =IF(ISNUMBER(SEARCH("E8",$H63)),1,0) -> 0 | AB63: =IF(ISNUMBER(SEARCH("E9",$H63)),1,0) -> 0 | AC63: =IF(ISNUMBER(SEARCH("TR",$H63)),1,0) -> 0 | AD63: S0 | AE63: =IF(ISNUMBER(SEARCH("S0",$AD63)),1,0) -> 1 | AF63: =IF(ISNUMBER(SEARCH("R01",$AD63)),1,0) -> 0 | AG63: =IF(ISNUMBER(SEARCH("R02R03",$AD63)),1,0) -> 0 | AH63: =IF(ISNUMBER(SEARCH("R04",$AD63)),1,0) -> 0 | AI63: =IF(ISNUMBER(SEARCH("R05",$AD63)),1,0) -> 0 | AJ63: =IF(ISNUMBER(SEARCH("S3R06",$AD63)),1,0) -> 0 | AK63: =IF(ISNUMBER(SEARCH("R07",$AD63)),1,0) -> 0 | AL63: =IF(ISNUMBER(SEARCH("R09",$AD63)),1,0) -> 0 | AM63: =IF(ISNUMBER(SEARCH("R10",$AD63)),1,0) -> 0 | AN63: =IF(ISNUMBER(SEARCH("S5",$AD63)),1,0) -> 0 | AO63: =IF(ISNUMBER(SEARCH("S6",$AD63)),1,0) -> 0 | AP63: =IF(ISNUMBER(SEARCH("TR",$AD63)),1,0) -> 0
A64: AMLR-24 | B64: AML | C64: Reglamento (UE) 2024/1624 (AMLR) | D64: art. 76.5.b) | E64: UE_reglamento | F64: Aplicable_desde_2027-07-10 | G64: Supervision_humana | H64: E5; E8; E9 | I64: Intervencion_humana | J64: Trazabilidad_IA | K64: No especificado | L64: Uso_interno | M64: Todas_entidades_obligadas | N64: Si | O64: toda decisión de entablar o negarse a entablar o mantener una relación de negocios con un cliente (...) esté sujeta a una intervención humana significativa para garantizar la exactitud y adecuación de dicha decisión | P64: https://eur-lex.europa.eu/legal-content/ES/TXT/HTML/?uri=CELEX:32024R1624 | Q64: Alta | R64: Condición para usar decisiones automatizadas, perfiles o sistemas de IA en la diligencia debida. El texto ES remite al 'Reglamento (UE) 2024/XXX' (Reglamento de IA). | S64: =IF(ISNUMBER(SEARCH("E0",$H64)),1,0) -> 0 | T64: =IF(ISNUMBER(SEARCH("E1",$H64)),1,0) -> 0 | U64: =IF(ISNUMBER(SEARCH("E2",$H64)),1,0) -> 0 | V64: =IF(ISNUMBER(SEARCH("E3",$H64)),1,0) -> 0 | W64: =IF(ISNUMBER(SEARCH("E4",$H64)),1,0) -> 0 | X64: =IF(ISNUMBER(SEARCH("E5",$H64)),1,0) -> 1 | Y64: =IF(ISNUMBER(SEARCH("E6",$H64)),1,0) -> 0 | Z64: =IF(ISNUMBER(SEARCH("E7",$H64)),1,0) -> 0 | AA64: =IF(ISNUMBER(SEARCH("E8",$H64)),1,0) -> 1 | AB64: =IF(ISNUMBER(SEARCH("E9",$H64)),1,0) -> 1 | AC64: =IF(ISNUMBER(SEARCH("TR",$H64)),1,0) -> 0 | AD64: S3R06; S5; S6 | AE64: =IF(ISNUMBER(SEARCH("S0",$AD64)),1,0) -> 0 | AF64: =IF(ISNUMBER(SEARCH("R01",$AD64)),1,0) -> 0 | AG64: =IF(ISNUMBER(SEARCH("R02R03",$AD64)),1,0) -> 0 | AH64: =IF(ISNUMBER(SEARCH("R04",$AD64)),1,0) -> 0 | AI64: =IF(ISNUMBER(SEARCH("R05",$AD64)),1,0) -> 0 | AJ64: =IF(ISNUMBER(SEARCH("S3R06",$AD64)),1,0) -> 1 | AK64: =IF(ISNUMBER(SEARCH("R07",$AD64)),1,0) -> 0 | AL64: =IF(ISNUMBER(SEARCH("R09",$AD64)),1,0) -> 0 | AM64: =IF(ISNUMBER(SEARCH("R10",$AD64)),1,0) -> 0 | AN64: =IF(ISNUMBER(SEARCH("S5",$AD64)),1,0) -> 1 | AO64: =IF(ISNUMBER(SEARCH("S6",$AD64)),1,0) -> 1 | AP64: =IF(ISNUMBER(SEARCH("TR",$AD64)),1,0) -> 0
A65: AMLR-25 | B65: AML | C65: Reglamento (UE) 2024/1624 (AMLR) | D65: art. 76.5.c) | E65: UE_reglamento | F65: Aplicable_desde_2027-07-10 | G65: Informar_interesado | H65: E8 | I65: Motivo_decision | J65: Reclamaciones | K65: No especificado | L65: Interesado | M65: Todas_entidades_obligadas | N65: Si | O65: el cliente pueda obtener una explicación sobre la decisión adoptada por la entidad obligada, y pueda impugnar dicha decisión, excepto en relación con el informe a que se refiere el artículo 69 | P65: https://eur-lex.europa.eu/legal-content/ES/TXT/HTML/?uri=CELEX:32024R1624 | Q65: Alta | R65: Aplicable cuando la decisión se basa en procesos automatizados o IA (art. 76.5). | S65: =IF(ISNUMBER(SEARCH("E0",$H65)),1,0) -> 0 | T65: =IF(ISNUMBER(SEARCH("E1",$H65)),1,0) -> 0 | U65: =IF(ISNUMBER(SEARCH("E2",$H65)),1,0) -> 0 | V65: =IF(ISNUMBER(SEARCH("E3",$H65)),1,0) -> 0 | W65: =IF(ISNUMBER(SEARCH("E4",$H65)),1,0) -> 0 | X65: =IF(ISNUMBER(SEARCH("E5",$H65)),1,0) -> 0 | Y65: =IF(ISNUMBER(SEARCH("E6",$H65)),1,0) -> 0 | Z65: =IF(ISNUMBER(SEARCH("E7",$H65)),1,0) -> 0 | AA65: =IF(ISNUMBER(SEARCH("E8",$H65)),1,0) -> 1 | AB65: =IF(ISNUMBER(SEARCH("E9",$H65)),1,0) -> 0 | AC65: =IF(ISNUMBER(SEARCH("TR",$H65)),1,0) -> 0 | AD65: S5 | AE65: =IF(ISNUMBER(SEARCH("S0",$AD65)),1,0) -> 0 | AF65: =IF(ISNUMBER(SEARCH("R01",$AD65)),1,0) -> 0 | AG65: =IF(ISNUMBER(SEARCH("R02R03",$AD65)),1,0) -> 0 | AH65: =IF(ISNUMBER(SEARCH("R04",$AD65)),1,0) -> 0 | AI65: =IF(ISNUMBER(SEARCH("R05",$AD65)),1,0) -> 0 | AJ65: =IF(ISNUMBER(SEARCH("S3R06",$AD65)),1,0) -> 0 | AK65: =IF(ISNUMBER(SEARCH("R07",$AD65)),1,0) -> 0 | AL65: =IF(ISNUMBER(SEARCH("R09",$AD65)),1,0) -> 0 | AM65: =IF(ISNUMBER(SEARCH("R10",$AD65)),1,0) -> 0 | AN65: =IF(ISNUMBER(SEARCH("S5",$AD65)),1,0) -> 1 | AO65: =IF(ISNUMBER(SEARCH("S6",$AD65)),1,0) -> 0 | AP65: =IF(ISNUMBER(SEARCH("TR",$AD65)),1,0) -> 0
A66: AMLR-26 | B66: AML | C66: Reglamento (UE) 2024/1624 (AMLR) | D66: art. 77.1.a) | E66: UE_reglamento | F66: Aplicable_desde_2027-07-10 | G66: Conservar | H66: TR | I66: Expediente_completo | J66: Diligencia_debida_AML | K66: 5 años | L66: Varios | M66: Todas_entidades_obligadas | N66: Si | O66: una copia de los documentos y la información obtenidos durante la realización del procedimiento de diligencia debida con respecto al cliente (...) incluida la información obtenida a través de medios de identificación electrónica; | P66: https://eur-lex.europa.eu/legal-content/ES/TXT/HTML/?uri=CELEX:32024R1624 | Q66: Alta | R66: Párrafo final del 77.1: los registros no se expurgarán. Art. 77.2: posible conservación por referencia si la información no puede modificarse ni alterarse. | S66: =IF(ISNUMBER(SEARCH("E0",$H66)),1,0) -> 0 | T66: =IF(ISNUMBER(SEARCH("E1",$H66)),1,0) -> 0 | U66: =IF(ISNUMBER(SEARCH("E2",$H66)),1,0) -> 0 | V66: =IF(ISNUMBER(SEARCH("E3",$H66)),1,0) -> 0 | W66: =IF(ISNUMBER(SEARCH("E4",$H66)),1,0) -> 0 | X66: =IF(ISNUMBER(SEARCH("E5",$H66)),1,0) -> 0 | Y66: =IF(ISNUMBER(SEARCH("E6",$H66)),1,0) -> 0 | Z66: =IF(ISNUMBER(SEARCH("E7",$H66)),1,0) -> 0 | AA66: =IF(ISNUMBER(SEARCH("E8",$H66)),1,0) -> 0 | AB66: =IF(ISNUMBER(SEARCH("E9",$H66)),1,0) -> 0 | AC66: =IF(ISNUMBER(SEARCH("TR",$H66)),1,0) -> 1 | AD66: TR | AE66: =IF(ISNUMBER(SEARCH("S0",$AD66)),1,0) -> 0 | AF66: =IF(ISNUMBER(SEARCH("R01",$AD66)),1,0) -> 0 | AG66: =IF(ISNUMBER(SEARCH("R02R03",$AD66)),1,0) -> 0 | AH66: =IF(ISNUMBER(SEARCH("R04",$AD66)),1,0) -> 0 | AI66: =IF(ISNUMBER(SEARCH("R05",$AD66)),1,0) -> 0 | AJ66: =IF(ISNUMBER(SEARCH("S3R06",$AD66)),1,0) -> 0 | AK66: =IF(ISNUMBER(SEARCH("R07",$AD66)),1,0) -> 0 | AL66: =IF(ISNUMBER(SEARCH("R09",$AD66)),1,0) -> 0 | AM66: =IF(ISNUMBER(SEARCH("R10",$AD66)),1,0) -> 0 | AN66: =IF(ISNUMBER(SEARCH("S5",$AD66)),1,0) -> 0 | AO66: =IF(ISNUMBER(SEARCH("S6",$AD66)),1,0) -> 0 | AP66: =IF(ISNUMBER(SEARCH("TR",$AD66)),1,0) -> 1
A67: AMLR-27 | B67: AML | C67: Reglamento (UE) 2024/1624 (AMLR) | D67: art. 77.1.b) | E67: UE_reglamento | F67: Aplicable_desde_2027-07-10 | G67: Conservar | H67: E4; E5; E8 | I67: Motivo_decision | J67: Diligencia_debida_AML | K67: 5 años | L67: Autoridad_AML | M67: Todas_entidades_obligadas | N67: Si | O67: un registro de la evaluación realizada de conformidad con el artículo 69, apartado 2 (...) con independencia de que dicha evaluación dé lugar o no a una comunicación de operaciones sospechosas a la UIF | P67: https://eur-lex.europa.eu/legal-content/ES/TXT/HTML/?uri=CELEX:32024R1624 | Q67: Alta | R67: Cubre la valoración de sospecha que exige el art. 21.1 cuando no se puede completar la diligencia debida. | S67: =IF(ISNUMBER(SEARCH("E0",$H67)),1,0) -> 0 | T67: =IF(ISNUMBER(SEARCH("E1",$H67)),1,0) -> 0 | U67: =IF(ISNUMBER(SEARCH("E2",$H67)),1,0) -> 0 | V67: =IF(ISNUMBER(SEARCH("E3",$H67)),1,0) -> 0 | W67: =IF(ISNUMBER(SEARCH("E4",$H67)),1,0) -> 1 | X67: =IF(ISNUMBER(SEARCH("E5",$H67)),1,0) -> 1 | Y67: =IF(ISNUMBER(SEARCH("E6",$H67)),1,0) -> 0 | Z67: =IF(ISNUMBER(SEARCH("E7",$H67)),1,0) -> 0 | AA67: =IF(ISNUMBER(SEARCH("E8",$H67)),1,0) -> 1 | AB67: =IF(ISNUMBER(SEARCH("E9",$H67)),1,0) -> 0 | AC67: =IF(ISNUMBER(SEARCH("TR",$H67)),1,0) -> 0 | AD67: R05; S3R06; S5 | AE67: =IF(ISNUMBER(SEARCH("S0",$AD67)),1,0) -> 0 | AF67: =IF(ISNUMBER(SEARCH("R01",$AD67)),1,0) -> 0 | AG67: =IF(ISNUMBER(SEARCH("R02R03",$AD67)),1,0) -> 0 | AH67: =IF(ISNUMBER(SEARCH("R04",$AD67)),1,0) -> 0 | AI67: =IF(ISNUMBER(SEARCH("R05",$AD67)),1,0) -> 1 | AJ67: =IF(ISNUMBER(SEARCH("S3R06",$AD67)),1,0) -> 1 | AK67: =IF(ISNUMBER(SEARCH("R07",$AD67)),1,0) -> 0 | AL67: =IF(ISNUMBER(SEARCH("R09",$AD67)),1,0) -> 0 | AM67: =IF(ISNUMBER(SEARCH("R10",$AD67)),1,0) -> 0 | AN67: =IF(ISNUMBER(SEARCH("S5",$AD67)),1,0) -> 1 | AO67: =IF(ISNUMBER(SEARCH("S6",$AD67)),1,0) -> 0 | AP67: =IF(ISNUMBER(SEARCH("TR",$AD67)),1,0) -> 0
A68: AMLR-28 | B68: AML | C68: Reglamento (UE) 2024/1624 (AMLR) | D68: art. 77.3 | E68: UE_reglamento | F68: Aplicable_desde_2027-07-10 | G68: Conservar | H68: E4; E7; E8; E9 | I68: Expediente_completo | J68: Diligencia_debida_AML | K68: 5 años | L68: Varios | M68: Todas_entidades_obligadas | N68: Si | O68: se conservará durante un período de cinco años, a partir de la fecha de extinción de la relación de negocios o (...) de la fecha de la negativa a entablar una relación de negocios | P68: https://eur-lex.europa.eu/legal-content/ES/TXT/HTML/?uri=CELEX:32024R1624 | Q68: Alta | R68: Al expirar, supresión de datos personales salvo otros plazos legales compatibles con el RGPD; las autoridades pueden exigir prórroga de hasta cinco años más. No se fija cómputo expreso para el abandono sin negativa formal (E1, E6). | S68: =IF(ISNUMBER(SEARCH("E0",$H68)),1,0) -> 0 | T68: =IF(ISNUMBER(SEARCH("E1",$H68)),1,0) -> 0 | U68: =IF(ISNUMBER(SEARCH("E2",$H68)),1,0) -> 0 | V68: =IF(ISNUMBER(SEARCH("E3",$H68)),1,0) -> 0 | W68: =IF(ISNUMBER(SEARCH("E4",$H68)),1,0) -> 1 | X68: =IF(ISNUMBER(SEARCH("E5",$H68)),1,0) -> 0 | Y68: =IF(ISNUMBER(SEARCH("E6",$H68)),1,0) -> 0 | Z68: =IF(ISNUMBER(SEARCH("E7",$H68)),1,0) -> 1 | AA68: =IF(ISNUMBER(SEARCH("E8",$H68)),1,0) -> 1 | AB68: =IF(ISNUMBER(SEARCH("E9",$H68)),1,0) -> 1 | AC68: =IF(ISNUMBER(SEARCH("TR",$H68)),1,0) -> 0 | AD68: R05; R10; S5; S6 | AE68: =IF(ISNUMBER(SEARCH("S0",$AD68)),1,0) -> 0 | AF68: =IF(ISNUMBER(SEARCH("R01",$AD68)),1,0) -> 0 | AG68: =IF(ISNUMBER(SEARCH("R02R03",$AD68)),1,0) -> 0 | AH68: =IF(ISNUMBER(SEARCH("R04",$AD68)),1,0) -> 0 | AI68: =IF(ISNUMBER(SEARCH("R05",$AD68)),1,0) -> 1 | AJ68: =IF(ISNUMBER(SEARCH("S3R06",$AD68)),1,0) -> 0 | AK68: =IF(ISNUMBER(SEARCH("R07",$AD68)),1,0) -> 0 | AL68: =IF(ISNUMBER(SEARCH("R09",$AD68)),1,0) -> 0 | AM68: =IF(ISNUMBER(SEARCH("R10",$AD68)),1,0) -> 1 | AN68: =IF(ISNUMBER(SEARCH("S5",$AD68)),1,0) -> 1 | AO68: =IF(ISNUMBER(SEARCH("S6",$AD68)),1,0) -> 1 | AP68: =IF(ISNUMBER(SEARCH("TR",$AD68)),1,0) -> 0
A69: EBA-RO-01 | B69: Directrices EBA | C69: Directrices EBA/GL/2022/15 (alta de clientes a distancia) | D69: párr. 9.a) | E69: Soft_law_EBA | F69: Aplicable_desde_2023-10-02 | G69: Registrar | H69: TR | I69: Logs_sistema | J69: Diligencia_debida_AML | K69: No especificado | L69: Uso_interno | M69: Todas_entidades_obligadas | N69: Parcial | O69: una descripción general de la solución que las entidades de crédito y financieras han puesto en marcha para recopilar, verificar y conservar la información durante el proceso de alta de clientes a distancia. | P69: https://www.eba.europa.eu/sites/default/files/document_library/Publications/Guidelines/2022/EBA-GL-2022-15%20GL%20on%20remote%20customer%20onboarding/Translations/1054115/GL%20remote%20customer%20onboarding%20solutions%20%28EBA%20GL%202022%2015%29_ES_REV.pdf | Q69: Alta | R69: Contenido mínimo de las políticas y procedimientos de alta a distancia (párr. 9 a-e). Destinatarias: entidades de crédito y financieras (no todas las entidades obligadas). Basada en la Directiva (UE) 2015/849; previsible sustitución por normas/directrices ALBC al aplicarse el AMLR. | S69: =IF(ISNUMBER(SEARCH("E0",$H69)),1,0) -> 0 | T69: =IF(ISNUMBER(SEARCH("E1",$H69)),1,0) -> 0 | U69: =IF(ISNUMBER(SEARCH("E2",$H69)),1,0) -> 0 | V69: =IF(ISNUMBER(SEARCH("E3",$H69)),1,0) -> 0 | W69: =IF(ISNUMBER(SEARCH("E4",$H69)),1,0) -> 0 | X69: =IF(ISNUMBER(SEARCH("E5",$H69)),1,0) -> 0 | Y69: =IF(ISNUMBER(SEARCH("E6",$H69)),1,0) -> 0 | Z69: =IF(ISNUMBER(SEARCH("E7",$H69)),1,0) -> 0 | AA69: =IF(ISNUMBER(SEARCH("E8",$H69)),1,0) -> 0 | AB69: =IF(ISNUMBER(SEARCH("E9",$H69)),1,0) -> 0 | AC69: =IF(ISNUMBER(SEARCH("TR",$H69)),1,0) -> 1 | AD69: TR | AE69: =IF(ISNUMBER(SEARCH("S0",$AD69)),1,0) -> 0 | AF69: =IF(ISNUMBER(SEARCH("R01",$AD69)),1,0) -> 0 | AG69: =IF(ISNUMBER(SEARCH("R02R03",$AD69)),1,0) -> 0 | AH69: =IF(ISNUMBER(SEARCH("R04",$AD69)),1,0) -> 0 | AI69: =IF(ISNUMBER(SEARCH("R05",$AD69)),1,0) -> 0 | AJ69: =IF(ISNUMBER(SEARCH("S3R06",$AD69)),1,0) -> 0 | AK69: =IF(ISNUMBER(SEARCH("R07",$AD69)),1,0) -> 0 | AL69: =IF(ISNUMBER(SEARCH("R09",$AD69)),1,0) -> 0 | AM69: =IF(ISNUMBER(SEARCH("R10",$AD69)),1,0) -> 0 | AN69: =IF(ISNUMBER(SEARCH("S5",$AD69)),1,0) -> 0 | AO69: =IF(ISNUMBER(SEARCH("S6",$AD69)),1,0) -> 0 | AP69: =IF(ISNUMBER(SEARCH("TR",$AD69)),1,0) -> 1
... A122: GDPR-04 | B122: RGPD | C122: Reglamento (UE) 2016/679 (RGPD) | D122: art. 13.1 | E122: UE_reglamento | F122: Vigente | G122: Informar_interesado | H122: E0 | I122: Informacion_tratamiento | J122: Proteccion_datos | K122: En el momento de la obtención | L122: Interesado | M122: Responsable_tratamiento | N122: Si | O122: Cuando se obtengan de un interesado datos personales relativos a él, el responsable del tratamiento, en el momento en que estos se obtengan, le facilitará toda la información indicada a continuación: | P122: https://eur-lex.europa.eu/legal-content/ES/TXT/HTML/?uri=CELEX:32016R0679 | Q122: Alta | R122: Incluye letras a) identidad del responsable, c) fines y base jurídica, e) destinatarios. Se debe al inicio, con independencia del resultado del alta. | S122: =IF(ISNUMBER(SEARCH("E0",$H122)),1,0) -> 1 | T122: =IF(ISNUMBER(SEARCH("E1",$H122)),1,0) -> 0 | U122: =IF(ISNUMBER(SEARCH("E2",$H122)),1,0) -> 0 | V122: =IF(ISNUMBER(SEARCH("E3",$H122)),1,0) -> 0 | W122: =IF(ISNUMBER(SEARCH("E4",$H122)),1,0) -> 0 | X122: =IF(ISNUMBER(SEARCH("E5",$H122)),1,0) -> 0 | Y122: =IF(ISNUMBER(SEARCH("E6",$H122)),1,0) -> 0 | Z122: =IF(ISNUMBER(SEARCH("E7",$H122)),1,0) -> 0 | AA122: =IF(ISNUMBER(SEARCH("E8",$H122)),1,0) -> 0 | AB122: =IF(ISNUMBER(SEARCH("E9",$H122)),1,0) -> 0 | AC122: =IF(ISNUMBER(SEARCH("TR",$H122)),1,0) -> 0 | AD122: S0 | AE122: =IF(ISNUMBER(SEARCH("S0",$AD122)),1,0) -> 1 | AF122: =IF(ISNUMBER(SEARCH("R01",$AD122)),1,0) -> 0 | AG122: =IF(ISNUMBER(SEARCH("R02R03",$AD122)),1,0) -> 0 | AH122: =IF(ISNUMBER(SEARCH("R04",$AD122)),1,0) -> 0 | AI122: =IF(ISNUMBER(SEARCH("R05",$AD122)),1,0) -> 0 | AJ122: =IF(ISNUMBER(SEARCH("S3R06",$AD122)),1,0) -> 0 | AK122: =IF(ISNUMBER(SEARCH("R07",$AD122)),1,0) -> 0 | AL122: =IF(ISNUMBER(SEARCH("R09",$AD122)),1,0) -> 0 | AM122: =IF(ISNUMBER(SEARCH("R10",$AD122)),1,0) -> 0 | AN122: =IF(ISNUMBER(SEARCH("S5",$AD122)),1,0) -> 0 | AO122: =IF(ISNUMBER(SEARCH("S6",$AD122)),1,0) -> 0 | AP122: =IF(ISNUMBER(SEARCH("TR",$AD122)),1,0) -> 0
A123: GDPR-05 | B123: RGPD | C123: Reglamento (UE) 2016/679 (RGPD) | D123: art. 13.2.a | E123: UE_reglamento | F123: Vigente | G123: Informar_interesado | H123: E0 | I123: Informacion_tratamiento | J123: Proteccion_datos | K123: En el momento de la obtención | L123: Interesado | M123: Responsable_tratamiento | N123: Si | O123: el plazo durante el cual se conservarán los datos personales o, cuando no sea posible, los criterios utilizados para determinar este plazo | P123: https://eur-lex.europa.eu/legal-content/ES/TXT/HTML/?uri=CELEX:32016R0679 | Q123: Alta | S123: =IF(ISNUMBER(SEARCH("E0",$H123)),1,0) -> 1 | T123: =IF(ISNUMBER(SEARCH("E1",$H123)),1,0) -> 0 | U123: =IF(ISNUMBER(SEARCH("E2",$H123)),1,0) -> 0 | V123: =IF(ISNUMBER(SEARCH("E3",$H123)),1,0) -> 0 | W123: =IF(ISNUMBER(SEARCH("E4",$H123)),1,0) -> 0 | X123: =IF(ISNUMBER(SEARCH("E5",$H123)),1,0) -> 0 | Y123: =IF(ISNUMBER(SEARCH("E6",$H123)),1,0) -> 0 | Z123: =IF(ISNUMBER(SEARCH("E7",$H123)),1,0) -> 0 | AA123: =IF(ISNUMBER(SEARCH("E8",$H123)),1,0) -> 0 | AB123: =IF(ISNUMBER(SEARCH("E9",$H123)),1,0) -> 0 | AC123: =IF(ISNUMBER(SEARCH("TR",$H123)),1,0) -> 0 | AD123: S0 | AE123: =IF(ISNUMBER(SEARCH("S0",$AD123)),1,0) -> 1 | AF123: =IF(ISNUMBER(SEARCH("R01",$AD123)),1,0) -> 0 | AG123: =IF(ISNUMBER(SEARCH("R02R03",$AD123)),1,0) -> 0 | AH123: =IF(ISNUMBER(SEARCH("R04",$AD123)),1,0) -> 0 | AI123: =IF(ISNUMBER(SEARCH("R05",$AD123)),1,0) -> 0 | AJ123: =IF(ISNUMBER(SEARCH("S3R06",$AD123)),1,0) -> 0 | AK123: =IF(ISNUMBER(SEARCH("R07",$AD123)),1,0) -> 0 | AL123: =IF(ISNUMBER(SEARCH("R09",$AD123)),1,0) -> 0 | AM123: =IF(ISNUMBER(SEARCH("R10",$AD123)),1,0) -> 0 | AN123: =IF(ISNUMBER(SEARCH("S5",$AD123)),1,0) -> 0 | AO123: =IF(ISNUMBER(SEARCH("S6",$AD123)),1,0) -> 0 | AP123: =IF(ISNUMBER(SEARCH("TR",$AD123)),1,0) -> 0
A124: GDPR-06 | B124: RGPD | C124: Reglamento (UE) 2016/679 (RGPD) | D124: art. 13.2.f | E124: UE_reglamento | F124: Vigente | G124: Informar_interesado | H124: E0 | I124: Informacion_tratamiento | J124: Proteccion_datos | K124: En el momento de la obtención | L124: Interesado | M124: Responsable_tratamiento | N124: Si | O124: la existencia de decisiones automatizadas, incluida la elaboración de perfiles, a que se refiere el artículo 22, apartados 1 y 4, y, al menos en tales casos, información significativa sobre la lógica aplicada | P124: https://eur-lex.europa.eu/legal-content/ES/TXT/HTML/?uri=CELEX:32016R0679 | Q124: Alta | R124: Continúa: «así como la importancia y las consecuencias previstas de dicho tratamiento para el interesado». | S124: =IF(ISNUMBER(SEARCH("E0",$H124)),1,0) -> 1 | T124: =IF(ISNUMBER(SEARCH("E1",$H124)),1,0) -> 0 | U124: =IF(ISNUMBER(SEARCH("E2",$H124)),1,0) -> 0 | V124: =IF(ISNUMBER(SEARCH("E3",$H124)),1,0) -> 0 | W124: =IF(ISNUMBER(SEARCH("E4",$H124)),1,0) -> 0 | X124: =IF(ISNUMBER(SEARCH("E5",$H124)),1,0) -> 0 | Y124: =IF(ISNUMBER(SEARCH("E6",$H124)),1,0) -> 0 | Z124: =IF(ISNUMBER(SEARCH("E7",$H124)),1,0) -> 0 | AA124: =IF(ISNUMBER(SEARCH("E8",$H124)),1,0) -> 0 | AB124: =IF(ISNUMBER(SEARCH("E9",$H124)),1,0) -> 0 | AC124: =IF(ISNUMBER(SEARCH("TR",$H124)),1,0) -> 0 | AD124: S0 | AE124: =IF(ISNUMBER(SEARCH("S0",$AD124)),1,0) -> 1 | AF124: =IF(ISNUMBER(SEARCH("R01",$AD124)),1,0) -> 0 | AG124: =IF(ISNUMBER(SEARCH("R02R03",$AD124)),1,0) -> 0 | AH124: =IF(ISNUMBER(SEARCH("R04",$AD124)),1,0) -> 0 | AI124: =IF(ISNUMBER(SEARCH("R05",$AD124)),1,0) -> 0 | AJ124: =IF(ISNUMBER(SEARCH("S3R06",$AD124)),1,0) -> 0 | AK124: =IF(ISNUMBER(SEARCH("R07",$AD124)),1,0) -> 0 | AL124: =IF(ISNUMBER(SEARCH("R09",$AD124)),1,0) -> 0 | AM124: =IF(ISNUMBER(SEARCH("R10",$AD124)),1,0) -> 0 | AN124: =IF(ISNUMBER(SEARCH("S5",$AD124)),1,0) -> 0 | AO124: =IF(ISNUMBER(SEARCH("S6",$AD124)),1,0) -> 0 | AP124: =IF(ISNUMBER(SEARCH("TR",$AD124)),1,0) -> 0
A125: GDPR-07 | B125: RGPD | C125: Reglamento (UE) 2016/679 (RGPD) | D125: art. 15.1 | E125: UE_reglamento | F125: Vigente | G125: Informar_interesado | H125: TR | I125: Expediente_completo | J125: Proteccion_datos | K125: No especificado | L125: Interesado | M125: Responsable_tratamiento | N125: Si | O125: El interesado tendrá derecho a obtener del responsable del tratamiento confirmación de si se están tratando o no datos personales que le conciernen | P125: https://eur-lex.europa.eu/legal-content/ES/TXT/HTML/?uri=CELEX:32016R0679 | Q125: Alta | R125: Letra h): existencia de decisiones automatizadas y lógica aplicada. Plazo de respuesta en art. 12.3 (no codificado aquí). Frase completa del encabezado transcrita parcialmente por la herramienta. | S125: =IF(ISNUMBER(SEARCH("E0",$H125)),1,0) -> 0 | T125: =IF(ISNUMBER(SEARCH("E1",$H125)),1,0) -> 0 | U125: =IF(ISNUMBER(SEARCH("E2",$H125)),1,0) -> 0 | V125: =IF(ISNUMBER(SEARCH("E3",$H125)),1,0) -> 0 | W125: =IF(ISNUMBER(SEARCH("E4",$H125)),1,0) -> 0 | X125: =IF(ISNUMBER(SEARCH("E5",$H125)),1,0) -> 0 | Y125: =IF(ISNUMBER(SEARCH("E6",$H125)),1,0) -> 0 | Z125: =IF(ISNUMBER(SEARCH("E7",$H125)),1,0) -> 0 | AA125: =IF(ISNUMBER(SEARCH("E8",$H125)),1,0) -> 0 | AB125: =IF(ISNUMBER(SEARCH("E9",$H125)),1,0) -> 0 | AC125: =IF(ISNUMBER(SEARCH("TR",$H125)),1,0) -> 1 | AD125: TR | AE125: =IF(ISNUMBER(SEARCH("S0",$AD125)),1,0) -> 0 | AF125: =IF(ISNUMBER(SEARCH("R01",$AD125)),1,0) -> 0 | AG125: =IF(ISNUMBER(SEARCH("R02R03",$AD125)),1,0) -> 0 | AH125: =IF(ISNUMBER(SEARCH("R04",$AD125)),1,0) -> 0 | AI125: =IF(ISNUMBER(SEARCH("R05",$AD125)),1,0) -> 0 | AJ125: =IF(ISNUMBER(SEARCH("S3R06",$AD125)),1,0) -> 0 | AK125: =IF(ISNUMBER(SEARCH("R07",$AD125)),1,0) -> 0 | AL125: =IF(ISNUMBER(SEARCH("R09",$AD125)),1,0) -> 0 | AM125: =IF(ISNUMBER(SEARCH("R10",$AD125)),1,0) -> 0 | AN125: =IF(ISNUMBER(SEARCH("S5",$AD125)),1,0) -> 0 | AO125: =IF(ISNUMBER(SEARCH("S6",$AD125)),1,0) -> 0 | AP125: =IF(ISNUMBER(SEARCH("TR",$AD125)),1,0) -> 1
A126: GDPR-08 | B126: RGPD | C126: Reglamento (UE) 2016/679 (RGPD) | D126: art. 15.3 | E126: UE_reglamento | F126: Vigente | G126: Informar_interesado | H126: TR | I126: Expediente_completo | J126: Proteccion_datos | K126: No especificado | L126: Interesado | M126: Responsable_tratamiento | N126: Si | O126: El responsable del tratamiento facilitará una copia de los datos personales objeto de tratamiento. | P126: https://eur-lex.europa.eu/legal-content/ES/TXT/HTML/?uri=CELEX:32016R0679 | Q126: Alta | R126: Alcanza a solicitantes cuyo alta no culminó mientras sus datos sigan tratándose. | S126: =IF(ISNUMBER(SEARCH("E0",$H126)),1,0) -> 0 | T126: =IF(ISNUMBER(SEARCH("E1",$H126)),1,0) -> 0 | U126: =IF(ISNUMBER(SEARCH("E2",$H126)),1,0) -> 0 | V126: =IF(ISNUMBER(SEARCH("E3",$H126)),1,0) -> 0 | W126: =IF(ISNUMBER(SEARCH("E4",$H126)),1,0) -> 0 | X126: =IF(ISNUMBER(SEARCH("E5",$H126)),1,0) -> 0 | Y126: =IF(ISNUMBER(SEARCH("E6",$H126)),1,0) -> 0 | Z126: =IF(ISNUMBER(SEARCH("E7",$H126)),1,0) -> 0 | AA126: =IF(ISNUMBER(SEARCH("E8",$H126)),1,0) -> 0 | AB126: =IF(ISNUMBER(SEARCH("E9",$H126)),1,0) -> 0 | AC126: =IF(ISNUMBER(SEARCH("TR",$H126)),1,0) -> 1 | AD126: TR | AE126: =IF(ISNUMBER(SEARCH("S0",$AD126)),1,0) -> 0 | AF126: =IF(ISNUMBER(SEARCH("R01",$AD126)),1,0) -> 0 | AG126: =IF(ISNUMBER(SEARCH("R02R03",$AD126)),1,0) -> 0 | AH126: =IF(ISNUMBER(SEARCH("R04",$AD126)),1,0) -> 0 | AI126: =IF(ISNUMBER(SEARCH("R05",$AD126)),1,0) -> 0 | AJ126: =IF(ISNUMBER(SEARCH("S3R06",$AD126)),1,0) -> 0 | AK126: =IF(ISNUMBER(SEARCH("R07",$AD126)),1,0) -> 0 | AL126: =IF(ISNUMBER(SEARCH("R09",$AD126)),1,0) -> 0 | AM126: =IF(ISNUMBER(SEARCH("R10",$AD126)),1,0) -> 0 | AN126: =IF(ISNUMBER(SEARCH("S5",$AD126)),1,0) -> 0 | AO126: =IF(ISNUMBER(SEARCH("S6",$AD126)),1,0) -> 0 | AP126: =IF(ISNUMBER(SEARCH("TR",$AD126)),1,0) -> 1
A127: GDPR-09 | B127: RGPD | C127: Reglamento (UE) 2016/679 (RGPD) | D127: art. 22.1 | E127: UE_reglamento | F127: Vigente | G127: Abstenerse | H127: E8 | I127: Motivo_decision | J127: Proteccion_datos | K127: No especificado | L127: Interesado | M127: Responsable_tratamiento | N127: Si | O127: Todo interesado tendrá derecho a no ser objeto de una decisión basada únicamente en el tratamiento automatizado, incluida la elaboración de perfiles, que produzca efectos jurídicos en él o le afecte significativamente de modo similar. | P127: https://eur-lex.europa.eu/legal-content/ES/TXT/HTML/?uri=CELEX:32016R0679 | Q127: Alta | R127: Excepciones del art. 22.2: necesidad contractual (a), autorización legal (b), consentimiento explícito (c). Una denegación automatizada del alta puede entrar aquí. | S127: =IF(ISNUMBER(SEARCH("E0",$H127)),1,0) -> 0 | T127: =IF(ISNUMBER(SEARCH("E1",$H127)),1,0) -> 0 | U127: =IF(ISNUMBER(SEARCH("E2",$H127)),1,0) -> 0 | V127: =IF(ISNUMBER(SEARCH("E3",$H127)),1,0) -> 0 | W127: =IF(ISNUMBER(SEARCH("E4",$H127)),1,0) -> 0 | X127: =IF(ISNUMBER(SEARCH("E5",$H127)),1,0) -> 0 | Y127: =IF(ISNUMBER(SEARCH("E6",$H127)),1,0) -> 0 | Z127: =IF(ISNUMBER(SEARCH("E7",$H127)),1,0) -> 0 | AA127: =IF(ISNUMBER(SEARCH("E8",$H127)),1,0) -> 1 | AB127: =IF(ISNUMBER(SEARCH("E9",$H127)),1,0) -> 0 | AC127: =IF(ISNUMBER(SEARCH("TR",$H127)),1,0) -> 0 | AD127: S5 | AE127: =IF(ISNUMBER(SEARCH("S0",$AD127)),1,0) -> 0 | AF127: =IF(ISNUMBER(SEARCH("R01",$AD127)),1,0) -> 0 | AG127: =IF(ISNUMBER(SEARCH("R02R03",$AD127)),1,0) -> 0 | AH127: =IF(ISNUMBER(SEARCH("R04",$AD127)),1,0) -> 0 | AI127: =IF(ISNUMBER(SEARCH("R05",$AD127)),1,0) -> 0 | AJ127: =IF(ISNUMBER(SEARCH("S3R06",$AD127)),1,0) -> 0 | AK127: =IF(ISNUMBER(SEARCH("R07",$AD127)),1,0) -> 0 | AL127: =IF(ISNUMBER(SEARCH("R09",$AD127)),1,0) -> 0 | AM127: =IF(ISNUMBER(SEARCH("R10",$AD127)),1,0) -> 0 | AN127: =IF(ISNUMBER(SEARCH("S5",$AD127)),1,0) -> 1 | AO127: =IF(ISNUMBER(SEARCH("S6",$AD127)),1,0) -> 0 | AP127: =IF(ISNUMBER(SEARCH("TR",$AD127)),1,0) -> 0
A128: GDPR-10 | B128: RGPD | C128: Reglamento (UE) 2016/679 (RGPD) | D128: art. 22.3 | E128: UE_reglamento | F128: Vigente | G128: Supervision_humana | H128: E5; E8 | I128: Intervencion_humana | J128: Proteccion_datos | K128: No especificado | L128: Interesado | M128: Responsable_tratamiento | N128: Si | O128: como mínimo el derecho a obtener intervención humana por parte del responsable, a expresar su punto de vista y a impugnar la decisión. | P128: https://eur-lex.europa.eu/legal-content/ES/TXT/HTML/?uri=CELEX:32016R0679 | Q128: Alta | R128: Aplica en los casos del art. 22.2.a y c. El art. 22 no menciona expresamente un «derecho a explicación»: este se apoya en arts. 13.2.f y 15.1.h (y en el considerando 71, no verificado aquí). | S128: =IF(ISNUMBER(SEARCH("E0",$H128)),1,0) -> 0 | T128: =IF(ISNUMBER(SEARCH("E1",$H128)),1,0) -> 0 | U128: =IF(ISNUMBER(SEARCH("E2",$H128)),1,0) -> 0 | V128: =IF(ISNUMBER(SEARCH("E3",$H128)),1,0) -> 0 | W128: =IF(ISNUMBER(SEARCH("E4",$H128)),1,0) -> 0 | X128: =IF(ISNUMBER(SEARCH("E5",$H128)),1,0) -> 1 | Y128: =IF(ISNUMBER(SEARCH("E6",$H128)),1,0) -> 0 | Z128: =IF(ISNUMBER(SEARCH("E7",$H128)),1,0) -> 0 | AA128: =IF(ISNUMBER(SEARCH("E8",$H128)),1,0) -> 1 | AB128: =IF(ISNUMBER(SEARCH("E9",$H128)),1,0) -> 0 | AC128: =IF(ISNUMBER(SEARCH("TR",$H128)),1,0) -> 0 | AD128: S3R06; S5 | AE128: =IF(ISNUMBER(SEARCH("S0",$AD128)),1,0) -> 0 | AF128: =IF(ISNUMBER(SEARCH("R01",$AD128)),1,0) -> 0 | AG128: =IF(ISNUMBER(SEARCH("R02R03",$AD128)),1,0) -> 0 | AH128: =IF(ISNUMBER(SEARCH("R04",$AD128)),1,0) -> 0 | AI128: =IF(ISNUMBER(SEARCH("R05",$AD128)),1,0) -> 0 | AJ128: =IF(ISNUMBER(SEARCH("S3R06",$AD128)),1,0) -> 1 | AK128: =IF(ISNUMBER(SEARCH("R07",$AD128)),1,0) -> 0 | AL128: =IF(ISNUMBER(SEARCH("R09",$AD128)),1,0) -> 0 | AM128: =IF(ISNUMBER(SEARCH("R10",$AD128)),1,0) -> 0 | AN128: =IF(ISNUMBER(SEARCH("S5",$AD128)),1,0) -> 1 | AO128: =IF(ISNUMBER(SEARCH("S6",$AD128)),1,0) -> 0 | AP128: =IF(ISNUMBER(SEARCH("TR",$AD128)),1,0) -> 0
A129: GDPR-11 | B129: RGPD | C129: Reglamento (UE) 2016/679 (RGPD) | D129: art. 25.1 | E129: UE_reglamento | F129: Vigente | G129: Evaluar_riesgo | H129: TR | I129: Expediente_completo | J129: Proteccion_datos | K129: No especificado | L129: Uso_interno | M129: Responsable_tratamiento | N129: Si | O129: el responsable del tratamiento aplicará, tanto en el momento de determinar los medios de tratamiento como en el momento del propio tratamiento, medidas técnicas y organizativas apropiadas | P129: https://eur-lex.europa.eu/legal-content/ES/TXT/HTML/?uri=CELEX:32016R0679 | Q129: Alta | R129: Protección de datos desde el diseño, ponderando los riesgos del tratamiento. | S129: =IF(ISNUMBER(SEARCH("E0",$H129)),1,0) -> 0 | T129: =IF(ISNUMBER(SEARCH("E1",$H129)),1,0) -> 0 | U129: =IF(ISNUMBER(SEARCH("E2",$H129)),1,0) -> 0 | V129: =IF(ISNUMBER(SEARCH("E3",$H129)),1,0) -> 0 | W129: =IF(ISNUMBER(SEARCH("E4",$H129)),1,0) -> 0 | X129: =IF(ISNUMBER(SEARCH("E5",$H129)),1,0) -> 0 | Y129: =IF(ISNUMBER(SEARCH("E6",$H129)),1,0) -> 0 | Z129: =IF(ISNUMBER(SEARCH("E7",$H129)),1,0) -> 0 | AA129: =IF(ISNUMBER(SEARCH("E8",$H129)),1,0) -> 0 | AB129: =IF(ISNUMBER(SEARCH("E9",$H129)),1,0) -> 0 | AC129: =IF(ISNUMBER(SEARCH("TR",$H129)),1,0) -> 1 | AD129: TR | AE129: =IF(ISNUMBER(SEARCH("S0",$AD129)),1,0) -> 0 | AF129: =IF(ISNUMBER(SEARCH("R01",$AD129)),1,0) -> 0 | AG129: =IF(ISNUMBER(SEARCH("R02R03",$AD129)),1,0) -> 0 | AH129: =IF(ISNUMBER(SEARCH("R04",$AD129)),1,0) -> 0 | AI129: =IF(ISNUMBER(SEARCH("R05",$AD129)),1,0) -> 0 | AJ129: =IF(ISNUMBER(SEARCH("S3R06",$AD129)),1,0) -> 0 | AK129: =IF(ISNUMBER(SEARCH("R07",$AD129)),1,0) -> 0 | AL129: =IF(ISNUMBER(SEARCH("R09",$AD129)),1,0) -> 0 | AM129: =IF(ISNUMBER(SEARCH("R10",$AD129)),1,0) -> 0 | AN129: =IF(ISNUMBER(SEARCH("S5",$AD129)),1,0) -> 0 | AO129: =IF(ISNUMBER(SEARCH("S6",$AD129)),1,0) -> 0 | AP129: =IF(ISNUMBER(SEARCH("TR",$AD129)),1,0) -> 1
A130: GDPR-12 | B130: RGPD | C130: Reglamento (UE) 2016/679 (RGPD) | D130: art. 25.2 | E130: UE_reglamento | F130: Vigente | G130: Abstenerse | H130: TR | I130: Expediente_completo | J130: Proteccion_datos | K130: No especificado | L130: Uso_interno | M130: Responsable_tratamiento | N130: Si | O130: garantizar que, por defecto, solo sean objeto de tratamiento los datos personales que sean necesarios para cada uno de los fines específicos del tratamiento. | P130: https://eur-lex.europa.eu/legal-content/ES/TXT/HTML/?uri=CELEX:32016R0679 | Q130: Alta | R130: Protección de datos por defecto. | S130: =IF(ISNUMBER(SEARCH("E0",$H130)),1,0) -> 0 | T130: =IF(ISNUMBER(SEARCH("E1",$H130)),1,0) -> 0 | U130: =IF(ISNUMBER(SEARCH("E2",$H130)),1,0) -> 0 | V130: =IF(ISNUMBER(SEARCH("E3",$H130)),1,0) -> 0 | W130: =IF(ISNUMBER(SEARCH("E4",$H130)),1,0) -> 0 | X130: =IF(ISNUMBER(SEARCH("E5",$H130)),1,0) -> 0 | Y130: =IF(ISNUMBER(SEARCH("E6",$H130)),1,0) -> 0 | Z130: =IF(ISNUMBER(SEARCH("E7",$H130)),1,0) -> 0 | AA130: =IF(ISNUMBER(SEARCH("E8",$H130)),1,0) -> 0 | AB130: =IF(ISNUMBER(SEARCH("E9",$H130)),1,0) -> 0 | AC130: =IF(ISNUMBER(SEARCH("TR",$H130)),1,0) -> 1 | AD130: TR | AE130: =IF(ISNUMBER(SEARCH("S0",$AD130)),1,0) -> 0 | AF130: =IF(ISNUMBER(SEARCH("R01",$AD130)),1,0) -> 0 | AG130: =IF(ISNUMBER(SEARCH("R02R03",$AD130)),1,0) -> 0 | AH130: =IF(ISNUMBER(SEARCH("R04",$AD130)),1,0) -> 0 | AI130: =IF(ISNUMBER(SEARCH("R05",$AD130)),1,0) -> 0 | AJ130: =IF(ISNUMBER(SEARCH("S3R06",$AD130)),1,0) -> 0 | AK130: =IF(ISNUMBER(SEARCH("R07",$AD130)),1,0) -> 0 | AL130: =IF(ISNUMBER(SEARCH("R09",$AD130)),1,0) -> 0 | AM130: =IF(ISNUMBER(SEARCH("R10",$AD130)),1,0) -> 0 | AN130: =IF(ISNUMBER(SEARCH("S5",$AD130)),1,0) -> 0 | AO130: =IF(ISNUMBER(SEARCH("S6",$AD130)),1,0) -> 0 | AP130: =IF(ISNUMBER(SEARCH("TR",$AD130)),1,0) -> 1
A131: GDPR-13 | B131: RGPD | C131: Reglamento (UE) 2016/679 (RGPD) | D131: art. 30.1 | E131: UE_reglamento | F131: Vigente | G131: Registrar | H131: TR | I131: Informacion_tratamiento | J131: Proteccion_datos | K131: No especificado | L131: Autoridad_proteccion_datos | M131: Responsable_tratamiento | N131: Si | O131: Cada responsable y, en su caso, su representante llevarán un registro de las actividades de tratamiento efectuadas bajo su responsabilidad. | P131: https://eur-lex.europa.eu/legal-content/ES/TXT/HTML/?uri=CELEX:32016R0679 | Q131: Alta | R131: Incluye c) categorías de interesados y datos, f) plazos previstos para la supresión, g) medidas de seguridad. Disponible para la autoridad (art. 30.4, no codificado). | S131: =IF(ISNUMBER(SEARCH("E0",$H131)),1,0) -> 0 | T131: =IF(ISNUMBER(SEARCH("E1",$H131)),1,0) -> 0 | U131: =IF(ISNUMBER(SEARCH("E2",$H131)),1,0) -> 0 | V131: =IF(ISNUMBER(SEARCH("E3",$H131)),1,0) -> 0 | W131: =IF(ISNUMBER(SEARCH("E4",$H131)),1,0) -> 0 | X131: =IF(ISNUMBER(SEARCH("E5",$H131)),1,0) -> 0 | Y131: =IF(ISNUMBER(SEARCH("E6",$H131)),1,0) -> 0 | Z131: =IF(ISNUMBER(SEARCH("E7",$H131)),1,0) -> 0 | AA131: =IF(ISNUMBER(SEARCH("E8",$H131)),1,0) -> 0 | AB131: =IF(ISNUMBER(SEARCH("E9",$H131)),1,0) -> 0 | AC131: =IF(ISNUMBER(SEARCH("TR",$H131)),1,0) -> 1 | AD131: TR | AE131: =IF(ISNUMBER(SEARCH("S0",$AD131)),1,0) -> 0 | AF131: =IF(ISNUMBER(SEARCH("R01",$AD131)),1,0) -> 0 | AG131: =IF(ISNUMBER(SEARCH("R02R03",$AD131)),1,0) -> 0 | AH131: =IF(ISNUMBER(SEARCH("R04",$AD131)),1,0) -> 0 | AI131: =IF(ISNUMBER(SEARCH("R05",$AD131)),1,0) -> 0 | AJ131: =IF(ISNUMBER(SEARCH("S3R06",$AD131)),1,0) -> 0 | AK131: =IF(ISNUMBER(SEARCH("R07",$AD131)),1,0) -> 0 | AL131: =IF(ISNUMBER(SEARCH("R09",$AD131)),1,0) -> 0 | AM131: =IF(ISNUMBER(SEARCH("R10",$AD131)),1,0) -> 0 | AN131: =IF(ISNUMBER(SEARCH("S5",$AD131)),1,0) -> 0 | AO131: =IF(ISNUMBER(SEARCH("S6",$AD131)),1,0) -> 0 | AP131: =IF(ISNUMBER(SEARCH("TR",$AD131)),1,0) -> 1
A132: GDPR-14 | B132: RGPD | C132: Reglamento (UE) 2016/679 (RGPD) | D132: art. 35.1; art. 35.3.a | E132: UE_reglamento | F132: Vigente | G132: Evaluar_riesgo | H132: TR | I132: Evaluacion_riesgo | J132: Proteccion_datos | K132: Antes del tratamiento | L132: Uso_interno | M132: Responsable_tratamiento | N132: Si | O132: el responsable del tratamiento realizará, antes del tratamiento, una evaluación del impacto de las operaciones de tratamiento en la protección de datos personales. | P132: https://eur-lex.europa.eu/legal-content/ES/TXT/HTML/?uri=CELEX:32016R0679 | Q132: Alta | R132: Art. 35.3.a: evaluación sistemática de aspectos personales basada en tratamiento automatizado, como la elaboración de perfiles, con decisiones con efectos jurídicos (p. ej., scoring en el alta). | S132: =IF(ISNUMBER(SEARCH("E0",$H132)),1,0) -> 0 | T132: =IF(ISNUMBER(SEARCH("E1",$H132)),1,0) -> 0 | U132: =IF(ISNUMBER(SEARCH("E2",$H132)),1,0) -> 0 | V132: =IF(ISNUMBER(SEARCH("E3",$H132)),1,0) -> 0 | W132: =IF(ISNUMBER(SEARCH("E4",$H132)),1,0) -> 0 | X132: =IF(ISNUMBER(SEARCH("E5",$H132)),1,0) -> 0 | Y132: =IF(ISNUMBER(SEARCH("E6",$H132)),1,0) -> 0 | Z132: =IF(ISNUMBER(SEARCH("E7",$H132)),1,0) -> 0 | AA132: =IF(ISNUMBER(SEARCH("E8",$H132)),1,0) -> 0 | AB132: =IF(ISNUMBER(SEARCH("E9",$H132)),1,0) -> 0 | AC132: =IF(ISNUMBER(SEARCH("TR",$H132)),1,0) -> 1 | AD132: TR | AE132: =IF(ISNUMBER(SEARCH("S0",$AD132)),1,0) -> 0 | AF132: =IF(ISNUMBER(SEARCH("R01",$AD132)),1,0) -> 0 | AG132: =IF(ISNUMBER(SEARCH("R02R03",$AD132)),1,0) -> 0 | AH132: =IF(ISNUMBER(SEARCH("R04",$AD132)),1,0) -> 0 | AI132: =IF(ISNUMBER(SEARCH("R05",$AD132)),1,0) -> 0 | AJ132: =IF(ISNUMBER(SEARCH("S3R06",$AD132)),1,0) -> 0 | AK132: =IF(ISNUMBER(SEARCH("R07",$AD132)),1,0) -> 0 | AL132: =IF(ISNUMBER(SEARCH("R09",$AD132)),1,0) -> 0 | AM132: =IF(ISNUMBER(SEARCH("R10",$AD132)),1,0) -> 0 | AN132: =IF(ISNUMBER(SEARCH("S5",$AD132)),1,0) -> 0 | AO132: =IF(ISNUMBER(SEARCH("S6",$AD132)),1,0) -> 0 | AP132: =IF(ISNUMBER(SEARCH("TR",$AD132)),1,0) -> 1
A133: AIA-01 | B133: AI Act | C133: Reglamento (UE) 2024/1689 (AI Act) | D133: art. 12.1 | E133: UE_reglamento | F133: Aplicable_desde_2027-12-02 | G133: Registrar | H133: TR | I133: Logs_sistema | J133: Trazabilidad_IA | K133: No especificado | L133: Varios | M133: Sistemas_IA_alto_riesgo | N133: Si | O133: Los sistemas de IA de alto riesgo permitirán técnicamente el registro automático de acontecimientos (en lo sucesivo, «archivos de registro») a lo largo de todo el ciclo de vida del sistema. | P133: https://eur-lex.europa.eu/legal-content/ES/TXT/HTML/?uri=CELEX:32024R1689 | Q133: Alta | R133: Obligación de diseño del proveedor; los registros abarcan toda solicitud procesada, culmine o no. Solo si el alta incluye evaluación de solvencia/calificación crediticia (anexo III, 5.b); no la verificación biométrica 1:1 (anexo III, 1.a) ni la detección de fraude. Verificado en el texto ES de EUR-Lex. Fecha: art. 113, párr. 3, letra c), inciso i), en la redacción del Reglamento (UE) 2026/1744 (Ómnibus digital sobre IA): el capítulo III, secciones 1 a 3, se aplica a los sistemas del anexo III desde el 2-12-2027 (antes, 2-8-2026). Anexo III verificado: 1.a) excluye la verificación biométrica cuya única finalidad sea confirmar que la persona es quien afirma ser; 5.b) excluye los sistemas para detectar fraudes financieros. | S133: =IF(ISNUMBER(SEARCH("E0",$H133)),1,0) -> 0 | T133: =IF(ISNUMBER(SEARCH("E1",$H133)),1,0) -> 0 | U133: =IF(ISNUMBER(SEARCH("E2",$H133)),1,0) -> 0 | V133: =IF(ISNUMBER(SEARCH("E3",$H133)),1,0) -> 0 | W133: =IF(ISNUMBER(SEARCH("E4",$H133)),1,0) -> 0 | X133: =IF(ISNUMBER(SEARCH("E5",$H133)),1,0) -> 0 | Y133: =IF(ISNUMBER(SEARCH("E6",$H133)),1,0) -> 0 | Z133: =IF(ISNUMBER(SEARCH("E7",$H133)),1,0) -> 0 | AA133: =IF(ISNUMBER(SEARCH("E8",$H133)),1,0) -> 0 | AB133: =IF(ISNUMBER(SEARCH("E9",$H133)),1,0) -> 0 | AC133: =IF(ISNUMBER(SEARCH("TR",$H133)),1,0) -> 1 | AD133: TR | AE133: =IF(ISNUMBER(SEARCH("S0",$AD133)),1,0) -> 0 | AF133: =IF(ISNUMBER(SEARCH("R01",$AD133)),1,0) -> 0 | AG133: =IF(ISNUMBER(SEARCH("R02R03",$AD133)),1,0) -> 0 | AH133: =IF(ISNUMBER(SEARCH("R04",$AD133)),1,0) -> 0 | AI133: =IF(ISNUMBER(SEARCH("R05",$AD133)),1,0) -> 0 | AJ133: =IF(ISNUMBER(SEARCH("S3R06",$AD133)),1,0) -> 0 | AK133: =IF(ISNUMBER(SEARCH("R07",$AD133)),1,0) -> 0 | AL133: =IF(ISNUMBER(SEARCH("R09",$AD133)),1,0) -> 0 | AM133: =IF(ISNUMBER(SEARCH("R10",$AD133)),1,0) -> 0 | AN133: =IF(ISNUMBER(SEARCH("S5",$AD133)),1,0) -> 0 | AO133: =IF(ISNUMBER(SEARCH("S6",$AD133)),1,0) -> 0 | AP133: =IF(ISNUMBER(SEARCH("TR",$AD133)),1,0) -> 1
A134: AIA-02 | B134: AI Act | C134: Reglamento (UE) 2024/1689 (AI Act) | D134: art. 12.2 | E134: UE_reglamento | F134: Aplicable_desde_2027-12-02 | G134: Registrar | H134: TR | I134: Logs_sistema | J134: Trazabilidad_IA | K134: No especificado | L134: Varios | M134: Sistemas_IA_alto_riesgo | N134: Si | O134: las capacidades de registro permitirán que se registren acontecimientos pertinentes para: | P134: https://eur-lex.europa.eu/legal-content/ES/TXT/HTML/?uri=CELEX:32024R1689 | Q134: Alta | R134: Finalidades: detectar riesgos o modificaciones sustanciales (a), seguimiento poscomercialización (b), vigilancia del funcionamiento por el responsable del despliegue (c). Solo si el alta incluye evaluación de solvencia/calificación crediticia (anexo III, 5.b); no la verificación biométrica 1:1 (anexo III, 1.a) ni la detección de fraude. Verificado en el texto ES de EUR-Lex. Fecha: art. 113, párr. 3, letra c), inciso i), en la redacción del Reglamento (UE) 2026/1744 (Ómnibus digital sobre IA): el capítulo III, secciones 1 a 3, se aplica a los sistemas del anexo III desde el 2-12-2027 (antes, 2-8-2026). Anexo III verificado: 1.a) excluye la verificación biométrica cuya única finalidad sea confirmar que la persona es quien afirma ser; 5.b) excluye los sistemas para detectar fraudes financieros. | S134: =IF(ISNUMBER(SEARCH("E0",$H134)),1,0) -> 0 | T134: =IF(ISNUMBER(SEARCH("E1",$H134)),1,0) -> 0 | U134: =IF(ISNUMBER(SEARCH("E2",$H134)),1,0) -> 0 | V134: =IF(ISNUMBER(SEARCH("E3",$H134)),1,0) -> 0 | W134: =IF(ISNUMBER(SEARCH("E4",$H134)),1,0) -> 0 | X134: =IF(ISNUMBER(SEARCH("E5",$H134)),1,0) -> 0 | Y134: =IF(ISNUMBER(SEARCH("E6",$H134)),1,0) -> 0 | Z134: =IF(ISNUMBER(SEARCH("E7",$H134)),1,0) -> 0 | AA134: =IF(ISNUMBER(SEARCH("E8",$H134)),1,0) -> 0 | AB134: =IF(ISNUMBER(SEARCH("E9",$H134)),1,0) -> 0 | AC134: =IF(ISNUMBER(SEARCH("TR",$H134)),1,0) -> 1 | AD134: TR | AE134: =IF(ISNUMBER(SEARCH("S0",$AD134)),1,0) -> 0 | AF134: =IF(ISNUMBER(SEARCH("R01",$AD134)),1,0) -> 0 | AG134: =IF(ISNUMBER(SEARCH("R02R03",$AD134)),1,0) -> 0 | AH134: =IF(ISNUMBER(SEARCH("R04",$AD134)),1,0) -> 0 | AI134: =IF(ISNUMBER(SEARCH("R05",$AD134)),1,0) -> 0 | AJ134: =IF(ISNUMBER(SEARCH("S3R06",$AD134)),1,0) -> 0 | AK134: =IF(ISNUMBER(SEARCH("R07",$AD134)),1,0) -> 0 | AL134: =IF(ISNUMBER(SEARCH("R09",$AD134)),1,0) -> 0 | AM134: =IF(ISNUMBER(SEARCH("R10",$AD134)),1,0) -> 0 | AN134: =IF(ISNUMBER(SEARCH("S5",$AD134)),1,0) -> 0 | AO134: =IF(ISNUMBER(SEARCH("S6",$AD134)),1,0) -> 0 | AP134: =IF(ISNUMBER(SEARCH("TR",$AD134)),1,0) -> 1
A135: AIA-03 | B135: AI Act | C135: Reglamento (UE) 2024/1689 (AI Act) | D135: art. 14.1 | E135: UE_reglamento | F135: Aplicable_desde_2027-12-02 | G135: Supervision_humana | H135: TR | I135: Intervencion_humana | J135: Trazabilidad_IA | K135: No especificado | L135: Uso_interno | M135: Sistemas_IA_alto_riesgo | N135: Si | O135: Los sistemas de IA de alto riesgo se diseñarán y desarrollarán de modo que puedan ser vigilados de manera efectiva por personas físicas durante el período que estén en uso | P135: https://eur-lex.europa.eu/legal-content/ES/TXT/HTML/?uri=CELEX:32024R1689 | Q135: Alta | R135: Obligación de diseño (proveedor). Solo si el alta incluye evaluación de solvencia/calificación crediticia (anexo III, 5.b); no la verificación biométrica 1:1 (anexo III, 1.a) ni la detección de fraude. Verificado en el texto ES de EUR-Lex. Fecha: art. 113, párr. 3, letra c), inciso i), en la redacción del Reglamento (UE) 2026/1744 (Ómnibus digital sobre IA): el capítulo III, secciones 1 a 3, se aplica a los sistemas del anexo III desde el 2-12-2027 (antes, 2-8-2026). Anexo III verificado: 1.a) excluye la verificación biométrica cuya única finalidad sea confirmar que la persona es quien afirma ser; 5.b) excluye los sistemas para detectar fraudes financieros. | S135: =IF(ISNUMBER(SEARCH("E0",$H135)),1,0) -> 0 | T135: =IF(ISNUMBER(SEARCH("E1",$H135)),1,0) -> 0 | U135: =IF(ISNUMBER(SEARCH("E2",$H135)),1,0) -> 0 | V135: =IF(ISNUMBER(SEARCH("E3",$H135)),1,0) -> 0 | W135: =IF(ISNUMBER(SEARCH("E4",$H135)),1,0) -> 0 | X135: =IF(ISNUMBER(SEARCH("E5",$H135)),1,0) -> 0 | Y135: =IF(ISNUMBER(SEARCH("E6",$H135)),1,0) -> 0 | Z135: =IF(ISNUMBER(SEARCH("E7",$H135)),1,0) -> 0 | AA135: =IF(ISNUMBER(SEARCH("E8",$H135)),1,0) -> 0 | AB135: =IF(ISNUMBER(SEARCH("E9",$H135)),1,0) -> 0 | AC135: =IF(ISNUMBER(SEARCH("TR",$H135)),1,0) -> 1 | AD135: TR | AE135: =IF(ISNUMBER(SEARCH("S0",$AD135)),1,0) -> 0 | AF135: =IF(ISNUMBER(SEARCH("R01",$AD135)),1,0) -> 0 | AG135: =IF(ISNUMBER(SEARCH("R02R03",$AD135)),1,0) -> 0 | AH135: =IF(ISNUMBER(SEARCH("R04",$AD135)),1,0) -> 0 | AI135: =IF(ISNUMBER(SEARCH("R05",$AD135)),1,0) -> 0 | AJ135: =IF(ISNUMBER(SEARCH("S3R06",$AD135)),1,0) -> 0 | AK135: =IF(ISNUMBER(SEARCH("R07",$AD135)),1,0) -> 0 | AL135: =IF(ISNUMBER(SEARCH("R09",$AD135)),1,0) -> 0 | AM135: =IF(ISNUMBER(SEARCH("R10",$AD135)),1,0) -> 0 | AN135: =IF(ISNUMBER(SEARCH("S5",$AD135)),1,0) -> 0 | AO135: =IF(ISNUMBER(SEARCH("S6",$AD135)),1,0) -> 0 | AP135: =IF(ISNUMBER(SEARCH("TR",$AD135)),1,0) -> 1
... A177: ES-EAA-16 | B177: Accesibilidad | C177: Ley 11/2023 (trasposición Ley Europea de Accesibilidad) | D177: art. 16.7 | E177: ES_ley | F177: Vigente | G177: Comunicar_autoridad | H177: TR | I177: Evaluacion_riesgo | J177: Acceso_inclusion | K177: No especificado | L177: Varios | M177: Todas_entidades_obligadas | N177: No | O177: Cuando los agentes económicos se acojan a lo dispuesto en el apartado 1 para un producto o servicio determinado remitirán información a tal fin a las correspondientes autoridades de vigilancia | P177: https://www.boe.es/buscar/act.php?id=BOE-A-2023-11022 | Q177: Alta | R177: Ámbito: prestadores de servicios bancarios para consumidores (art. 2.2.d), salvo microempresas que presten servicios (art. 3.3). No aplicable a microempresas. Destinatario real: autoridades de vigilancia designadas por las CCAA y Ceuta y Melilla (art. 27.3), no el Banco de España (se usa Varios). Título I en vigor el 28-6-2025 (DF 18.ª.2). Transitorio: DT única (productos ya usados hasta 28-6-2030; contratos previos hasta su expiración, máx. 5 años). | S177: =IF(ISNUMBER(SEARCH("E0",$H177)),1,0) -> 0 | T177: =IF(ISNUMBER(SEARCH("E1",$H177)),1,0) -> 0 | U177: =IF(ISNUMBER(SEARCH("E2",$H177)),1,0) -> 0 | V177: =IF(ISNUMBER(SEARCH("E3",$H177)),1,0) -> 0 | W177: =IF(ISNUMBER(SEARCH("E4",$H177)),1,0) -> 0 | X177: =IF(ISNUMBER(SEARCH("E5",$H177)),1,0) -> 0 | Y177: =IF(ISNUMBER(SEARCH("E6",$H177)),1,0) -> 0 | Z177: =IF(ISNUMBER(SEARCH("E7",$H177)),1,0) -> 0 | AA177: =IF(ISNUMBER(SEARCH("E8",$H177)),1,0) -> 0 | AB177: =IF(ISNUMBER(SEARCH("E9",$H177)),1,0) -> 0 | AC177: =IF(ISNUMBER(SEARCH("TR",$H177)),1,0) -> 1 | AD177: TR | AE177: =IF(ISNUMBER(SEARCH("S0",$AD177)),1,0) -> 0 | AF177: =IF(ISNUMBER(SEARCH("R01",$AD177)),1,0) -> 0 | AG177: =IF(ISNUMBER(SEARCH("R02R03",$AD177)),1,0) -> 0 | AH177: =IF(ISNUMBER(SEARCH("R04",$AD177)),1,0) -> 0 | AI177: =IF(ISNUMBER(SEARCH("R05",$AD177)),1,0) -> 0 | AJ177: =IF(ISNUMBER(SEARCH("S3R06",$AD177)),1,0) -> 0 | AK177: =IF(ISNUMBER(SEARCH("R07",$AD177)),1,0) -> 0 | AL177: =IF(ISNUMBER(SEARCH("R09",$AD177)),1,0) -> 0 | AM177: =IF(ISNUMBER(SEARCH("R10",$AD177)),1,0) -> 0 | AN177: =IF(ISNUMBER(SEARCH("S5",$AD177)),1,0) -> 0 | AO177: =IF(ISNUMBER(SEARCH("S6",$AD177)),1,0) -> 0 | AP177: =IF(ISNUMBER(SEARCH("TR",$AD177)),1,0) -> 1

Sheet Resumen
A1: Resumen de la codificación
A3: Total de obligaciones | B3: =COUNTA(Codificacion!$A$2:$A$177) -> 176
A4: Citas literales verificadas en el texto oficial | B4: =COUNTIF(Codificacion!$Q$2:$Q$177,"Alta") -> 176
A5: Alcanzan a solicitudes no culminadas (Sí o Parcial) | B5: =COUNTIF(Codificacion!$N$2:$N$177,"Si")+COUNTIF(Codificacion!$N$2:$N$177,"Parcial") -> 153 | C5: =B5/B3 -> 0.86931818
A6: Clasificaciones de cobertura E/C/G con confianza alta (Auditoria_ECG0) | B6: =COUNTIF(Auditoria_ECG0!$I$2:$I$177,"Alta") -> 152 | C6: =B6/B3 -> 0.86363636
A7: Por familia normativa
A8: Valor | B8: Obligaciones | C8: % del total | D8: Cubre no culminado: Sí | E8: Parcial | F8: No
A9: Cuenta básica | B9: =COUNTIF(Codificacion!$B$2:$B$177,$A9) -> 24 | C9: =IF($B$3=0,0,B9/$B$3) -> 0.13636364 | D9: =COUNTIFS(Codificacion!$B$2:$B$177,$A9,Codificacion!$N$2:$N$177,"Si") -> 22 | E9: =COUNTIFS(Codificacion!$B$2:$B$177,$A9,Codificacion!$N$2:$N$177,"Parcial") -> 2 | F9: =COUNTIFS(Codificacion!$B$2:$B$177,$A9,Codificacion!$N$2:$N$177,"No") -> 0
A10: AML | B10: =COUNTIF(Codificacion!$B$2:$B$177,$A10) -> 42 | C10: =IF($B$3=0,0,B10/$B$3) -> 0.23863636 | D10: =COUNTIFS(Codificacion!$B$2:$B$177,$A10,Codificacion!$N$2:$N$177,"Si") -> 17 | E10: =COUNTIFS(Codificacion!$B$2:$B$177,$A10,Codificacion!$N$2:$N$177,"Parcial") -> 22 | F10: =COUNTIFS(Codificacion!$B$2:$B$177,$A10,Codificacion!$N$2:$N$177,"No") -> 3
A11: Directrices EBA | B11: =COUNTIF(Codificacion!$B$2:$B$177,$A11) -> 36 | C11: =IF($B$3=0,0,B11/$B$3) -> 0.20454545 | D11: =COUNTIFS(Codificacion!$B$2:$B$177,$A11,Codificacion!$N$2:$N$177,"Si") -> 18 | E11: =COUNTIFS(Codificacion!$B$2:$B$177,$A11,Codificacion!$N$2:$N$177,"Parcial") -> 14 | F11: =COUNTIFS(Codificacion!$B$2:$B$177,$A11,Codificacion!$N$2:$N$177,"No") -> 4
A12: RGPD | B12: =COUNTIF(Codificacion!$B$2:$B$177,$A12) -> 14 | C12: =IF($B$3=0,0,B12/$B$3) -> 0.079545455 | D12: =COUNTIFS(Codificacion!$B$2:$B$177,$A12,Codificacion!$N$2:$N$177,"Si") -> 14 | E12: =COUNTIFS(Codificacion!$B$2:$B$177,$A12,Codificacion!$N$2:$N$177,"Parcial") -> 0 | F12: =COUNTIFS(Codificacion!$B$2:$B$177,$A12,Codificacion!$N$2:$N$177,"No") -> 0
A13: AI Act | B13: =COUNTIF(Codificacion!$B$2:$B$177,$A13) -> 17 | C13: =IF($B$3=0,0,B13/$B$3) -> 0.096590909 | D13: =COUNTIFS(Codificacion!$B$2:$B$177,$A13,Codificacion!$N$2:$N$177,"Si") -> 12 | E13: =COUNTIFS(Codificacion!$B$2:$B$177,$A13,Codificacion!$N$2:$N$177,"Parcial") -> 5 | F13: =COUNTIFS(Codificacion!$B$2:$B$177,$A13,Codificacion!$N$2:$N$177,"No") -> 0
A14: DORA | B14: =COUNTIF(Codificacion!$B$2:$B$177,$A14) -> 10 | C14: =IF($B$3=0,0,B14/$B$3) -> 0.056818182 | D14: =COUNTIFS(Codificacion!$B$2:$B$177,$A14,Codificacion!$N$2:$N$177,"Si") -> 0 | E14: =COUNTIFS(Codificacion!$B$2:$B$177,$A14,Codificacion!$N$2:$N$177,"Parcial") -> 7 | F14: =COUNTIFS(Codificacion!$B$2:$B$177,$A14,Codificacion!$N$2:$N$177,"No") -> 3
A15: eIDAS 2 | B15: =COUNTIF(Codificacion!$B$2:$B$177,$A15) -> 2 | C15: =IF($B$3=0,0,B15/$B$3) -> 0.011363636 | D15: =COUNTIFS(Codificacion!$B$2:$B$177,$A15,Codificacion!$N$2:$N$177,"Si") -> 1 | E15: =COUNTIFS(Codificacion!$B$2:$B$177,$A15,Codificacion!$N$2:$N$177,"Parcial") -> 0 | F15: =COUNTIFS(Codificacion!$B$2:$B$177,$A15,Codificacion!$N$2:$N$177,"No") -> 1
A16: Accesibilidad | B16: =COUNTIF(Codificacion!$B$2:$B$177,$A16) -> 16 | C16: =IF($B$3=0,0,B16/$B$3) -> 0.090909091 | D16: =COUNTIFS(Codificacion!$B$2:$B$177,$A16,Codificacion!$N$2:$N$177,"Si") -> 0 | E16: =COUNTIFS(Codificacion!$B$2:$B$177,$A16,Codificacion!$N$2:$N$177,"Parcial") -> 6 | F16: =COUNTIFS(Codificacion!$B$2:$B$177,$A16,Codificacion!$N$2:$N$177,"No") -> 10
A17: Atención al cliente ES | B17: =COUNTIF(Codificacion!$B$2:$B$177,$A17) -> 15 | C17: =IF($B$3=0,0,B17/$B$3) -> 0.085227273 | D17: =COUNTIFS(Codificacion!$B$2:$B$177,$A17,Codificacion!$N$2:$N$177,"Si") -> 2 | E17: =COUNTIFS(Codificacion!$B$2:$B$177,$A17,Codificacion!$N$2:$N$177,"Parcial") -> 11 | F17: =COUNTIFS(Codificacion!$B$2:$B$177,$A17,Codificacion!$N$2:$N$177,"No") -> 2
A18: Total | B18: =SUM(B9:B17) -> 176 | D18: =SUM(D9:D17) -> 86 | E18: =SUM(E9:E17) -> 67 | F18: =SUM(F9:F17) -> 23
A20: Por tipo de obligación
A21: Valor | B21: Obligaciones | C21: % del total | D21: Cubre no culminado: Sí | E21: Parcial | F21: No
A22: Registrar | B22: =COUNTIF(Codificacion!$G$2:$G$177,$A22) -> 32 | C22: =IF($B$3=0,0,B22/$B$3) -> 0.18181818 | D22: =COUNTIFS(Codificacion!$G$2:$G$177,$A22,Codificacion!$N$2:$N$177,"Si") -> 10 | E22: =COUNTIFS(Codificacion!$G$2:$G$177,$A22,Codificacion!$N$2:$N$177,"Parcial") -> 17 | F22: =COUNTIFS(Codificacion!$G$2:$G$177,$A22,Codificacion!$N$2:$N$177,"No") -> 5
A23: Conservar | B23: =COUNTIF(Codificacion!$G$2:$G$177,$A23) -> 19 | C23: =IF($B$3=0,0,B23/$B$3) -> 0.10795455 | D23: =COUNTIFS(Codificacion!$G$2:$G$177,$A23,Codificacion!$N$2:$N$177,"Si") -> 11 | E23: =COUNTIFS(Codificacion!$G$2:$G$177,$A23,Codificacion!$N$2:$N$177,"Parcial") -> 4 | F23: =COUNTIFS(Codificacion!$G$2:$G$177,$A23,Codificacion!$N$2:$N$177,"No") -> 4
A24: Comunicar_autoridad | B24: =COUNTIF(Codificacion!$G$2:$G$177,$A24) -> 11 | C24: =IF($B$3=0,0,B24/$B$3) -> 0.0625 | D24: =COUNTIFS(Codificacion!$G$2:$G$177,$A24,Codificacion!$N$2:$N$177,"Si") -> 4 | E24: =COUNTIFS(Codificacion!$G$2:$G$177,$A24,Codificacion!$N$2:$N$177,"Parcial") -> 2 | F24: =COUNTIFS(Codificacion!$G$2:$G$177,$A24,Codificacion!$N$2:$N$177,"No") -> 5
A25: Informar_interesado | B25: =COUNTIF(Codificacion!$G$2:$G$177,$A25) -> 36 | C25: =IF($B$3=0,0,B25/$B$3) -> 0.20454545 | D25: =COUNTIFS(Codificacion!$G$2:$G$177,$A25,Codificacion!$N$2:$N$177,"Si") -> 22 | E25: =COUNTIFS(Codificacion!$G$2:$G$177,$A25,Codificacion!$N$2:$N$177,"Parcial") -> 12 | F25: =COUNTIFS(Codificacion!$G$2:$G$177,$A25,Codificacion!$N$2:$N$177,"No") -> 2
A26: Motivar | B26: =COUNTIF(Codificacion!$G$2:$G$177,$A26) -> 8 | C26: =IF($B$3=0,0,B26/$B$3) -> 0.045454545 | D26: =COUNTIFS(Codificacion!$G$2:$G$177,$A26,Codificacion!$N$2:$N$177,"Si") -> 5 | E26: =COUNTIFS(Codificacion!$G$2:$G$177,$A26,Codificacion!$N$2:$N$177,"Parcial") -> 2 | F26: =COUNTIFS(Codificacion!$G$2:$G$177,$A26,Codificacion!$N$2:$N$177,"No") -> 1
A27: Evaluar_riesgo | B27: =COUNTIF(Codificacion!$G$2:$G$177,$A27) -> 32 | C27: =IF($B$3=0,0,B27/$B$3) -> 0.18181818 | D27: =COUNTIFS(Codificacion!$G$2:$G$177,$A27,Codificacion!$N$2:$N$177,"Si") -> 9 | E27: =COUNTIFS(Codificacion!$G$2:$G$177,$A27,Codificacion!$N$2:$N$177,"Parcial") -> 17 | F27: =COUNTIFS(Codificacion!$G$2:$G$177,$A27,Codificacion!$N$2:$N$177,"No") -> 6
A28: Supervision_humana | B28: =COUNTIF(Codificacion!$G$2:$G$177,$A28) -> 13 | C28: =IF($B$3=0,0,B28/$B$3) -> 0.073863636 | D28: =COUNTIFS(Codificacion!$G$2:$G$177,$A28,Codificacion!$N$2:$N$177,"Si") -> 9 | E28: =COUNTIFS(Codificacion!$G$2:$G$177,$A28,Codificacion!$N$2:$N$177,"Parcial") -> 4 | F28: =COUNTIFS(Codificacion!$G$2:$G$177,$A28,Codificacion!$N$2:$N$177,"No") -> 0
A29: Notificar_incidente | B29: =COUNTIF(Codificacion!$G$2:$G$177,$A29) -> 2 | C29: =IF($B$3=0,0,B29/$B$3) -> 0.011363636 | D29: =COUNTIFS(Codificacion!$G$2:$G$177,$A29,Codificacion!$N$2:$N$177,"Si") -> 0 | E29: =COUNTIFS(Codificacion!$G$2:$G$177,$A29,Codificacion!$N$2:$N$177,"Parcial") -> 2 | F29: =COUNTIFS(Codificacion!$G$2:$G$177,$A29,Codificacion!$N$2:$N$177,"No") -> 0
A30: Abstenerse | B30: =COUNTIF(Codificacion!$G$2:$G$177,$A30) -> 23 | C30: =IF($B$3=0,0,B30/$B$3) -> 0.13068182 | D30: =COUNTIFS(Codificacion!$G$2:$G$177,$A30,Codificacion!$N$2:$N$177,"Si") -> 16 | E30: =COUNTIFS(Codificacion!$G$2:$G$177,$A30,Codificacion!$N$2:$N$177,"Parcial") -> 7 | F30: =COUNTIFS(Codificacion!$G$2:$G$177,$A30,Codificacion!$N$2:$N$177,"No") -> 0
A31: Total | B31: =SUM(B22:B30) -> 176 | D31: =SUM(D22:D30) -> 86 | E31: =SUM(E22:E30) -> 67 | F31: =SUM(F22:F30) -> 23
A33: Por finalidad
A34: Valor | B34: Obligaciones | C34: % del total | D34: Cubre no culminado: Sí | E34: Parcial | F34: No
A35: Diligencia_debida_AML | B35: =COUNTIF(Codificacion!$J$2:$J$177,$A35) -> 52 | C35: =IF($B$3=0,0,B35/$B$3) -> 0.29545455 | D35: =COUNTIFS(Codificacion!$J$2:$J$177,$A35,Codificacion!$N$2:$N$177,"Si") -> 19 | E35: =COUNTIFS(Codificacion!$J$2:$J$177,$A35,Codificacion!$N$2:$N$177,"Parcial") -> 27 | F35: =COUNTIFS(Codificacion!$J$2:$J$177,$A35,Codificacion!$N$2:$N$177,"No") -> 6
A36: Prevencion_fraude | B36: =COUNTIF(Codificacion!$J$2:$J$177,$A36) -> 8 | C36: =IF($B$3=0,0,B36/$B$3) -> 0.045454545 | D36: =COUNTIFS(Codificacion!$J$2:$J$177,$A36,Codificacion!$N$2:$N$177,"Si") -> 6 | E36: =COUNTIFS(Codificacion!$J$2:$J$177,$A36,Codificacion!$N$2:$N$177,"Parcial") -> 1 | F36: =COUNTIFS(Codificacion!$J$2:$J$177,$A36,Codificacion!$N$2:$N$177,"No") -> 1
A37: Transparencia_consumidor | B37: =COUNTIF(Codificacion!$J$2:$J$177,$A37) -> 13 | C37: =IF($B$3=0,0,B37/$B$3) -> 0.073863636 | D37: =COUNTIFS(Codificacion!$J$2:$J$177,$A37,Codificacion!$N$2:$N$177,"Si") -> 7 | E37: =COUNTIFS(Codificacion!$J$2:$J$177,$A37,Codificacion!$N$2:$N$177,"Parcial") -> 3 | F37: =COUNTIFS(Codificacion!$J$2:$J$177,$A37,Codificacion!$N$2:$N$177,"No") -> 3
A38: Acceso_inclusion | B38: =COUNTIF(Codificacion!$J$2:$J$177,$A38) -> 42 | C38: =IF($B$3=0,0,B38/$B$3) -> 0.23863636 | D38: =COUNTIFS(Codificacion!$J$2:$J$177,$A38,Codificacion!$N$2:$N$177,"Si") -> 21 | E38: =COUNTIFS(Codificacion!$J$2:$J$177,$A38,Codificacion!$N$2:$N$177,"Parcial") -> 12 | F38: =COUNTIFS(Codificacion!$J$2:$J$177,$A38,Codificacion!$N$2:$N$177,"No") -> 9
A39: Proteccion_datos | B39: =COUNTIF(Codificacion!$J$2:$J$177,$A39) -> 20 | C39: =IF($B$3=0,0,B39/$B$3) -> 0.11363636 | D39: =COUNTIFS(Codificacion!$J$2:$J$177,$A39,Codificacion!$N$2:$N$177,"Si") -> 16 | E39: =COUNTIFS(Codificacion!$J$2:$J$177,$A39,Codificacion!$N$2:$N$177,"Parcial") -> 3 | F39: =COUNTIFS(Codificacion!$J$2:$J$177,$A39,Codificacion!$N$2:$N$177,"No") -> 1
A40: Trazabilidad_IA | B40: =COUNTIF(Codificacion!$J$2:$J$177,$A40) -> 15 | C40: =IF($B$3=0,0,B40/$B$3) -> 0.085227273 | D40: =COUNTIFS(Codificacion!$J$2:$J$177,$A40,Codificacion!$N$2:$N$177,"Si") -> 11 | E40: =COUNTIFS(Codificacion!$J$2:$J$177,$A40,Codificacion!$N$2:$N$177,"Parcial") -> 4 | F40: =COUNTIFS(Codificacion!$J$2:$J$177,$A40,Codificacion!$N$2:$N$177,"No") -> 0
A41: Resiliencia_operativa | B41: =COUNTIF(Codificacion!$J$2:$J$177,$A41) -> 11 | C41: =IF($B$3=0,0,B41/$B$3) -> 0.0625 | D41: =COUNTIFS(Codificacion!$J$2:$J$177,$A41,Codificacion!$N$2:$N$177,"Si") -> 0 | E41: =COUNTIFS(Codificacion!$J$2:$J$177,$A41,Codificacion!$N$2:$N$177,"Parcial") -> 8 | F41: =COUNTIFS(Codificacion!$J$2:$J$177,$A41,Codificacion!$N$2:$N$177,"No") -> 3
A42: Reclamaciones | B42: =COUNTIF(Codificacion!$J$2:$J$177,$A42) -> 15 | C42: =IF($B$3=0,0,B42/$B$3) -> 0.085227273 | D42: =COUNTIFS(Codificacion!$J$2:$J$177,$A42,Codificacion!$N$2:$N$177,"Si") -> 6 | E42: =COUNTIFS(Codificacion!$J$2:$J$177,$A42,Codificacion!$N$2:$N$177,"Parcial") -> 9 | F42: =COUNTIFS(Codificacion!$J$2:$J$177,$A42,Codificacion!$N$2:$N$177,"No") -> 0
A43: Total | B43: =SUM(B35:B42) -> 176 | D43: =SUM(D35:D42) -> 86 | E43: =SUM(E35:E42) -> 67 | F43: =SUM(F35:F42) -> 23
A45: Solapamiento: categoría de dato exigida por cada familia normativa
A46: Un dato exigido por dos o más familias con finalidades distintas es candidato a evidencia reutilizable.
A47: Dato | B47: Cuenta básica | C47: AML | D47: Directrices EBA | E47: RGPD | F47: AI Act | G47: DORA | H47: eIDAS 2 | I47: Accesibilidad | J47: Atención al cliente ES | K47: Familias que lo exigen | L47: Finalidades distintas
A48: Identidad | B48: =COUNTIFS(Codificacion!$I$2:$I$177,$A48,Codificacion!$B$2:$B$177,"Cuenta básica") -> 1 | C48: =COUNTIFS(Codificacion!$I$2:$I$177,$A48,Codificacion!$B$2:$B$177,"AML") -> 5 | D48: =COUNTIFS(Codificacion!$I$2:$I$177,$A48,Codificacion!$B$2:$B$177,"Directrices EBA") -> 1 | E48: =COUNTIFS(Codificacion!$I$2:$I$177,$A48,Codificacion!$B$2:$B$177,"RGPD") -> 1 | F48: =COUNTIFS(Codificacion!$I$2:$I$177,$A48,Codificacion!$B$2:$B$177,"AI Act") -> 0 | G48: =COUNTIFS(Codificacion!$I$2:$I$177,$A48,Codificacion!$B$2:$B$177,"DORA") -> 0 | H48: =COUNTIFS(Codificacion!$I$2:$I$177,$A48,Codificacion!$B$2:$B$177,"eIDAS 2") -> 1 | I48: =COUNTIFS(Codificacion!$I$2:$I$177,$A48,Codificacion!$B$2:$B$177,"Accesibilidad") -> 1 | J48: =COUNTIFS(Codificacion!$I$2:$I$177,$A48,Codificacion!$B$2:$B$177,"Atención al cliente ES") -> 0 | K48: =COUNTIF(B48:J48,">0") -> 6 | L48: =(COUNTIFS(Codificacion!$I$2:$I$177,$A48,Codificacion!$J$2:$J$177,"Diligencia_debida_AML")>0)+(COUNTIFS(Codificacion!$I$2:$I$177,$A48,Codificacion!$J$2:$J$177,"Prevencion_fraude")>0)+(COUNTIFS(Codificacion!$I$2:$I$177,$A48,Codificacion!$J$2:$J$177,"Transparencia_consumidor")>0)+(COUNTIFS(Codificacion!$I$2:$I$177,$A48,Codificacion!$J$2:$J$177,"Acceso_inclusion")>0)+(COUNTIFS(Codificacion!$I$2:$I$177,$A48,Codificacion!$J$2:$J$177,"Proteccion_datos")>0)+(COUNTIFS(Codificacion!$I$2:$I$177,$A48,Codificacion!$J$2:$J$177,"Trazabilidad_IA")>0)+(COUNTIFS(Codificacion!$I$2:$I$177,$A48,Codificacion!$J$2:$J$177,"Resiliencia_operativa")>0)+(COUNTIFS(Codificacion!$I$2:$I$177,$A48,Codificacion!$J$2:$J$177,"Reclamaciones")>0) -> 3
A49: Documento_identidad | B49: =COUNTIFS(Codificacion!$I$2:$I$177,$A49,Codificacion!$B$2:$B$177,"Cuenta básica") -> 0 | C49: =COUNTIFS(Codificacion!$I$2:$I$177,$A49,Codificacion!$B$2:$B$177,"AML") -> 4 | D49: =COUNTIFS(Codificacion!$I$2:$I$177,$A49,Codificacion!$B$2:$B$177,"Directrices EBA") -> 4 | E49: =COUNTIFS(Codificacion!$I$2:$I$177,$A49,Codificacion!$B$2:$B$177,"RGPD") -> 0 | F49: =COUNTIFS(Codificacion!$I$2:$I$177,$A49,Codificacion!$B$2:$B$177,"AI Act") -> 0 | G49: =COUNTIFS(Codificacion!$I$2:$I$177,$A49,Codificacion!$B$2:$B$177,"DORA") -> 0 | H49: =COUNTIFS(Codificacion!$I$2:$I$177,$A49,Codificacion!$B$2:$B$177,"eIDAS 2") -> 0 | I49: =COUNTIFS(Codificacion!$I$2:$I$177,$A49,Codificacion!$B$2:$B$177,"Accesibilidad") -> 0 | J49: =COUNTIFS(Codificacion!$I$2:$I$177,$A49,Codificacion!$B$2:$B$177,"Atención al cliente ES") -> 0 | K49: =COUNTIF(B49:J49,">0") -> 2 | L49: =(COUNTIFS(Codificacion!$I$2:$I$177,$A49,Codificacion!$J$2:$J$177,"Diligencia_debida_AML")>0)+(COUNTIFS(Codificacion!$I$2:$I$177,$A49,Codificacion!$J$2:$J$177,"Prevencion_fraude")>0)+(COUNTIFS(Codificacion!$I$2:$I$177,$A49,Codificacion!$J$2:$J$177,"Transparencia_consumidor")>0)+(COUNTIFS(Codificacion!$I$2:$I$177,$A49,Codificacion!$J$2:$J$177,"Acceso_inclusion")>0)+(COUNTIFS(Codificacion!$I$2:$I$177,$A49,Codificacion!$J$2:$J$177,"Proteccion_datos")>0)+(COUNTIFS(Codificacion!$I$2:$I$177,$A49,Codificacion!$J$2:$J$177,"Trazabilidad_IA")>0)+(COUNTIFS(Codificacion!$I$2:$I$177,$A49,Codificacion!$J$2:$J$177,"Resiliencia_operativa")>0)+(COUNTIFS(Codificacion!$I$2:$I$177,$A49,Codificacion!$J$2:$J$177,"Reclamaciones")>0) -> 2
A50: Resultado_verificacion | B50: =COUNTIFS(Codificacion!$I$2:$I$177,$A50,Codificacion!$B$2:$B$177,"Cuenta básica") -> 3 | C50: =COUNTIFS(Codificacion!$I$2:$I$177,$A50,Codificacion!$B$2:$B$177,"AML") -> 9 | D50: =COUNTIFS(Codificacion!$I$2:$I$177,$A50,Codificacion!$B$2:$B$177,"Directrices EBA") -> 5 | E50: =COUNTIFS(Codificacion!$I$2:$I$177,$A50,Codificacion!$B$2:$B$177,"RGPD") -> 0 | F50: =COUNTIFS(Codificacion!$I$2:$I$177,$A50,Codificacion!$B$2:$B$177,"AI Act") -> 0 | G50: =COUNTIFS(Codificacion!$I$2:$I$177,$A50,Codificacion!$B$2:$B$177,"DORA") -> 0 | H50: =COUNTIFS(Codificacion!$I$2:$I$177,$A50,Codificacion!$B$2:$B$177,"eIDAS 2") -> 0 | I50: =COUNTIFS(Codificacion!$I$2:$I$177,$A50,Codificacion!$B$2:$B$177,"Accesibilidad") -> 0 | J50: =COUNTIFS(Codificacion!$I$2:$I$177,$A50,Codificacion!$B$2:$B$177,"Atención al cliente ES") -> 0 | K50: =COUNTIF(B50:J50,">0") -> 3 | L50: =(COUNTIFS(Codificacion!$I$2:$I$177,$A50,Codificacion!$J$2:$J$177,"Diligencia_debida_AML")>0)+(COUNTIFS(Codificacion!$I$2:$I$177,$A50,Codificacion!$J$2:$J$177,"Prevencion_fraude")>0)+(COUNTIFS(Codificacion!$I$2:$I$177,$A50,Codificacion!$J$2:$J$177,"Transparencia_consumidor")>0)+(COUNTIFS(Codificacion!$I$2:$I$177,$A50,Codificacion!$J$2:$J$177,"Acceso_inclusion")>0)+(COUNTIFS(Codificacion!$I$2:$I$177,$A50,Codificacion!$J$2:$J$177,"Proteccion_datos")>0)+(COUNTIFS(Codificacion!$I$2:$I$177,$A50,Codificacion!$J$2:$J$177,"Trazabilidad_IA")>0)+(COUNTIFS(Codificacion!$I$2:$I$177,$A50,Codificacion!$J$2:$J$177,"Resiliencia_operativa")>0)+(COUNTIFS(Codificacion!$I$2:$I$177,$A50,Codificacion!$J$2:$J$177,"Reclamaciones")>0) -> 3
A51: Motivo_decision | B51: =COUNTIFS(Codificacion!$I$2:$I$177,$A51,Codificacion!$B$2:$B$177,"Cuenta básica") -> 11 | C51: =COUNTIFS(Codificacion!$I$2:$I$177,$A51,Codificacion!$B$2:$B$177,"AML") -> 9 | D51: =COUNTIFS(Codificacion!$I$2:$I$177,$A51,Codificacion!$B$2:$B$177,"Directrices EBA") -> 5 | E51: =COUNTIFS(Codificacion!$I$2:$I$177,$A51,Codificacion!$B$2:$B$177,"RGPD") -> 1 | F51: =COUNTIFS(Codificacion!$I$2:$I$177,$A51,Codificacion!$B$2:$B$177,"AI Act") -> 1 | G51: =COUNTIFS(Codificacion!$I$2:$I$177,$A51,Codificacion!$B$2:$B$177,"DORA") -> 0 | H51: =COUNTIFS(Codificacion!$I$2:$I$177,$A51,Codificacion!$B$2:$B$177,"eIDAS 2") -> 0 | I51: =COUNTIFS(Codificacion!$I$2:$I$177,$A51,Codificacion!$B$2:$B$177,"Accesibilidad") -> 0 | J51: =COUNTIFS(Codificacion!$I$2:$I$177,$A51,Codificacion!$B$2:$B$177,"Atención al cliente ES") -> 8 | K51: =COUNTIF(B51:J51,">0") -> 6 | L51: =(COUNTIFS(Codificacion!$I$2:$I$177,$A51,Codificacion!$J$2:$J$177,"Diligencia_debida_AML")>0)+(COUNTIFS(Codificacion!$I$2:$I$177,$A51,Codificacion!$J$2:$J$177,"Prevencion_fraude")>0)+(COUNTIFS(Codificacion!$I$2:$I$177,$A51,Codificacion!$J$2:$J$177,"Transparencia_consumidor")>0)+(COUNTIFS(Codificacion!$I$2:$I$177,$A51,Codificacion!$J$2:$J$177,"Acceso_inclusion")>0)+(COUNTIFS(Codificacion!$I$2:$I$177,$A51,Codificacion!$J$2:$J$177,"Proteccion_datos")>0)+(COUNTIFS(Codificacion!$I$2:$I$177,$A51,Codificacion!$J$2:$J$177,"Trazabilidad_IA")>0)+(COUNTIFS(Codificacion!$I$2:$I$177,$A51,Codificacion!$J$2:$J$177,"Resiliencia_operativa")>0)+(COUNTIFS(Codificacion!$I$2:$I$177,$A51,Codificacion!$J$2:$J$177,"Reclamaciones")>0) -> 5
A52: Logs_sistema | B52: =COUNTIFS(Codificacion!$I$2:$I$177,$A52,Codificacion!$B$2:$B$177,"Cuenta básica") -> 0 | C52: =COUNTIFS(Codificacion!$I$2:$I$177,$A52,Codificacion!$B$2:$B$177,"AML") -> 0 | D52: =COUNTIFS(Codificacion!$I$2:$I$177,$A52,Codificacion!$B$2:$B$177,"Directrices EBA") -> 5 | E52: =COUNTIFS(Codificacion!$I$2:$I$177,$A52,Codificacion!$B$2:$B$177,"RGPD") -> 0 | F52: =COUNTIFS(Codificacion!$I$2:$I$177,$A52,Codificacion!$B$2:$B$177,"AI Act") -> 7 | G52: =COUNTIFS(Codificacion!$I$2:$I$177,$A52,Codificacion!$B$2:$B$177,"DORA") -> 0 | H52: =COUNTIFS(Codificacion!$I$2:$I$177,$A52,Codificacion!$B$2:$B$177,"eIDAS 2") -> 0 | I52: =COUNTIFS(Codificacion!$I$2:$I$177,$A52,Codificacion!$B$2:$B$177,"Accesibilidad") -> 0 | J52: =COUNTIFS(Codificacion!$I$2:$I$177,$A52,Codificacion!$B$2:$B$177,"Atención al cliente ES") -> 0 | K52: =COUNTIF(B52:J52,">0") -> 2 | L52: =(COUNTIFS(Codificacion!$I$2:$I$177,$A52,Codificacion!$J$2:$J$177,"Diligencia_debida_AML")>0)+(COUNTIFS(Codificacion!$I$2:$I$177,$A52,Codificacion!$J$2:$J$177,"Prevencion_fraude")>0)+(COUNTIFS(Codificacion!$I$2:$I$177,$A52,Codificacion!$J$2:$J$177,"Transparencia_consumidor")>0)+(COUNTIFS(Codificacion!$I$2:$I$177,$A52,Codificacion!$J$2:$J$177,"Acceso_inclusion")>0)+(COUNTIFS(Codificacion!$I$2:$I$177,$A52,Codificacion!$J$2:$J$177,"Proteccion_datos")>0)+(COUNTIFS(Codificacion!$I$2:$I$177,$A52,Codificacion!$J$2:$J$177,"Trazabilidad_IA")>0)+(COUNTIFS(Codificacion!$I$2:$I$177,$A52,Codificacion!$J$2:$J$177,"Resiliencia_operativa")>0)+(COUNTIFS(Codificacion!$I$2:$I$177,$A52,Codificacion!$J$2:$J$177,"Reclamaciones")>0) -> 3
A53: Informacion_tratamiento | B53: =COUNTIFS(Codificacion!$I$2:$I$177,$A53,Codificacion!$B$2:$B$177,"Cuenta básica") -> 5 | C53: =COUNTIFS(Codificacion!$I$2:$I$177,$A53,Codificacion!$B$2:$B$177,"AML") -> 1 | D53: =COUNTIFS(Codificacion!$I$2:$I$177,$A53,Codificacion!$B$2:$B$177,"Directrices EBA") -> 1 | E53: =COUNTIFS(Codificacion!$I$2:$I$177,$A53,Codificacion!$B$2:$B$177,"RGPD") -> 4 | F53: =COUNTIFS(Codificacion!$I$2:$I$177,$A53,Codificacion!$B$2:$B$177,"AI Act") -> 2 | G53: =COUNTIFS(Codificacion!$I$2:$I$177,$A53,Codificacion!$B$2:$B$177,"DORA") -> 0 | H53: =COUNTIFS(Codificacion!$I$2:$I$177,$A53,Codificacion!$B$2:$B$177,"eIDAS 2") -> 1 | I53: =COUNTIFS(Codificacion!$I$2:$I$177,$A53,Codificacion!$B$2:$B$177,"Accesibilidad") -> 5 | J53: =COUNTIFS(Codificacion!$I$2:$I$177,$A53,Codificacion!$B$2:$B$177,"Atención al cliente ES") -> 3 | K53: =COUNTIF(B53:J53,">0") -> 8 | L53: =(COUNTIFS(Codificacion!$I$2:$I$177,$A53,Codificacion!$J$2:$J$177,"Diligencia_debida_AML")>0)+(COUNTIFS(Codificacion!$I$2:$I$177,$A53,Codificacion!$J$2:$J$177,"Prevencion_fraude")>0)+(COUNTIFS(Codificacion!$I$2:$I$177,$A53,Codificacion!$J$2:$J$177,"Transparencia_consumidor")>0)+(COUNTIFS(Codificacion!$I$2:$I$177,$A53,Codificacion!$J$2:$J$177,"Acceso_inclusion")>0)+(COUNTIFS(Codificacion!$I$2:$I$177,$A53,Codificacion!$J$2:$J$177,"Proteccion_datos")>0)+(COUNTIFS(Codificacion!$I$2:$I$177,$A53,Codificacion!$J$2:$J$177,"Trazabilidad_IA")>0)+(COUNTIFS(Codificacion!$I$2:$I$177,$A53,Codificacion!$J$2:$J$177,"Resiliencia_operativa")>0)+(COUNTIFS(Codificacion!$I$2:$I$177,$A53,Codificacion!$J$2:$J$177,"Reclamaciones")>0) -> 5
A54: Evaluacion_riesgo | B54: =COUNTIFS(Codificacion!$I$2:$I$177,$A54,Codificacion!$B$2:$B$177,"Cuenta básica") -> 0 | C54: =COUNTIFS(Codificacion!$I$2:$I$177,$A54,Codificacion!$B$2:$B$177,"AML") -> 8 | D54: =COUNTIFS(Codificacion!$I$2:$I$177,$A54,Codificacion!$B$2:$B$177,"Directrices EBA") -> 6 | E54: =COUNTIFS(Codificacion!$I$2:$I$177,$A54,Codificacion!$B$2:$B$177,"RGPD") -> 1 | F54: =COUNTIFS(Codificacion!$I$2:$I$177,$A54,Codificacion!$B$2:$B$177,"AI Act") -> 3 | G54: =COUNTIFS(Codificacion!$I$2:$I$177,$A54,Codificacion!$B$2:$B$177,"DORA") -> 0 | H54: =COUNTIFS(Codificacion!$I$2:$I$177,$A54,Codificacion!$B$2:$B$177,"eIDAS 2") -> 0 | I54: =COUNTIFS(Codificacion!$I$2:$I$177,$A54,Codificacion!$B$2:$B$177,"Accesibilidad") -> 5 | J54: =COUNTIFS(Codificacion!$I$2:$I$177,$A54,Codificacion!$B$2:$B$177,"Atención al cliente ES") -> 0 | K54: =COUNTIF(B54:J54,">0") -> 5 | L54: =(COUNTIFS(Codificacion!$I$2:$I$177,$A54,Codificacion!$J$2:$J$177,"Diligencia_debida_AML")>0)+(COUNTIFS(Codificacion!$I$2:$I$177,$A54,Codificacion!$J$2:$J$177,"Prevencion_fraude")>0)+(COUNTIFS(Codificacion!$I$2:$I$177,$A54,Codificacion!$J$2:$J$177,"Transparencia_consumidor")>0)+(COUNTIFS(Codificacion!$I$2:$I$177,$A54,Codificacion!$J$2:$J$177,"Acceso_inclusion")>0)+(COUNTIFS(Codificacion!$I$2:$I$177,$A54,Codificacion!$J$2:$J$177,"Proteccion_datos")>0)+(COUNTIFS(Codificacion!$I$2:$I$177,$A54,Codificacion!$J$2:$J$177,"Trazabilidad_IA")>0)+(COUNTIFS(Codificacion!$I$2:$I$177,$A54,Codificacion!$J$2:$J$177,"Resiliencia_operativa")>0)+(COUNTIFS(Codificacion!$I$2:$I$177,$A54,Codificacion!$J$2:$J$177,"Reclamaciones")>0) -> 4
A55: Intervencion_humana | B55: =COUNTIFS(Codificacion!$I$2:$I$177,$A55,Codificacion!$B$2:$B$177,"Cuenta básica") -> 0 | C55: =COUNTIFS(Codificacion!$I$2:$I$177,$A55,Codificacion!$B$2:$B$177,"AML") -> 2 | D55: =COUNTIFS(Codificacion!$I$2:$I$177,$A55,Codificacion!$B$2:$B$177,"Directrices EBA") -> 4 | E55: =COUNTIFS(Codificacion!$I$2:$I$177,$A55,Codificacion!$B$2:$B$177,"RGPD") -> 1 | F55: =COUNTIFS(Codificacion!$I$2:$I$177,$A55,Codificacion!$B$2:$B$177,"AI Act") -> 3 | G55: =COUNTIFS(Codificacion!$I$2:$I$177,$A55,Codificacion!$B$2:$B$177,"DORA") -> 0 | H55: =COUNTIFS(Codificacion!$I$2:$I$177,$A55,Codificacion!$B$2:$B$177,"eIDAS 2") -> 0 | I55: =COUNTIFS(Codificacion!$I$2:$I$177,$A55,Codificacion!$B$2:$B$177,"Accesibilidad") -> 0 | J55: =COUNTIFS(Codificacion!$I$2:$I$177,$A55,Codificacion!$B$2:$B$177,"Atención al cliente ES") -> 1 | K55: =COUNTIF(B55:J55,">0") -> 5 | L55: =(COUNTIFS(Codificacion!$I$2:$I$177,$A55,Codificacion!$J$2:$J$177,"Diligencia_debida_AML")>0)+(COUNTIFS(Codificacion!$I$2:$I$177,$A55,Codificacion!$J$2:$J$177,"Prevencion_fraude")>0)+(COUNTIFS(Codificacion!$I$2:$I$177,$A55,Codificacion!$J$2:$J$177,"Transparencia_consumidor")>0)+(COUNTIFS(Codificacion!$I$2:$I$177,$A55,Codificacion!$J$2:$J$177,"Acceso_inclusion")>0)+(COUNTIFS(Codificacion!$I$2:$I$177,$A55,Codificacion!$J$2:$J$177,"Proteccion_datos")>0)+(COUNTIFS(Codificacion!$I$2:$I$177,$A55,Codificacion!$J$2:$J$177,"Trazabilidad_IA")>0)+(COUNTIFS(Codificacion!$I$2:$I$177,$A55,Codificacion!$J$2:$J$177,"Resiliencia_operativa")>0)+(COUNTIFS(Codificacion!$I$2:$I$177,$A55,Codificacion!$J$2:$J$177,"Reclamaciones")>0) -> 5
A56: Incidente_TIC | B56: =COUNTIFS(Codificacion!$I$2:$I$177,$A56,Codificacion!$B$2:$B$177,"Cuenta básica") -> 0 | C56: =COUNTIFS(Codificacion!$I$2:$I$177,$A56,Codificacion!$B$2:$B$177,"AML") -> 0 | D56: =COUNTIFS(Codificacion!$I$2:$I$177,$A56,Codificacion!$B$2:$B$177,"Directrices EBA") -> 2 | E56: =COUNTIFS(Codificacion!$I$2:$I$177,$A56,Codificacion!$B$2:$B$177,"RGPD") -> 0 | F56: =COUNTIFS(Codificacion!$I$2:$I$177,$A56,Codificacion!$B$2:$B$177,"AI Act") -> 0 | G56: =COUNTIFS(Codificacion!$I$2:$I$177,$A56,Codificacion!$B$2:$B$177,"DORA") -> 8 | H56: =COUNTIFS(Codificacion!$I$2:$I$177,$A56,Codificacion!$B$2:$B$177,"eIDAS 2") -> 0 | I56: =COUNTIFS(Codificacion!$I$2:$I$177,$A56,Codificacion!$B$2:$B$177,"Accesibilidad") -> 0 | J56: =COUNTIFS(Codificacion!$I$2:$I$177,$A56,Codificacion!$B$2:$B$177,"Atención al cliente ES") -> 0 | K56: =COUNTIF(B56:J56,">0") -> 2 | L56: =(COUNTIFS(Codificacion!$I$2:$I$177,$A56,Codificacion!$J$2:$J$177,"Diligencia_debida_AML")>0)+(COUNTIFS(Codificacion!$I$2:$I$177,$A56,Codificacion!$J$2:$J$177,"Prevencion_fraude")>0)+(COUNTIFS(Codificacion!$I$2:$I$177,$A56,Codificacion!$J$2:$J$177,"Transparencia_consumidor")>0)+(COUNTIFS(Codificacion!$I$2:$I$177,$A56,Codificacion!$J$2:$J$177,"Acceso_inclusion")>0)+(COUNTIFS(Codificacion!$I$2:$I$177,$A56,Codificacion!$J$2:$J$177,"Proteccion_datos")>0)+(COUNTIFS(Codificacion!$I$2:$I$177,$A56,Codificacion!$J$2:$J$177,"Trazabilidad_IA")>0)+(COUNTIFS(Codificacion!$I$2:$I$177,$A56,Codificacion!$J$2:$J$177,"Resiliencia_operativa")>0)+(COUNTIFS(Codificacion!$I$2:$I$177,$A56,Codificacion!$J$2:$J$177,"Reclamaciones")>0) -> 2
A57: Proveedor_tercero | B57: =COUNTIFS(Codificacion!$I$2:$I$177,$A57,Codificacion!$B$2:$B$177,"Cuenta básica") -> 0 | C57: =COUNTIFS(Codificacion!$I$2:$I$177,$A57,Codificacion!$B$2:$B$177,"AML") -> 0 | D57: =COUNTIFS(Codificacion!$I$2:$I$177,$A57,Codificacion!$B$2:$B$177,"Directrices EBA") -> 2 | E57: =COUNTIFS(Codificacion!$I$2:$I$177,$A57,Codificacion!$B$2:$B$177,"RGPD") -> 0 | F57: =COUNTIFS(Codificacion!$I$2:$I$177,$A57,Codificacion!$B$2:$B$177,"AI Act") -> 0 | G57: =COUNTIFS(Codificacion!$I$2:$I$177,$A57,Codificacion!$B$2:$B$177,"DORA") -> 2 | H57: =COUNTIFS(Codificacion!$I$2:$I$177,$A57,Codificacion!$B$2:$B$177,"eIDAS 2") -> 0 | I57: =COUNTIFS(Codificacion!$I$2:$I$177,$A57,Codificacion!$B$2:$B$177,"Accesibilidad") -> 1 | J57: =COUNTIFS(Codificacion!$I$2:$I$177,$A57,Codificacion!$B$2:$B$177,"Atención al cliente ES") -> 0 | K57: =COUNTIF(B57:J57,">0") -> 3 | L57: =(COUNTIFS(Codificacion!$I$2:$I$177,$A57,Codificacion!$J$2:$J$177,"Diligencia_debida_AML")>0)+(COUNTIFS(Codificacion!$I$2:$I$177,$A57,Codificacion!$J$2:$J$177,"Prevencion_fraude")>0)+(COUNTIFS(Codificacion!$I$2:$I$177,$A57,Codificacion!$J$2:$J$177,"Transparencia_consumidor")>0)+(COUNTIFS(Codificacion!$I$2:$I$177,$A57,Codificacion!$J$2:$J$177,"Acceso_inclusion")>0)+(COUNTIFS(Codificacion!$I$2:$I$177,$A57,Codificacion!$J$2:$J$177,"Proteccion_datos")>0)+(COUNTIFS(Codificacion!$I$2:$I$177,$A57,Codificacion!$J$2:$J$177,"Trazabilidad_IA")>0)+(COUNTIFS(Codificacion!$I$2:$I$177,$A57,Codificacion!$J$2:$J$177,"Resiliencia_operativa")>0)+(COUNTIFS(Codificacion!$I$2:$I$177,$A57,Codificacion!$J$2:$J$177,"Reclamaciones")>0) -> 4
A58: Expediente_completo | B58: =COUNTIFS(Codificacion!$I$2:$I$177,$A58,Codificacion!$B$2:$B$177,"Cuenta básica") -> 4 | C58: =COUNTIFS(Codificacion!$I$2:$I$177,$A58,Codificacion!$B$2:$B$177,"AML") -> 4 | D58: =COUNTIFS(Codificacion!$I$2:$I$177,$A58,Codificacion!$B$2:$B$177,"Directrices EBA") -> 1 | E58: =COUNTIFS(Codificacion!$I$2:$I$177,$A58,Codificacion!$B$2:$B$177,"RGPD") -> 6 | F58: =COUNTIFS(Codificacion!$I$2:$I$177,$A58,Codificacion!$B$2:$B$177,"AI Act") -> 1 | G58: =COUNTIFS(Codificacion!$I$2:$I$177,$A58,Codificacion!$B$2:$B$177,"DORA") -> 0 | H58: =COUNTIFS(Codificacion!$I$2:$I$177,$A58,Codificacion!$B$2:$B$177,"eIDAS 2") -> 0 | I58: =COUNTIFS(Codificacion!$I$2:$I$177,$A58,Codificacion!$B$2:$B$177,"Accesibilidad") -> 4 | J58: =COUNTIFS(Codificacion!$I$2:$I$177,$A58,Codificacion!$B$2:$B$177,"Atención al cliente ES") -> 3 | K58: =COUNTIF(B58:J58,">0") -> 7 | L58: =(COUNTIFS(Codificacion!$I$2:$I$177,$A58,Codificacion!$J$2:$J$177,"Diligencia_debida_AML")>0)+(COUNTIFS(Codificacion!$I$2:$I$177,$A58,Codificacion!$J$2:$J$177,"Prevencion_fraude")>0)+(COUNTIFS(Codificacion!$I$2:$I$177,$A58,Codificacion!$J$2:$J$177,"Transparencia_consumidor")>0)+(COUNTIFS(Codificacion!$I$2:$I$177,$A58,Codificacion!$J$2:$J$177,"Acceso_inclusion")>0)+(COUNTIFS(Codificacion!$I$2:$I$177,$A58,Codificacion!$J$2:$J$177,"Proteccion_datos")>0)+(COUNTIFS(Codificacion!$I$2:$I$177,$A58,Codificacion!$J$2:$J$177,"Trazabilidad_IA")>0)+(COUNTIFS(Codificacion!$I$2:$I$177,$A58,Codificacion!$J$2:$J$177,"Resiliencia_operativa")>0)+(COUNTIFS(Codificacion!$I$2:$I$177,$A58,Codificacion!$J$2:$J$177,"Reclamaciones")>0) -> 5
A60: Datos exigidos por 2 o más familias | B60: =COUNTIF(K48:K58,">=2") -> 11
A61: Datos exigidos por 3 o más familias | B61: =COUNTIF(K48:K58,">=3") -> 8

Sheet Mapa_visibilidad
A1: Mapa de visibilidad regulatoria: obligaciones que observan cada estado del alta
A2: Cada celda cuenta las obligaciones de esa familia que se refieren al estado. Es un mapa descriptivo/binario: no distingue si la norma exige evidencia, cubre el supuesto condicionalmente o solo gobierna el dato. Para esa distinción, véase Mapa_ECG0. 0 = no se codificó referencia a ese estado. Versión en códigos S/R: Mapa_ensayo (Figura A1 del ensayo).
A4: Código | B4: Estado | C4: Cuenta básica | D4: AML | E4: Directrices EBA | F4: RGPD | G4: AI Act | H4: DORA | I4: eIDAS 2 | J4: Accesibilidad | K4: Atención al cliente ES | L4: Total obligaciones | M4: Familias que lo observan
A5: E0 | B5: Iniciado | C5: =COUNTIFS(Codificacion!$S$2:$S$177,1,Codificacion!$B$2:$B$177,"Cuenta básica") -> 2 | D5: =COUNTIFS(Codificacion!$S$2:$S$177,1,Codificacion!$B$2:$B$177,"AML") -> 8 | E5: =COUNTIFS(Codificacion!$S$2:$S$177,1,Codificacion!$B$2:$B$177,"Directrices EBA") -> 3 | F5: =COUNTIFS(Codificacion!$S$2:$S$177,1,Codificacion!$B$2:$B$177,"RGPD") -> 3 | G5: =COUNTIFS(Codificacion!$S$2:$S$177,1,Codificacion!$B$2:$B$177,"AI Act") -> 1 | H5: =COUNTIFS(Codificacion!$S$2:$S$177,1,Codificacion!$B$2:$B$177,"DORA") -> 0 | I5: =COUNTIFS(Codificacion!$S$2:$S$177,1,Codificacion!$B$2:$B$177,"eIDAS 2") -> 0 | J5: =COUNTIFS(Codificacion!$S$2:$S$177,1,Codificacion!$B$2:$B$177,"Accesibilidad") -> 2 | K5: =COUNTIFS(Codificacion!$S$2:$S$177,1,Codificacion!$B$2:$B$177,"Atención al cliente ES") -> 2 | L5: =SUM(C5:K5) -> 21 | M5: =COUNTIF(C5:K5,">0") -> 7
A6: E1 | B6: Abandono temprano | C6: =COUNTIFS(Codificacion!$T$2:$T$177,1,Codificacion!$B$2:$B$177,"Cuenta básica") -> 0 | D6: =COUNTIFS(Codificacion!$T$2:$T$177,1,Codificacion!$B$2:$B$177,"AML") -> 3 | E6: =COUNTIFS(Codificacion!$T$2:$T$177,1,Codificacion!$B$2:$B$177,"Directrices EBA") -> 0 | F6: =COUNTIFS(Codificacion!$T$2:$T$177,1,Codificacion!$B$2:$B$177,"RGPD") -> 0 | G6: =COUNTIFS(Codificacion!$T$2:$T$177,1,Codificacion!$B$2:$B$177,"AI Act") -> 0 | H6: =COUNTIFS(Codificacion!$T$2:$T$177,1,Codificacion!$B$2:$B$177,"DORA") -> 0 | I6: =COUNTIFS(Codificacion!$T$2:$T$177,1,Codificacion!$B$2:$B$177,"eIDAS 2") -> 0 | J6: =COUNTIFS(Codificacion!$T$2:$T$177,1,Codificacion!$B$2:$B$177,"Accesibilidad") -> 1 | K6: =COUNTIFS(Codificacion!$T$2:$T$177,1,Codificacion!$B$2:$B$177,"Atención al cliente ES") -> 0 | L6: =SUM(C6:K6) -> 4 | M6: =COUNTIF(C6:K6,">0") -> 2
A7: E2 | B7: Fallo técnico | C7: =COUNTIFS(Codificacion!$U$2:$U$177,1,Codificacion!$B$2:$B$177,"Cuenta básica") -> 0 | D7: =COUNTIFS(Codificacion!$U$2:$U$177,1,Codificacion!$B$2:$B$177,"AML") -> 1 | E7: =COUNTIFS(Codificacion!$U$2:$U$177,1,Codificacion!$B$2:$B$177,"Directrices EBA") -> 3 | F7: =COUNTIFS(Codificacion!$U$2:$U$177,1,Codificacion!$B$2:$B$177,"RGPD") -> 0 | G7: =COUNTIFS(Codificacion!$U$2:$U$177,1,Codificacion!$B$2:$B$177,"AI Act") -> 0 | H7: =COUNTIFS(Codificacion!$U$2:$U$177,1,Codificacion!$B$2:$B$177,"DORA") -> 8 | I7: =COUNTIFS(Codificacion!$U$2:$U$177,1,Codificacion!$B$2:$B$177,"eIDAS 2") -> 0 | J7: =COUNTIFS(Codificacion!$U$2:$U$177,1,Codificacion!$B$2:$B$177,"Accesibilidad") -> 0 | K7: =COUNTIFS(Codificacion!$U$2:$U$177,1,Codificacion!$B$2:$B$177,"Atención al cliente ES") -> 0 | L7: =SUM(C7:K7) -> 12 | M7: =COUNTIF(C7:K7,">0") -> 3
A8: E3 | B8: Documento no admitido | C8: =COUNTIFS(Codificacion!$V$2:$V$177,1,Codificacion!$B$2:$B$177,"Cuenta básica") -> 0 | D8: =COUNTIFS(Codificacion!$V$2:$V$177,1,Codificacion!$B$2:$B$177,"AML") -> 8 | E8: =COUNTIFS(Codificacion!$V$2:$V$177,1,Codificacion!$B$2:$B$177,"Directrices EBA") -> 10 | F8: =COUNTIFS(Codificacion!$V$2:$V$177,1,Codificacion!$B$2:$B$177,"RGPD") -> 0 | G8: =COUNTIFS(Codificacion!$V$2:$V$177,1,Codificacion!$B$2:$B$177,"AI Act") -> 0 | H8: =COUNTIFS(Codificacion!$V$2:$V$177,1,Codificacion!$B$2:$B$177,"DORA") -> 0 | I8: =COUNTIFS(Codificacion!$V$2:$V$177,1,Codificacion!$B$2:$B$177,"eIDAS 2") -> 0 | J8: =COUNTIFS(Codificacion!$V$2:$V$177,1,Codificacion!$B$2:$B$177,"Accesibilidad") -> 0 | K8: =COUNTIFS(Codificacion!$V$2:$V$177,1,Codificacion!$B$2:$B$177,"Atención al cliente ES") -> 0 | L8: =SUM(C8:K8) -> 18 | M8: =COUNTIF(C8:K8,">0") -> 2
A9: E4 | B9: Diligencia debida incompleta | C9: =COUNTIFS(Codificacion!$W$2:$W$177,1,Codificacion!$B$2:$B$177,"Cuenta básica") -> 3 | D9: =COUNTIFS(Codificacion!$W$2:$W$177,1,Codificacion!$B$2:$B$177,"AML") -> 20 | E9: =COUNTIFS(Codificacion!$W$2:$W$177,1,Codificacion!$B$2:$B$177,"Directrices EBA") -> 6 | F9: =COUNTIFS(Codificacion!$W$2:$W$177,1,Codificacion!$B$2:$B$177,"RGPD") -> 0 | G9: =COUNTIFS(Codificacion!$W$2:$W$177,1,Codificacion!$B$2:$B$177,"AI Act") -> 0 | H9: =COUNTIFS(Codificacion!$W$2:$W$177,1,Codificacion!$B$2:$B$177,"DORA") -> 0 | I9: =COUNTIFS(Codificacion!$W$2:$W$177,1,Codificacion!$B$2:$B$177,"eIDAS 2") -> 0 | J9: =COUNTIFS(Codificacion!$W$2:$W$177,1,Codificacion!$B$2:$B$177,"Accesibilidad") -> 0 | K9: =COUNTIFS(Codificacion!$W$2:$W$177,1,Codificacion!$B$2:$B$177,"Atención al cliente ES") -> 0 | L9: =SUM(C9:K9) -> 29 | M9: =COUNTIF(C9:K9,">0") -> 3
A10: E5 | B10: En revisión manual | C10: =COUNTIFS(Codificacion!$X$2:$X$177,1,Codificacion!$B$2:$B$177,"Cuenta básica") -> 0 | D10: =COUNTIFS(Codificacion!$X$2:$X$177,1,Codificacion!$B$2:$B$177,"AML") -> 13 | E10: =COUNTIFS(Codificacion!$X$2:$X$177,1,Codificacion!$B$2:$B$177,"Directrices EBA") -> 12 | F10: =COUNTIFS(Codificacion!$X$2:$X$177,1,Codificacion!$B$2:$B$177,"RGPD") -> 1 | G10: =COUNTIFS(Codificacion!$X$2:$X$177,1,Codificacion!$B$2:$B$177,"AI Act") -> 1 | H10: =COUNTIFS(Codificacion!$X$2:$X$177,1,Codificacion!$B$2:$B$177,"DORA") -> 0 | I10: =COUNTIFS(Codificacion!$X$2:$X$177,1,Codificacion!$B$2:$B$177,"eIDAS 2") -> 0 | J10: =COUNTIFS(Codificacion!$X$2:$X$177,1,Codificacion!$B$2:$B$177,"Accesibilidad") -> 0 | K10: =COUNTIFS(Codificacion!$X$2:$X$177,1,Codificacion!$B$2:$B$177,"Atención al cliente ES") -> 0 | L10: =SUM(C10:K10) -> 27 | M10: =COUNTIF(C10:K10,">0") -> 4
A11: E6 | B11: Revisión sin resolución | C11: =COUNTIFS(Codificacion!$Y$2:$Y$177,1,Codificacion!$B$2:$B$177,"Cuenta básica") -> 0 | D11: =COUNTIFS(Codificacion!$Y$2:$Y$177,1,Codificacion!$B$2:$B$177,"AML") -> 0 | E11: =COUNTIFS(Codificacion!$Y$2:$Y$177,1,Codificacion!$B$2:$B$177,"Directrices EBA") -> 0 | F11: =COUNTIFS(Codificacion!$Y$2:$Y$177,1,Codificacion!$B$2:$B$177,"RGPD") -> 0 | G11: =COUNTIFS(Codificacion!$Y$2:$Y$177,1,Codificacion!$B$2:$B$177,"AI Act") -> 0 | H11: =COUNTIFS(Codificacion!$Y$2:$Y$177,1,Codificacion!$B$2:$B$177,"DORA") -> 0 | I11: =COUNTIFS(Codificacion!$Y$2:$Y$177,1,Codificacion!$B$2:$B$177,"eIDAS 2") -> 0 | J11: =COUNTIFS(Codificacion!$Y$2:$Y$177,1,Codificacion!$B$2:$B$177,"Accesibilidad") -> 0 | K11: =COUNTIFS(Codificacion!$Y$2:$Y$177,1,Codificacion!$B$2:$B$177,"Atención al cliente ES") -> 0 | L11: =SUM(C11:K11) -> 0 | M11: =COUNTIF(C11:K11,">0") -> 0
A12: E7 | B12: Desistimiento tras requerimiento | C12: =COUNTIFS(Codificacion!$Z$2:$Z$177,1,Codificacion!$B$2:$B$177,"Cuenta básica") -> 1 | D12: =COUNTIFS(Codificacion!$Z$2:$Z$177,1,Codificacion!$B$2:$B$177,"AML") -> 7 | E12: =COUNTIFS(Codificacion!$Z$2:$Z$177,1,Codificacion!$B$2:$B$177,"Directrices EBA") -> 0 | F12: =COUNTIFS(Codificacion!$Z$2:$Z$177,1,Codificacion!$B$2:$B$177,"RGPD") -> 0 | G12: =COUNTIFS(Codificacion!$Z$2:$Z$177,1,Codificacion!$B$2:$B$177,"AI Act") -> 0 | H12: =COUNTIFS(Codificacion!$Z$2:$Z$177,1,Codificacion!$B$2:$B$177,"DORA") -> 0 | I12: =COUNTIFS(Codificacion!$Z$2:$Z$177,1,Codificacion!$B$2:$B$177,"eIDAS 2") -> 0 | J12: =COUNTIFS(Codificacion!$Z$2:$Z$177,1,Codificacion!$B$2:$B$177,"Accesibilidad") -> 0 | K12: =COUNTIFS(Codificacion!$Z$2:$Z$177,1,Codificacion!$B$2:$B$177,"Atención al cliente ES") -> 0 | L12: =SUM(C12:K12) -> 8 | M12: =COUNTIF(C12:K12,">0") -> 2
A13: E8 | B13: Denegación formal | C13: =COUNTIFS(Codificacion!$AA$2:$AA$177,1,Codificacion!$B$2:$B$177,"Cuenta básica") -> 16 | D13: =COUNTIFS(Codificacion!$AA$2:$AA$177,1,Codificacion!$B$2:$B$177,"AML") -> 11 | E13: =COUNTIFS(Codificacion!$AA$2:$AA$177,1,Codificacion!$B$2:$B$177,"Directrices EBA") -> 7 | F13: =COUNTIFS(Codificacion!$AA$2:$AA$177,1,Codificacion!$B$2:$B$177,"RGPD") -> 2 | G13: =COUNTIFS(Codificacion!$AA$2:$AA$177,1,Codificacion!$B$2:$B$177,"AI Act") -> 2 | H13: =COUNTIFS(Codificacion!$AA$2:$AA$177,1,Codificacion!$B$2:$B$177,"DORA") -> 0 | I13: =COUNTIFS(Codificacion!$AA$2:$AA$177,1,Codificacion!$B$2:$B$177,"eIDAS 2") -> 0 | J13: =COUNTIFS(Codificacion!$AA$2:$AA$177,1,Codificacion!$B$2:$B$177,"Accesibilidad") -> 0 | K13: =COUNTIFS(Codificacion!$AA$2:$AA$177,1,Codificacion!$B$2:$B$177,"Atención al cliente ES") -> 9 | L13: =SUM(C13:K13) -> 47 | M13: =COUNTIF(C13:K13,">0") -> 6
A14: E9 | B14: Alta completada | C14: =COUNTIFS(Codificacion!$AB$2:$AB$177,1,Codificacion!$B$2:$B$177,"Cuenta básica") -> 6 | D14: =COUNTIFS(Codificacion!$AB$2:$AB$177,1,Codificacion!$B$2:$B$177,"AML") -> 19 | E14: =COUNTIFS(Codificacion!$AB$2:$AB$177,1,Codificacion!$B$2:$B$177,"Directrices EBA") -> 6 | F14: =COUNTIFS(Codificacion!$AB$2:$AB$177,1,Codificacion!$B$2:$B$177,"RGPD") -> 0 | G14: =COUNTIFS(Codificacion!$AB$2:$AB$177,1,Codificacion!$B$2:$B$177,"AI Act") -> 0 | H14: =COUNTIFS(Codificacion!$AB$2:$AB$177,1,Codificacion!$B$2:$B$177,"DORA") -> 0 | I14: =COUNTIFS(Codificacion!$AB$2:$AB$177,1,Codificacion!$B$2:$B$177,"eIDAS 2") -> 0 | J14: =COUNTIFS(Codificacion!$AB$2:$AB$177,1,Codificacion!$B$2:$B$177,"Accesibilidad") -> 0 | K14: =COUNTIFS(Codificacion!$AB$2:$AB$177,1,Codificacion!$B$2:$B$177,"Atención al cliente ES") -> 2 | L14: =SUM(C14:K14) -> 33 | M14: =COUNTIF(C14:K14,">0") -> 4
A15: TR | B15: Transversal | C15: =COUNTIFS(Codificacion!$AC$2:$AC$177,1,Codificacion!$B$2:$B$177,"Cuenta básica") -> 6 | D15: =COUNTIFS(Codificacion!$AC$2:$AC$177,1,Codificacion!$B$2:$B$177,"AML") -> 9 | E15: =COUNTIFS(Codificacion!$AC$2:$AC$177,1,Codificacion!$B$2:$B$177,"Directrices EBA") -> 11 | F15: =COUNTIFS(Codificacion!$AC$2:$AC$177,1,Codificacion!$B$2:$B$177,"RGPD") -> 9 | G15: =COUNTIFS(Codificacion!$AC$2:$AC$177,1,Codificacion!$B$2:$B$177,"AI Act") -> 14 | H15: =COUNTIFS(Codificacion!$AC$2:$AC$177,1,Codificacion!$B$2:$B$177,"DORA") -> 2 | I15: =COUNTIFS(Codificacion!$AC$2:$AC$177,1,Codificacion!$B$2:$B$177,"eIDAS 2") -> 2 | J15: =COUNTIFS(Codificacion!$AC$2:$AC$177,1,Codificacion!$B$2:$B$177,"Accesibilidad") -> 14 | K15: =COUNTIFS(Codificacion!$AC$2:$AC$177,1,Codificacion!$B$2:$B$177,"Atención al cliente ES") -> 3 | L15: =SUM(C15:K15) -> 70 | M15: =COUNTIF(C15:K15,">0") -> 9
A17: Lectura
